Workbook
Name CAJA_DE_CAPTACION: #REF!
Name LIN_DISTR_ELECT.: '[1]PRES 1'!#REF!
Name SUBEST_ELECTR: '[1]PRES 1'!#REF!

Sheet DATOS
C1: ESTUDIO FINANCIERO
C3: DATOS ADICIONALES
C5: Inflación | D5: 0.09 | E5: Anual
C6: Incremento salarial | D6: 0.12 | E6: Anual
C7: Incremento volumen | D7: 0.03 | E7: cada 3 meses durante el primer año
C8: Incremento precio unitario de venta | D8: 0.09 | E8: A partir del segundo semestre del primer año y durante los sig años
C10: Depreciación en línea recta | E10: LISR
C12: Amortización de la deuda de acuerdo a la
C13: dependencia que otorgará el financiamiento

Sheet CRONOGRAMA DE ACTIVIDADES
A1: CRONOGRAMA DE ACTIVIDADES
A3: PROYECTO:
A4: SOCIEDAD
A5: BENEFICIARIOS:
A7: CRONOGRAMA DE ACTIVIDADES
C8: MES
A9: CONCEPTO | C9: 1 | D9: 2 | E9: 3 | F9: 4 | G9: 5 | H9: 6 | I9: 7 | J9: 8 | K9: 9 | L9: 10 | M9: 11 | N9: 12
A51: CRONOGRAMA DE ACTIVIDADES SEGUNDO AÑO
B53: CONCEPTO | C53: 1 | D53: 2 | E53: 3 | F53: 4 | G53: 5 | H53: 6 | I53: 7 | J53: 8 | K53: 9 | L53: 10 | M53: 11 | N53: 12
A68: CRONOGRAMA DE ACTIVIDADES TERCER AÑO
B70: CONCEPTO | C70: 1 | D70: 2 | E70: 3 | F70: 4 | G70: 5 | H70: 6 | I70: 7 | J70: 8 | K70: 9 | L70: 10 | M70: 11 | N70: 12
A85: CRONOGRAMA DE ACTIVIDADES CUARTO AÑO
B87: CONCEPTO | C87: 1 | D87: 2 | E87: 3 | F87: 4 | G87: 5 | H87: 6 | I87: 7 | J87: 8 | K87: 9 | L87: 10 | M87: 11 | N87: 12

Sheet ESTRUCTURA FINANCIERA
A1: ESTUDIO FINANCIERO
A3: ESTRUCTURA FINANCIERA
A5: PROYECTO: Las Amarguitas Fabrica de Cervezas y Destilados
A6: SOCIEDAD RESPONSABILIDAD LIMITADA
A7: BENEFICIARIOS: PABLO PUIG TRESS, HUGO PUIG TRESS.
A9: DESGLOSE DE INVERSION PARA UN AÑO
A10: CONCEPTO | B10: UNIDAD DE | C10: CANTIDAD | D10: PRECIO | E10: COSTO | F10: APORTACION | J10: Monto total | K10: $ SE | L10: % | M10: $ GRUPO | N10: % | O10: TOTAL
B11: MEDIDA | D11: UNITARIO | E11: TOTAL | F11: DEPENDENCIA | G11: GRUPO | I11: Capital de Trabajo | J11: 28600 | K11: 0 | L11: 0 | M11: =J11 -> 28600 | N11: 1 | O11: 1
A12: CAPITAL DE TRABAJO | I12: Inversión fija | J12: 759000 | K12: 759000 | L12: 1 | N12: 0 | O12: 1
A13: MALTA BASE | B13: KG | C13: 120 | D13: =E13/C13 -> 50 | E13: 6000 | F13: 0 | G13: =E13 -> 6000 | I13: Inversión diferida | J13: 40000 | K13: 40000 | L13: 1 | N13: 0 | O13: 1
A14: MALTAS ESPECIALES | B14: KG | C14: 10 | D14: =E14/C14 -> 60 | E14: 600 | F14: 0 | G14: =E14 -> 600
A15: LUPULO | B15: KG | C15: 2 | D15: =E15/C15 -> 800 | E15: 1600 | F15: 0 | G15: =E15 -> 1600 | K15: =SUM(K11:K13) -> 799000 | M15: =SUM(M11:M13) -> 28600
A16: LEVADURA | B16: KG | C16: 1 | D16: =E16/C16 -> 5000 | E16: 5000 | F16: 0 | G16: =E16 -> 5000
A17: AGUA | B17: LITROS | C17: 500 | D17: =E17/C17 -> 5 | E17: 2500 | F17: 0 | G17: =E17 -> 2500
A18: ENVASES | B18: PZ | C18: 1000 | D18: =E18/C18 -> 12.5 | E18: 12500 | F18: 0 | G18: =E18 -> 12500
A19: CLARIFICANTE | B19: KG | C19: 1 | D19: =E19/C19 -> 400 | E19: 400 | F19: 0 | G19: =E19 -> 400
A21: INVERSION FIJA
A22: Plataforma y Escalera de Operación | B22: Pz | C22: 1 | D22: 50000 | E22: =D22*C22 -> 50000 | F22: =E22 -> 50000 | G22: 0
A23: Mash Tun | B23: Pz | C23: 1 | D23: 169000 | E23: =D23*C23 -> 169000 | F23: =E23 -> 169000 | G23: 0
A24: Lauter Tun | B24: Pz | C24: 1 | D24: 220000 | E24: =D24*C24 -> 220000 | F24: =E24 -> 220000 | G24: 0
A25: Kettle | B25: Pz | C25: 1 | D25: 50000 | E25: =D25*C25 -> 50000 | F25: =E25 -> 50000 | G25: 0
A26: Tanque con Agitador | B26: Pz | C26: 1 | D26: 125000 | E26: =D26*C26 -> 125000 | F26: =E26 -> 125000 | G26: 0
A27: Tanque de Agua | B27: Pz | C27: 1 | D27: 95000 | E27: =D27*C27 -> 95000 | F27: =E27 -> 95000 | G27: 0
A28: Intercambiador de Calor | B28: Pz | C28: 1 | D28: 30000 | E28: =D28*C28 -> 30000 | F28: =E28 -> 30000 | G28: 0
A29: Sistema de Tuberías y Bomba Sanitaria | B29: Pz | C29: 1 | D29: 20000 | E29: =D29*C29 -> 20000 | F29: =E29 -> 20000 | G29: 0
A30: Subtotal | E30: =SUM(E12:E29) -> 787600 | F30: =SUM(F22:F29) -> 759000 | G30: =SUM(G13:G28) -> 28600
A31: INVERSION DIFERIDA
A34: CAPACITACIÓN | B34: servicio | C34: 1 | D34: 40000 | E34: 40000 | F34: 40000 | G34: 0
A36: TOTAL | E36: =E34+E30 -> 827600 | F36: =F34+F30 -> 799000 | G36: =+G34+G30 -> 28600
A37: PORCENTAJE | E37: =+E36/E36 -> 1 | F37: =+F36/E36 -> 0.96544224 | G37: =G36/E36 -> 0.034557757
A42: NOTAS:

Sheet CUADRO DE EGRESOS E INGRESOS
A1: ESTRUCTURA DE INGRESOS Y EGERESOS
A3: SITUACION FINANCIERA ACTUAL Y PROYECTADA
A5: PROYECTO:
A6: SOCIEDAD
A7: BENEFICIARIOS:
B9: FLUJO DE I N G R E S O S Y E G R E S O S
A10: PRIMER AÑO DE INVERSIÓN
A11: C O N C E P T O | C11: 1 MES | D11: 2 MES | E11: 3 MES | F11: 4 MES | G11: 5 MES | H11: 6 MES | I11: 7 MES | J11: 8 MES | K11: 9 MES | L11: 10 MES | M11: 11 MES | N11: 12 MES | O11: TOTAL
A12: TOTAL DE INGRESOS | Q12: CALCULO DE UTILIDADES
A13: VENTAS | C13: =INGRESOS!B17 -> 291523.05 | D13: =INGRESOS!C17 -> 291523.05 | E13: =INGRESOS!D17 -> 291523.05 | F13: =INGRESOS!E17 -> 291523.05 | G13: =INGRESOS!F17 -> 291523.05 | H13: =INGRESOS!G17 -> 291523.05 | I13: =INGRESOS!H17 -> 317760.12 | J13: =INGRESOS!I17 -> 317760.12 | ... N13: =INGRESOS!M17 -> 317760.12 | O13: =SUM(C13:N13) -> 3655699 | Q13: =O13-O18 -> 1521321.2
A14: TOTAL DE EGRESOS | Q14: =Q13-25000 -> 1496321.2
A15: VARIABLE | C15: =COSTOS!B29 -> 144198.13 | D15: =COSTOS!C29 -> 144198.13 | E15: =COSTOS!D29 -> 144198.13 | F15: =COSTOS!E29 -> 144198.13 | G15: =COSTOS!F29 -> 144198.13 | H15: =COSTOS!G29 -> 144198.13 | I15: =COSTOS!H29 -> 144198.13 | J15: =COSTOS!I29 -> 144198.13 | ... N15: =COSTOS!M29 -> 144198.13 | O15: =SUM(C15:N15) -> 1730377.5 | Q15: =Q14*0.1 -> 149632.12
A16: FIJOS | C16: =COSTOS!B33 -> 33666.693 | D16: =COSTOS!C33 -> 33666.693 | E16: =COSTOS!D33 -> 33666.693 | F16: =COSTOS!E33 -> 33666.693 | G16: =COSTOS!F33 -> 33666.693 | H16: =COSTOS!G33 -> 33666.693 | I16: =COSTOS!H33 -> 33666.693 | J16: =COSTOS!I33 -> 33666.693 | ... N16: =COSTOS!M33 -> 33666.693 | O16: =SUM(C16:N16) -> 404000.32 | Q16: =Q14*0.3 -> 448896.37
A17: SALDO | C17: =SUM(C15:C16) -> 177864.82 | D17: =SUM(D15:D16) -> 177864.82 | E17: =SUM(E15:E16) -> 177864.82 | F17: =SUM(F15:F16) -> 177864.82 | G17: =SUM(G15:G16) -> 177864.82 | H17: =SUM(H15:H16) -> 177864.82 | I17: =SUM(I15:I16) -> 177864.82 | J17: =SUM(J15:J16) -> 177864.82 | ... N17: =SUM(N15:N16) -> 177864.82 | O17: =SUM(C17:N17) -> 2134377.8 | Q17: =Q15+Q16 -> 598528.49
A18: SALDO ACUMULADO | C18: =+C17 -> 177864.82 | D18: =+D17+C18 -> 355729.64 | E18: =+E17+D18 -> 533594.46 | F18: =+F17+E18 -> 711459.27 | G18: =+G17+F18 -> 889324.09 | H18: =+H17+G18 -> 1067188.9 | I18: =+I17+H18 -> 1245053.7 | J18: =+J17+I18 -> 1422918.5 | K18: =+K17+J18 -> 1600783.4 | ... N18: =+N17+M18 -> 2134377.8 | O18: =+N18 -> 2134377.8 | Q18: =Q14-Q17 -> 897792.73
A22: PROYECCION FINANCIERA ANUAL
A24: SEGUNDO AÑO DE INVERSIÓN
A25: C O N C E P T O | C25: 1 MES | D25: 2 MES | E25: 3 MES | F25: 4 MES | G25: 5 MES | H25: 6 MES | I25: 7 MES | J25: 8 MES | K25: 9 MES | L25: 10 MES | M25: 11 MES | N25: 12 MES | O25: TOTAL
A26: TOTAL DE INGRESOS | Q26: CALCULO DE UTILIDADES
A27: VENTAS | C27: =INGRESOS!B29 -> 346358.54 | D27: =INGRESOS!C29 -> 346358.54 | E27: =INGRESOS!D29 -> 346358.54 | F27: =INGRESOS!E29 -> 346358.54 | G27: =INGRESOS!F29 -> 346358.54 | H27: =INGRESOS!G29 -> 346358.54 | I27: =INGRESOS!H29 -> 346358.54 | J27: =INGRESOS!I29 -> 346358.54 | ... N27: =INGRESOS!M29 -> 346358.54 | O27: =SUM(C27:N27) -> 4156302.4 | Q27: =O27-O32 -> 2008399.8
A28: EGRESOS | Q28: =Q27-25000 -> 1983399.8
A29: VARIABLE | C29: =COSTOS!B44 -> 145154.69 | D29: =COSTOS!C44 -> 145154.69 | E29: =COSTOS!D44 -> 145154.69 | F29: =COSTOS!E44 -> 145154.69 | G29: =COSTOS!F44 -> 145154.69 | H29: =COSTOS!G44 -> 145154.69 | I29: =COSTOS!H44 -> 145154.69 | J29: =COSTOS!I44 -> 145154.69 | ... N29: =COSTOS!M44 -> 145154.69 | O29: =SUM(C29:N29) -> 1741856.3 | Q29: =Q28*0.1 -> 198339.98
A30: FIJOS | C30: =COSTOS!B48 -> 33837.194 | D30: =COSTOS!C48 -> 33837.194 | E30: =COSTOS!D48 -> 33837.194 | F30: =COSTOS!E48 -> 33837.194 | G30: =COSTOS!F48 -> 33837.194 | H30: =COSTOS!G48 -> 33837.194 | I30: =COSTOS!H48 -> 33837.194 | J30: =COSTOS!I48 -> 33837.194 | ... N30: =COSTOS!M48 -> 33837.194 | O30: =SUM(C30:N30) -> 406046.32 | Q30: =Q28*0.3 -> 595019.95
A31: SALDO | C31: =C29+C30 -> 178991.88 | D31: =D29+D30 -> 178991.88 | E31: =E29+E30 -> 178991.88 | F31: =F29+F30 -> 178991.88 | G31: =G29+G30 -> 178991.88 | H31: =H29+H30 -> 178991.88 | I31: =I29+I30 -> 178991.88 | J31: =J29+J30 -> 178991.88 | ... N31: =N29+N30 -> 178991.88 | O31: =SUM(C31:N31) -> 2147902.6 | Q31: =Q29+Q30 -> 793359.94
A32: SALDO ACUMULADO | C32: =+C31 -> 178991.88 | D32: =+D31+C32 -> 357983.76 | E32: =+E31+D32 -> 536975.65 | F32: =+F31+E32 -> 715967.53 | G32: =+G31+F32 -> 894959.41 | H32: =+H31+G32 -> 1073951.3 | I32: =+I31+H32 -> 1252943.2 | J32: =+J31+I32 -> 1431935.1 | K32: =+K31+J32 -> 1610926.9 | ... N32: =+N31+M32 -> 2147902.6 | O32: =+N32 -> 2147902.6 | Q32: =Q28-Q31 -> 1190039.9
A37: TERCER AÑO DE INVERSIÓN
A38: C O N C E P T O | C38: 1 MES | D38: 2 MES | E38: 3 MES | F38: 4 MES | G38: 5 MES | H38: 6 MES | I38: 7 MES | J38: 8 MES | K38: 9 MES | L38: 10 MES | M38: 11 MES | N38: 12 MES | O38: TOTAL
A39: TOTAL DE INGRESOS | Q39: CALCULO DE UTILIDADES
A40: VENTAS | C40: =INGRESOS!B41 -> 377530.8 | D40: =INGRESOS!C41 -> 377530.8 | E40: =INGRESOS!D41 -> 377530.8 | F40: =INGRESOS!E41 -> 377530.8 | G40: =INGRESOS!F41 -> 377530.8 | H40: =INGRESOS!G41 -> 377530.8 | I40: =INGRESOS!H41 -> 377530.8 | J40: =INGRESOS!I41 -> 377530.8 | ... N40: =INGRESOS!M41 -> 377530.8 | O40: =SUM(C40:N40) -> 4530369.6 | Q40: =O40-O45 -> 2368830.7
A41: EGRESOS | Q41: =Q40-25000 -> 2343830.7
A42: VARIABLE | C42: =COSTOS!B57 -> 146118.84 | D42: =COSTOS!C57 -> 146118.84 | E42: =COSTOS!D57 -> 146118.84 | F42: =COSTOS!E57 -> 146118.84 | G42: =COSTOS!F57 -> 146118.84 | H42: =COSTOS!G57 -> 146118.84 | I42: =COSTOS!H57 -> 146118.84 | J42: =COSTOS!I57 -> 146118.84 | ... N42: =COSTOS!M57 -> 146118.84 | O42: =SUM(C42:N42) -> 1753426.1 | Q42: =Q41*0.1 -> 234383.07
A43: FIJOS | C43: =COSTOS!B61 -> 34009.399 | D43: =COSTOS!C61 -> 34009.399 | E43: =COSTOS!D61 -> 34009.399 | F43: =COSTOS!E61 -> 34009.399 | G43: =COSTOS!F61 -> 34009.399 | H43: =COSTOS!G61 -> 34009.399 | I43: =COSTOS!H61 -> 34009.399 | J43: =COSTOS!I61 -> 34009.399 | ... N43: =COSTOS!M61 -> 34009.399 | O43: =SUM(C43:N43) -> 408112.79 | Q43: =Q41*0.3 -> 703149.22
A44: SALDO | C44: =C42+C43 -> 180128.24 | D44: =D42+D43 -> 180128.24 | E44: =E42+E43 -> 180128.24 | F44: =F42+F43 -> 180128.24 | G44: =G42+G43 -> 180128.24 | H44: =H42+H43 -> 180128.24 | I44: =I42+I43 -> 180128.24 | J44: =J42+J43 -> 180128.24 | ... N44: =N42+N43 -> 180128.24 | O44: =SUM(C44:N44) -> 2161538.9 | Q44: =Q42+Q43 -> 937532.29
A45: SALDO ACUMULADO | C45: =+C44 -> 180128.24 | D45: =+D44+C45 -> 360256.49 | E45: =+E44+D45 -> 540384.73 | F45: =+F44+E45 -> 720512.97 | G45: =+G44+F45 -> 900641.21 | H45: =+H44+G45 -> 1080769.5 | I45: =+I44+H45 -> 1260897.7 | J45: =+J44+I45 -> 1441025.9 | K45: =+K44+J45 -> 1621154.2 | ... N45: =+N44+M45 -> 2161538.9 | O45: =+N45 -> 2161538.9 | Q45: =Q41-Q44 -> 1406298.4
A48: CUARTO AÑO DE INVERSIÓN
A49: C O N C E P T O | C49: 1 MES | D49: 2 MES | E49: 3 MES | F49: 4 MES | G49: 5 MES | H49: 6 MES | I49: 7 MES | J49: 8 MES | K49: 9 MES | L49: 10 MES | M49: 11 MES | N49: 12 MES | O49: TOTAL
A50: TOTAL DE INGRESOS | Q50: CALCULO DE UTILIDADES
A51: VENTAS | C51: =INGRESOS!B53 -> 411508.58 | D51: =INGRESOS!C53 -> 411508.58 | E51: =INGRESOS!D53 -> 411508.58 | F51: =INGRESOS!E53 -> 411508.58 | G51: =INGRESOS!F53 -> 411508.58 | H51: =INGRESOS!G53 -> 411508.58 | I51: =INGRESOS!H53 -> 411508.58 | J51: =INGRESOS!I53 -> 411508.58 | ... N51: =INGRESOS!M53 -> 411508.58 | O51: =SUM(C51:N51) -> 4938102.9 | Q51: =O51-O56 -> 2764902.3
A52: EGRESOS | Q52: =Q51-25000 -> 2739902.3
A53: VARIABLE | C53: =COSTOS!B70 -> 147090.65 | D53: =COSTOS!C70 -> 147090.65 | E53: =COSTOS!D70 -> 147090.65 | F53: =COSTOS!E70 -> 147090.65 | G53: =COSTOS!F70 -> 147090.65 | H53: =COSTOS!G70 -> 147090.65 | I53: =COSTOS!H70 -> 147090.65 | J53: =COSTOS!I70 -> 147090.65 | ... N53: =COSTOS!M70 -> 147090.65 | O53: =SUM(C53:N53) -> 1765087.8 | Q53: =Q52*0.1 -> 273990.23
A54: FIJOS | C54: =COSTOS!B61 -> 34009.399 | D54: =COSTOS!C61 -> 34009.399 | E54: =COSTOS!D61 -> 34009.399 | F54: =COSTOS!E61 -> 34009.399 | G54: =COSTOS!F61 -> 34009.399 | H54: =COSTOS!G61 -> 34009.399 | I54: =COSTOS!H61 -> 34009.399 | J54: =COSTOS!I61 -> 34009.399 | ... N54: =COSTOS!M61 -> 34009.399 | O54: =SUM(C54:N54) -> 408112.79 | Q54: =Q52*0.3 -> 821970.69
A55: SALDO | C55: =C53+C54 -> 181100.05 | D55: =D53+D54 -> 181100.05 | E55: =E53+E54 -> 181100.05 | F55: =F53+F54 -> 181100.05 | G55: =G53+G54 -> 181100.05 | H55: =H53+H54 -> 181100.05 | I55: =I53+I54 -> 181100.05 | J55: =J53+J54 -> 181100.05 | ... N55: =N53+N54 -> 181100.05 | O55: =SUM(C55:N55) -> 2173200.6 | Q55: =Q53+Q54 -> 1095960.9
A56: SALDO ACUMULADO | C56: =+C55 -> 181100.05 | D56: =+D55+C56 -> 362200.1 | E56: =+E55+D56 -> 543300.15 | F56: =+F55+E56 -> 724400.21 | G56: =+G55+F56 -> 905500.26 | H56: =+H55+G56 -> 1086600.3 | I56: =+I55+H56 -> 1267700.4 | J56: =+J55+I56 -> 1448800.4 | K56: =+K55+J56 -> 1629900.5 | ... N56: =+N55+M56 -> 2173200.6 | O56: =+N56 -> 2173200.6 | Q56: =Q52-Q55 -> 1643941.4
A60: QUINTO AÑO DE INVERSIÓN
A61: C O N C E P T O | C61: 1 MES | D61: 2 MES | E61: 3 MES | F61: 4 MES | G61: 5 MES | H61: 6 MES | I61: 7 MES | J61: 8 MES | K61: 9 MES | L61: 10 MES | M61: 11 MES | N61: 12 MES | O61: TOTAL
A62: TOTAL DE INGRESOS | Q62: CALCULO DE UTILIDADES
A63: VENTAS | C63: =INGRESOS!B65 -> 448544.35 | D63: =INGRESOS!C65 -> 448544.35 | E63: =INGRESOS!D65 -> 448544.35 | F63: =INGRESOS!E65 -> 448544.35 | G63: =INGRESOS!F65 -> 448544.35 | H63: =INGRESOS!G65 -> 448544.35 | I63: =INGRESOS!H65 -> 448544.35 | J63: =INGRESOS!I65 -> 448544.35 | ... N63: =INGRESOS!M65 -> 448544.35 | O63: =SUM(C63:N63) -> 5382532.2 | Q63: =O63-O68 -> 3193382.1
A64: EGRESOS | Q64: =Q63-25000 -> 3168382.1
A65: VARIABLE | C65: =COSTOS!B83 -> 148070.18 | D65: =COSTOS!C83 -> 148070.18 | E65: =COSTOS!D83 -> 148070.18 | F65: =COSTOS!E83 -> 148070.18 | G65: =COSTOS!F83 -> 148070.18 | H65: =COSTOS!G83 -> 148070.18 | I65: =COSTOS!H83 -> 148070.18 | J65: =COSTOS!I83 -> 148070.18 | ... N65: =COSTOS!M83 -> 148070.18 | O65: =SUM(C65:N65) -> 1776842.1 | Q65: =Q64*0.1 -> 316838.21
A66: FIJOS | C66: =COSTOS!B87 -> 34358.994 | D66: =COSTOS!C87 -> 34358.994 | E66: =COSTOS!D87 -> 34358.994 | F66: =COSTOS!E87 -> 34358.994 | G66: =COSTOS!F87 -> 34358.994 | H66: =COSTOS!G87 -> 34358.994 | I66: =COSTOS!H87 -> 34358.994 | J66: =COSTOS!I87 -> 34358.994 | ... N66: =COSTOS!M87 -> 34358.994 | O66: =SUM(C66:N66) -> 412307.93 | Q66: =Q64*0.3 -> 950514.64
A67: SALDO | C67: =C65+C66 -> 182429.17 | D67: =D65+D66 -> 182429.17 | E67: =E65+E66 -> 182429.17 | F67: =F65+F66 -> 182429.17 | G67: =G65+G66 -> 182429.17 | H67: =H65+H66 -> 182429.17 | I67: =I65+I66 -> 182429.17 | J67: =J65+J66 -> 182429.17 | ... N67: =N65+N66 -> 182429.17 | O67: =SUM(C67:N67) -> 2189150 | Q67: =Q65+Q66 -> 1267352.9
A68: SALDO ACUMULADO | C68: =+C67 -> 182429.17 | D68: =+D67+C68 -> 364858.34 | E68: =+E67+D68 -> 547287.51 | F68: =+F67+E68 -> 729716.68 | G68: =+G67+F68 -> 912145.85 | H68: =+H67+G68 -> 1094575 | I68: =+I67+H68 -> 1277004.2 | J68: =+J67+I68 -> 1459433.4 | K68: =+K67+J68 -> 1641862.5 | ... N68: =+N67+M68 -> 2189150 | O68: =+N68 -> 2189150 | Q68: =Q64-Q67 -> 1901029.3
A76: CAPACIDAD DE PAGO
A78: CONCEPTO | B78: PRMER AÑO | C78: SEGUNDO AÑO | D78: TERCER AÑO | E78: CUARTO AÑO | F78: QUINTO AÑO
A79: INGRESOS | B79: =O13 -> 3655699 | C79: =O27 -> 4156302.4 | D79: =O40 -> 4530369.6 | E79: =O51 -> 4938102.9 | F79: =O63 -> 5382532.2
A80: EGRESOS | B80: =O45 -> 2161538.9 | C80: =O32 -> 2147902.6 | D80: =O45 -> 2161538.9 | E80: =O56 -> 2173200.6 | F80: =O68 -> 2189150
A81: TOTAL | B81: =B79-B80 -> 1494160.1 | C81: =C79-C80 -> 2008399.8 | D81: =+D79-D80 -> 2368830.7 | E81: =+E79-E80 -> 2764902.3 | F81: =+F79-F80 -> 3193382.1

Sheet COSTOS
B2: COSTOS DE PRODUCCION AÑO 1 sin inversión
A3: VARIABLES | B3: 1 | C3: 2 | D3: 3 | E3: 4 | F3: 5 | G3: 6 | H3: 7 | I3: 8 | J3: 9 | K3: 10 | L3: 11 | M3: 12 | N3: TOTAL
A4: TOTAL VARIABLES | B4: =SUM(B5:B7) -> 91844.451 | C4: =SUM(C5:C7) -> 91844.451 | D4: =SUM(D5:D7) -> 91844.451 | E4: =SUM(E5:E7) -> 91844.451 | F4: =SUM(F5:F7) -> 91844.451 | G4: =SUM(G5:G7) -> 91844.451 | H4: =SUM(H5:H7) -> 91844.451 | I4: =SUM(I5:I7) -> 91844.451 | ... N4: =SUM(N5:N7) -> 1102133.4
A5: Materia prima | B5: ='M. DE CALCULO DE COSTOS VARIABL'!$G$26 -> 52882.5 | C5: ='M. DE CALCULO DE COSTOS VARIABL'!$G$26 -> 52882.5 | D5: ='M. DE CALCULO DE COSTOS VARIABL'!$G$26 -> 52882.5 | E5: ='M. DE CALCULO DE COSTOS VARIABL'!$G$26 -> 52882.5 | F5: ='M. DE CALCULO DE COSTOS VARIABL'!$G$26 -> 52882.5 | G5: ='M. DE CALCULO DE COSTOS VARIABL'!$G$26 -> 52882.5 | H5: ='M. DE CALCULO DE COSTOS VARIABL'!$G$26 -> 52882.5 | I5: ='M. DE CALCULO DE COSTOS VARIABL'!$G$26 -> 52882.5 | ... M5: ='M. DE CALCULO DE COSTOS VARIABL'!$G$26 -> 52882.5 | N5: =SUM(B5:M5) -> 634590
A6: Mano de obra directa | B6: ='M. DE CALCULO DE COSTOS VARIABL'!$D$27 -> 16729.14 | C6: ='M. DE CALCULO DE COSTOS VARIABL'!$D$27 -> 16729.14 | D6: ='M. DE CALCULO DE COSTOS VARIABL'!$D$27 -> 16729.14 | E6: ='M. DE CALCULO DE COSTOS VARIABL'!$D$27 -> 16729.14 | F6: ='M. DE CALCULO DE COSTOS VARIABL'!$D$27 -> 16729.14 | G6: ='M. DE CALCULO DE COSTOS VARIABL'!$D$27 -> 16729.14 | H6: ='M. DE CALCULO DE COSTOS VARIABL'!$D$27 -> 16729.14 | I6: ='M. DE CALCULO DE COSTOS VARIABL'!$D$27 -> 16729.14 | ... M6: ='M. DE CALCULO DE COSTOS VARIABL'!$D$27 -> 16729.14 | N6: =SUM(B6:M6) -> 200749.68
A7: Costos Indirectos de Fabricación | B7: ='M. DE CALCULO DE COSTOS VARIABL'!$E$42 -> 22232.811 | C7: ='M. DE CALCULO DE COSTOS VARIABL'!$E$42 -> 22232.811 | D7: ='M. DE CALCULO DE COSTOS VARIABL'!$E$42 -> 22232.811 | E7: ='M. DE CALCULO DE COSTOS VARIABL'!$E$42 -> 22232.811 | F7: ='M. DE CALCULO DE COSTOS VARIABL'!$E$42 -> 22232.811 | G7: ='M. DE CALCULO DE COSTOS VARIABL'!$E$42 -> 22232.811 | H7: ='M. DE CALCULO DE COSTOS VARIABL'!$E$42 -> 22232.811 | I7: ='M. DE CALCULO DE COSTOS VARIABL'!$E$42 -> 22232.811 | ... M7: ='M. DE CALCULO DE COSTOS VARIABL'!$E$42 -> 22232.811 | N7: =SUM(B7:M7) -> 266793.73
A8: TOTAL FIJOS | B8: =B9+B10 -> 33666.693 | C8: =SUM(C9:C10) -> 39716.726 | D8: =SUM(D9:D10) -> 33666.693 | E8: =SUM(E9:E10) -> 33666.693 | F8: =SUM(F9:F10) -> 33666.693 | G8: =SUM(G9:G10) -> 33666.693 | H8: =SUM(H9:H10) -> 33666.693 | I8: =SUM(I9:I10) -> 33666.693 | J8: =SUM(J9:J10) -> 33666.693 | ... M8: =SUM(M9:M10) -> 33666.693 | N8: =SUM(B8:M8) -> 410050.35
A9: Gastos de administración | B9: ='M. DE CALCULO DE GASTOS FIJOS'!F13 -> 17050.07 | C9: ='M. DE CALCULO DE GASTOS FIJOS'!G13 -> 17050.07 | D9: ='M. DE CALCULO DE GASTOS FIJOS'!H13 -> 17050.07 | E9: ='M. DE CALCULO DE GASTOS FIJOS'!I13 -> 17050.07 | F9: ='M. DE CALCULO DE GASTOS FIJOS'!J13 -> 17050.07 | G9: ='M. DE CALCULO DE GASTOS FIJOS'!K13 -> 17050.07 | H9: ='M. DE CALCULO DE GASTOS FIJOS'!L13 -> 17050.07 | I9: ='M. DE CALCULO DE GASTOS FIJOS'!M13 -> 17050.07 | ... M9: ='M. DE CALCULO DE GASTOS FIJOS'!Q13 -> 17050.07 | N9: =SUM(B9:M9) -> 204600.84
A10: Gastos de venta | B10: ='M. DE CALCULO DE GASTOS FIJOS'!F21 -> 16616.623 | C10: ='M. DE CALCULO DE GASTOS FIJOS'!G21 -> 22666.656 | D10: ='M. DE CALCULO DE GASTOS FIJOS'!H21 -> 16616.623 | E10: ='M. DE CALCULO DE GASTOS FIJOS'!I21 -> 16616.623 | F10: ='M. DE CALCULO DE GASTOS FIJOS'!J21 -> 16616.623 | G10: ='M. DE CALCULO DE GASTOS FIJOS'!K21 -> 16616.623 | H10: ='M. DE CALCULO DE GASTOS FIJOS'!L21 -> 16616.623 | I10: ='M. DE CALCULO DE GASTOS FIJOS'!M21 -> 16616.623 | ... M10: ='M. DE CALCULO DE GASTOS FIJOS'!Q21 -> 16616.623 | N10: =SUM(B10:M10) -> 205449.51
A11: TOTAL COSTO OPERACIÓN | B11: =+B8+B4 -> 125511.14 | C11: =+C8+C4 -> 131561.18 | D11: =+D8+D4 -> 125511.14 | E11: =+E8+E4 -> 125511.14 | F11: =+F8+F4 -> 125511.14 | G11: =+G8+G4 -> 125511.14 | H11: =+H8+H4 -> 125511.14 | I11: =+I8+I4 -> 125511.14 | ... N11: =+N8+N4 -> 1512183.8
B12: =B11/3000 -> 41.837048 | C12: =C11/3000 -> 43.853726 | D12: =D11/3000 -> 41.837048 | E12: =E11/3000 -> 41.837048 | F12: =F11/3000 -> 41.837048 | G12: =G11/3000 -> 41.837048 | H12: =H11/3000 -> 41.837048 | I12: =I11/3000 -> 41.837048 | ... M12: =M11/3000 -> 41.837048
J14: Antes de la inversión
A15: VARIABLES | B15: AÑO 0 | C15: AÑO 1 | D15: AÑO 2 | E15: AÑO3 | F15: AÑO 4 | G15: AÑO 5 | J15: Costos promedio por litro de cerveza | M15: =AVERAGE(B12:M12) -> 42.005104 | N15: =M15*1500 -> 63007.657 | P15: Costo promedio
A16: TOTAL VARIABLES | B16: =SUM(B17:B19) -> 1102133.4 | C16: =SUM(C17:C19) -> 1730377.5 | D16: {=N44:N51} -> 1741856.3 | E16: {=N57:N64} -> 1753426.1 | F16: {=N70:N77} -> 1765087.8 | G16: {=N83:N90} -> 1776842.1 | J16: Precio de venta | M16: 97.5 | N16: =M16*1500 -> 146250 | P16: 80
A17: Materia prima | B17: =N5 -> 634590 | C17: =N30 -> 1262834.1 | D17: 1272305.4 | E17: 1281847.6 | F17: 1291461.5 | G17: 1301147.5 | J17: Utilidad bruta por litro | M17: =M16-M15 -> 55.494896 | N17: =N16-N15 -> 83242.343 | P17: 90
A18: Mano de obra directa | B18: =N6 -> 200749.68 | C18: =N31 -> 200749.68 | D18: 202757.18 | E18: 204784.75 | F18: 206832.6 | G18: 208900.92 | J18: Después de la inversión | P18: 120
A19: Costos Indirectos de Fabricación | B19: =N7 -> 266793.73 | C19: =N32 -> 266793.73 | D19: 266793.73 | E19: 266793.73 | F19: 266793.73 | G19: 266793.73 | J19: Costos promedio por litro de cerveza | M19: =E41 -> 59.486561 | N19: =M19*2990 -> 177864.82 | P19: 100
A20: TOTAL FIJOS | B20: =N8 -> 410050.35 | C20: =N33 -> 404000.32 | D20: 406046.32 | E20: 408112.79 | F20: 410199.93 | G20: 412307.93 | J20: Precio de venta | M20: =97.5 -> 97.5 | N20: =M20*2990 -> 291525 | P20: =AVERAGE(P16:P19) -> 97.5
A21: Gastos de administración | B21: =N9 -> 204600.84 | C21: =N34 -> 204600.84 | D21: 206646.85 | E21: 208713.32 | F21: 210800.45 | G21: 212908.45 | J21: Utilidad bruta por litro | M21: =M20-M19 -> 38.013439 | N21: =N20-N19 -> 113660.18
A22: Gastos de venta | B22: =N10 -> 205449.51 | C22: =N35 -> 199399.48 | D22: 199399.48 | E22: 199399.48 | F22: 199399.48 | G22: 199399.48 | P22: Factor de aumento
A23: TOTAL COSTO OPERACIÓN | B23: =B16+B20 -> 1512183.8 | C23: =C16+C20 -> 2134377.8 | D23: 2147902.6 | E23: 2161538.9 | F23: 2175287.8 | G23: 2189150 | P23: 1.99
B27: COSTOS DE PRODUCCION AÑO 1
A28: VARIABLES | B28: 1 | C28: 2 | D28: 3 | E28: 4 | F28: 5 | G28: 6 | H28: 7 | I28: 8 | J28: 9 | K28: 10 | L28: 11 | M28: 12 | N28: TOTAL
A29: TOTAL VARIABLES | B29: =SUM(B30:B32) -> 144198.13 | C29: =SUM(C30:C32) -> 144198.13 | D29: =SUM(D30:D32) -> 144198.13 | E29: =SUM(E30:E32) -> 144198.13 | F29: =SUM(F30:F32) -> 144198.13 | G29: =SUM(G30:G32) -> 144198.13 | H29: =SUM(H30:H32) -> 144198.13 | I29: =SUM(I30:I32) -> 144198.13 | ... N29: =SUM(N30:N32) -> 1730377.5
A30: Materia prima | B30: ='M. DE CALCULO DE COSTOS VARIABL'!$G$26*$P$23 -> 105236.18 | C30: ='M. DE CALCULO DE COSTOS VARIABL'!$G$26*$P$23 -> 105236.18 | D30: ='M. DE CALCULO DE COSTOS VARIABL'!$G$26*$P$23 -> 105236.18 | E30: ='M. DE CALCULO DE COSTOS VARIABL'!$G$26*$P$23 -> 105236.18 | F30: ='M. DE CALCULO DE COSTOS VARIABL'!$G$26*$P$23 -> 105236.18 | G30: ='M. DE CALCULO DE COSTOS VARIABL'!$G$26*$P$23 -> 105236.18 | H30: ='M. DE CALCULO DE COSTOS VARIABL'!$G$26*$P$23 -> 105236.18 | I30: ='M. DE CALCULO DE COSTOS VARIABL'!$G$26*$P$23 -> 105236.18 | ... M30: ='M. DE CALCULO DE COSTOS VARIABL'!$G$26*$P$23 -> 105236.18 | N30: =SUM(B30:M30) -> 1262834.1
A31: Mano de obra directa | B31: =$B$6 -> 16729.14 | C31: =$B$6 -> 16729.14 | D31: =$B$6 -> 16729.14 | E31: =$B$6 -> 16729.14 | F31: =$B$6 -> 16729.14 | G31: =$B$6 -> 16729.14 | H31: =$B$6 -> 16729.14 | I31: =$B$6 -> 16729.14 | ... M31: =$B$6 -> 16729.14 | N31: =SUM(B31:M31) -> 200749.68
A32: Costos Indirectos de Fabricación | B32: ='M. DE CALCULO DE COSTOS VARIABL'!$F$42 -> 22232.811 | C32: ='M. DE CALCULO DE COSTOS VARIABL'!$F$42 -> 22232.811 | D32: ='M. DE CALCULO DE COSTOS VARIABL'!$F$42 -> 22232.811 | E32: ='M. DE CALCULO DE COSTOS VARIABL'!$F$42 -> 22232.811 | F32: ='M. DE CALCULO DE COSTOS VARIABL'!$F$42 -> 22232.811 | G32: ='M. DE CALCULO DE COSTOS VARIABL'!$F$42 -> 22232.811 | H32: ='M. DE CALCULO DE COSTOS VARIABL'!$F$42 -> 22232.811 | I32: ='M. DE CALCULO DE COSTOS VARIABL'!$F$42 -> 22232.811 | ... M32: ='M. DE CALCULO DE COSTOS VARIABL'!$F$42 -> 22232.811 | N32: =SUM(B32:M32) -> 266793.73
A33: TOTAL FIJOS | B33: =B34+B35 -> 33666.693 | C33: =SUM(C34:C35) -> 33666.693 | D33: =SUM(D34:D35) -> 33666.693 | E33: =SUM(E34:E35) -> 33666.693 | F33: =SUM(F34:F35) -> 33666.693 | G33: =SUM(G34:G35) -> 33666.693 | H33: =SUM(H34:H35) -> 33666.693 | I33: =SUM(I34:I35) -> 33666.693 | J33: =SUM(J34:J35) -> 33666.693 | ... M33: =SUM(M34:M35) -> 33666.693 | N33: =SUM(B33:M33) -> 404000.32
A34: Gastos de administración | B34: =$B$9 -> 17050.07 | C34: =$B$9 -> 17050.07 | D34: =$B$9 -> 17050.07 | E34: =$B$9 -> 17050.07 | F34: =$B$9 -> 17050.07 | G34: =$B$9 -> 17050.07 | H34: =$B$9 -> 17050.07 | I34: =$B$9 -> 17050.07 | ... M34: =$B$9 -> 17050.07 | N34: =SUM(B34:M34) -> 204600.84
A35: Gastos de venta | B35: =$B$10 -> 16616.623 | C35: =$B$10 -> 16616.623 | D35: =$B$10 -> 16616.623 | E35: =$B$10 -> 16616.623 | F35: =$B$10 -> 16616.623 | G35: =$B$10 -> 16616.623 | H35: =$B$10 -> 16616.623 | I35: =$B$10 -> 16616.623 | ... M35: =$B$10 -> 16616.623 | N35: =SUM(B35:M35) -> 199399.48
A36: TOTAL COSTO OPERACIÓN | B36: =+B33+B29 -> 177864.82 | C36: =+C33+C29 -> 177864.82 | D36: =+D33+D29 -> 177864.82 | E36: =+E33+E29 -> 177864.82 | F36: =+F33+F29 -> 177864.82 | G36: =+G33+G29 -> 177864.82 | H36: =+H33+H29 -> 177864.82 | I36: =+I33+I29 -> 177864.82 | ... N36: =+N33+N29 -> 2134377.8
B38: =B36/2990 -> 59.486561 | C38: =C36/2990 -> 59.486561 | D38: =D36/2990 -> 59.486561 | E38: =E36/2990 -> 59.486561 | F38: =F36/2990 -> 59.486561 | G38: =G36/2990 -> 59.486561 | H38: =H36/2990 -> 59.486561 | I38: =I36/2990 -> 59.486561 | ... M38: =M36/2990 -> 59.486561
E41: =AVERAGE(B38:M38) -> 59.486561
B42: COSTOS DE PRODUCCION AÑO 2
A43: VARIABLES | B43: 1 | C43: 2 | D43: 3 | E43: 4 | F43: 5 | G43: 6 | H43: 7 | I43: 8 | J43: 9 | K43: 10 | L43: 11 | M43: 12 | N43: TOTAL
A44: TOTAL VARIABLES | B44: =SUM(B45:B47) -> 145154.69 | C44: =SUM(C45:C47) -> 145154.69 | D44: =SUM(D45:D47) -> 145154.69 | E44: =SUM(E45:E47) -> 145154.69 | F44: =SUM(F45:F47) -> 145154.69 | G44: =SUM(G45:G47) -> 145154.69 | H44: =SUM(H45:H47) -> 145154.69 | I44: =SUM(I45:I47) -> 145154.69 | ... N44: =SUM(N45:N47) -> 1741856.3
A45: Materia prima | B45: =$B$30*1.0075 -> 106025.45 | C45: =$B$30*1.0075 -> 106025.45 | D45: =$B$30*1.0075 -> 106025.45 | E45: =$B$30*1.0075 -> 106025.45 | F45: =$B$30*1.0075 -> 106025.45 | G45: =$B$30*1.0075 -> 106025.45 | H45: =$B$30*1.0075 -> 106025.45 | I45: =$B$30*1.0075 -> 106025.45 | ... M45: =$B$30*1.0075 -> 106025.45 | N45: =SUM(B45:M45) -> 1272305.4
A46: Mano de obra directa | B46: =$B$6*1.01 -> 16896.431 | C46: =$B$6*1.01 -> 16896.431 | D46: =$B$6*1.01 -> 16896.431 | E46: =$B$6*1.01 -> 16896.431 | F46: =$B$6*1.01 -> 16896.431 | G46: =$B$6*1.01 -> 16896.431 | H46: =$B$6*1.01 -> 16896.431 | I46: =$B$6*1.01 -> 16896.431 | ... M46: =$B$6*1.01 -> 16896.431 | N46: =SUM(B46:M46) -> 202757.18
A47: Costos Indirectos de Fabricación | B47: ='M. DE CALCULO DE COSTOS VARIABL'!$F$42 -> 22232.811 | C47: ='M. DE CALCULO DE COSTOS VARIABL'!$F$42 -> 22232.811 | D47: ='M. DE CALCULO DE COSTOS VARIABL'!$F$42 -> 22232.811 | E47: ='M. DE CALCULO DE COSTOS VARIABL'!$F$42 -> 22232.811 | F47: ='M. DE CALCULO DE COSTOS VARIABL'!$F$42 -> 22232.811 | G47: ='M. DE CALCULO DE COSTOS VARIABL'!$F$42 -> 22232.811 | H47: ='M. DE CALCULO DE COSTOS VARIABL'!$F$42 -> 22232.811 | I47: ='M. DE CALCULO DE COSTOS VARIABL'!$F$42 -> 22232.811 | ... M47: ='M. DE CALCULO DE COSTOS VARIABL'!$F$42 -> 22232.811 | N47: =SUM(B47:M47) -> 266793.73
A48: TOTAL FIJOS | B48: =B49+B50 -> 33837.194 | C48: =SUM(C49:C50) -> 33837.194 | D48: =SUM(D49:D50) -> 33837.194 | E48: =SUM(E49:E50) -> 33837.194 | F48: =SUM(F49:F50) -> 33837.194 | G48: =SUM(G49:G50) -> 33837.194 | H48: =SUM(H49:H50) -> 33837.194 | I48: =SUM(I49:I50) -> 33837.194 | J48: =SUM(J49:J50) -> 33837.194 | ... M48: =SUM(M49:M50) -> 33837.194 | N48: =SUM(B48:M48) -> 406046.32
A49: Gastos de administración | B49: =$B$9*1.01 -> 17220.571 | C49: =$B$9*1.01 -> 17220.571 | D49: =$B$9*1.01 -> 17220.571 | E49: =$B$9*1.01 -> 17220.571 | F49: =$B$9*1.01 -> 17220.571 | G49: =$B$9*1.01 -> 17220.571 | H49: =$B$9*1.01 -> 17220.571 | I49: =$B$9*1.01 -> 17220.571 | ... M49: =$B$9*1.01 -> 17220.571 | N49: =SUM(B49:M49) -> 206646.85
A50: Gastos de venta | B50: =$B$10 -> 16616.623 | C50: =$B$10 -> 16616.623 | D50: =$B$10 -> 16616.623 | E50: =$B$10 -> 16616.623 | F50: =$B$10 -> 16616.623 | G50: =$B$10 -> 16616.623 | H50: =$B$10 -> 16616.623 | I50: =$B$10 -> 16616.623 | ... M50: =$B$10 -> 16616.623 | N50: =SUM(B50:M50) -> 199399.48
A51: TOTAL COSTO OPERACIÓN | B51: =+B48+B44 -> 178991.88 | C51: =+C48+C44 -> 178991.88 | D51: =+D48+D44 -> 178991.88 | E51: =+E48+E44 -> 178991.88 | F51: =+F48+F44 -> 178991.88 | G51: =+G48+G44 -> 178991.88 | H51: =+H48+H44 -> 178991.88 | I51: =+I48+I44 -> 178991.88 | ... N51: =+N48+N44 -> 2147902.6
B55: COSTOS DE PRODUCCION AÑO 3
A56: VARIABLES | B56: 1 | C56: 2 | D56: 3 | E56: 4 | F56: 5 | G56: 6 | H56: 7 | I56: 8 | J56: 9 | K56: 10 | L56: 11 | M56: 12 | N56: TOTAL
A57: TOTAL VARIABLES | B57: =SUM(B58:B60) -> 146118.84 | C57: =SUM(C58:C60) -> 146118.84 | D57: =SUM(D58:D60) -> 146118.84 | E57: =SUM(E58:E60) -> 146118.84 | F57: =SUM(F58:F60) -> 146118.84 | G57: =SUM(G58:G60) -> 146118.84 | H57: =SUM(H58:H60) -> 146118.84 | I57: =SUM(I58:I60) -> 146118.84 | ... N57: =SUM(N58:N60) -> 1753426.1
A58: Materia prima | B58: =$B$45*1.0075 -> 106820.64 | C58: =$B$45*1.0075 -> 106820.64 | D58: =$B$45*1.0075 -> 106820.64 | E58: =$B$45*1.0075 -> 106820.64 | F58: =$B$45*1.0075 -> 106820.64 | G58: =$B$45*1.0075 -> 106820.64 | H58: =$B$45*1.0075 -> 106820.64 | I58: =$B$45*1.0075 -> 106820.64 | ... M58: =$B$45*1.0075 -> 106820.64 | N58: =SUM(B58:M58) -> 1281847.6
A59: Mano de obra directa | B59: =$B$46*1.01 -> 17065.396 | C59: =$B$46*1.01 -> 17065.396 | D59: =$B$46*1.01 -> 17065.396 | E59: =$B$46*1.01 -> 17065.396 | F59: =$B$46*1.01 -> 17065.396 | G59: =$B$46*1.01 -> 17065.396 | H59: =$B$46*1.01 -> 17065.396 | I59: =$B$46*1.01 -> 17065.396 | ... M59: =$B$46*1.01 -> 17065.396 | N59: =SUM(B59:M59) -> 204784.75
A60: Costos Indirectos de Fabricación | B60: ='M. DE CALCULO DE COSTOS VARIABL'!$F$42 -> 22232.811 | C60: ='M. DE CALCULO DE COSTOS VARIABL'!$F$42 -> 22232.811 | D60: ='M. DE CALCULO DE COSTOS VARIABL'!$F$42 -> 22232.811 | E60: ='M. DE CALCULO DE COSTOS VARIABL'!$F$42 -> 22232.811 | F60: ='M. DE CALCULO DE COSTOS VARIABL'!$F$42 -> 22232.811 | G60: ='M. DE CALCULO DE COSTOS VARIABL'!$F$42 -> 22232.811 | H60: ='M. DE CALCULO DE COSTOS VARIABL'!$F$42 -> 22232.811 | I60: ='M. DE CALCULO DE COSTOS VARIABL'!$F$42 -> 22232.811 | ... M60: ='M. DE CALCULO DE COSTOS VARIABL'!$F$42 -> 22232.811 | N60: =SUM(B60:M60) -> 266793.73
A61: TOTAL FIJOS | B61: =B62+B63 -> 34009.399 | C61: =SUM(C62:C63) -> 34009.399 | D61: =SUM(D62:D63) -> 34009.399 | E61: =SUM(E62:E63) -> 34009.399 | F61: =SUM(F62:F63) -> 34009.399 | G61: =SUM(G62:G63) -> 34009.399 | H61: =SUM(H62:H63) -> 34009.399 | I61: =SUM(I62:I63) -> 34009.399 | J61: =SUM(J62:J63) -> 34009.399 | ... M61: =SUM(M62:M63) -> 34009.399 | N61: =SUM(B61:M61) -> 408112.79
A62: Gastos de administración | B62: =$B$49*1.01 -> 17392.776 | C62: =$B$49*1.01 -> 17392.776 | D62: =$B$49*1.01 -> 17392.776 | E62: =$B$49*1.01 -> 17392.776 | F62: =$B$49*1.01 -> 17392.776 | G62: =$B$49*1.01 -> 17392.776 | H62: =$B$49*1.01 -> 17392.776 | I62: =$B$49*1.01 -> 17392.776 | ... M62: =$B$49*1.01 -> 17392.776 | N62: =SUM(B62:M62) -> 208713.32
A63: Gastos de venta | B63: =$B$10 -> 16616.623 | C63: =$B$10 -> 16616.623 | D63: =$B$10 -> 16616.623 | E63: =$B$10 -> 16616.623 | F63: =$B$10 -> 16616.623 | G63: =$B$10 -> 16616.623 | H63: =$B$10 -> 16616.623 | I63: =$B$10 -> 16616.623 | ... M63: =$B$10 -> 16616.623 | N63: =SUM(B63:M63) -> 199399.48
A64: TOTAL COSTO OPERACIÓN | B64: =+B61+B57 -> 180128.24 | C64: =+C61+C57 -> 180128.24 | D64: =+D61+D57 -> 180128.24 | E64: =+E61+E57 -> 180128.24 | F64: =+F61+F57 -> 180128.24 | G64: =+G61+G57 -> 180128.24 | H64: =+H61+H57 -> 180128.24 | I64: =+I61+I57 -> 180128.24 | ... N64: =+N61+N57 -> 2161538.9
B68: COSTOS DE PRODUCCION AÑO 4
A69: VARIABLES | B69: 1 | C69: 2 | D69: 3 | E69: 4 | F69: 5 | G69: 6 | H69: 7 | I69: 8 | J69: 9 | K69: 10 | L69: 11 | M69: 12 | N69: TOTAL
A70: TOTAL VARIABLES | B70: =SUM(B71:B73) -> 147090.65 | C70: =SUM(C71:C73) -> 147090.65 | D70: =SUM(D71:D73) -> 147090.65 | E70: =SUM(E71:E73) -> 147090.65 | F70: =SUM(F71:F73) -> 147090.65 | G70: =SUM(G71:G73) -> 147090.65 | H70: =SUM(H71:H73) -> 147090.65 | I70: =SUM(I71:I73) -> 147090.65 | ... N70: =SUM(N71:N73) -> 1765087.8
A71: Materia prima | B71: =$B$58*1.0075 -> 107621.79 | C71: =$B$58*1.0075 -> 107621.79 | D71: =$B$58*1.0075 -> 107621.79 | E71: =$B$58*1.0075 -> 107621.79 | F71: =$B$58*1.0075 -> 107621.79 | G71: =$B$58*1.0075 -> 107621.79 | H71: =$B$58*1.0075 -> 107621.79 | I71: =$B$58*1.0075 -> 107621.79 | ... M71: =$B$58*1.0075 -> 107621.79 | N71: =SUM(B71:M71) -> 1291461.5
A72: Mano de obra directa | B72: =$B$59*1.01 -> 17236.05 | C72: =$B$59*1.01 -> 17236.05 | D72: =$B$59*1.01 -> 17236.05 | E72: =$B$59*1.01 -> 17236.05 | F72: =$B$59*1.01 -> 17236.05 | G72: =$B$59*1.01 -> 17236.05 | H72: =$B$59*1.01 -> 17236.05 | I72: =$B$59*1.01 -> 17236.05 | ... M72: =$B$59*1.01 -> 17236.05 | N72: =SUM(B72:M72) -> 206832.6
A73: Costos Indirectos de Fabricación | B73: ='M. DE CALCULO DE COSTOS VARIABL'!$F$42 -> 22232.811 | C73: ='M. DE CALCULO DE COSTOS VARIABL'!$F$42 -> 22232.811 | D73: ='M. DE CALCULO DE COSTOS VARIABL'!$F$42 -> 22232.811 | E73: ='M. DE CALCULO DE COSTOS VARIABL'!$F$42 -> 22232.811 | F73: ='M. DE CALCULO DE COSTOS VARIABL'!$F$42 -> 22232.811 | G73: ='M. DE CALCULO DE COSTOS VARIABL'!$F$42 -> 22232.811 | H73: ='M. DE CALCULO DE COSTOS VARIABL'!$F$42 -> 22232.811 | I73: ='M. DE CALCULO DE COSTOS VARIABL'!$F$42 -> 22232.811 | ... M73: ='M. DE CALCULO DE COSTOS VARIABL'!$F$42 -> 22232.811 | N73: =SUM(B73:M73) -> 266793.73
A74: TOTAL FIJOS | B74: =B75+B76 -> 34183.327 | C74: =SUM(C75:C76) -> 34183.327 | D74: =SUM(D75:D76) -> 34183.327 | E74: =SUM(E75:E76) -> 34183.327 | F74: =SUM(F75:F76) -> 34183.327 | G74: =SUM(G75:G76) -> 34183.327 | H74: =SUM(H75:H76) -> 34183.327 | I74: =SUM(I75:I76) -> 34183.327 | J74: =SUM(J75:J76) -> 34183.327 | ... M74: =SUM(M75:M76) -> 34183.327 | N74: =SUM(B74:M74) -> 410199.93
A75: Gastos de administración | B75: =$B$62*1.01 -> 17566.704 | C75: =$B$62*1.01 -> 17566.704 | D75: =$B$62*1.01 -> 17566.704 | E75: =$B$62*1.01 -> 17566.704 | F75: =$B$62*1.01 -> 17566.704 | G75: =$B$62*1.01 -> 17566.704 | H75: =$B$62*1.01 -> 17566.704 | I75: =$B$62*1.01 -> 17566.704 | ... M75: =$B$62*1.01 -> 17566.704 | N75: =SUM(B75:M75) -> 210800.45
A76: Gastos de venta | B76: =$B$10 -> 16616.623 | C76: =$B$10 -> 16616.623 | D76: =$B$10 -> 16616.623 | E76: =$B$10 -> 16616.623 | F76: =$B$10 -> 16616.623 | G76: =$B$10 -> 16616.623 | H76: =$B$10 -> 16616.623 | I76: =$B$10 -> 16616.623 | ... M76: =$B$10 -> 16616.623 | N76: =SUM(B76:M76) -> 199399.48
A77: TOTAL COSTO OPERACIÓN | B77: =+B74+B70 -> 181273.98 | C77: =+C74+C70 -> 181273.98 | D77: =+D74+D70 -> 181273.98 | E77: =+E74+E70 -> 181273.98 | F77: =+F74+F70 -> 181273.98 | G77: =+G74+G70 -> 181273.98 | H77: =+H74+H70 -> 181273.98 | I77: =+I74+I70 -> 181273.98 | ... N77: =+N74+N70 -> 2175287.8
B81: COSTOS DE PRODUCCION AÑO 5
A82: VARIABLES | B82: 1 | C82: 2 | D82: 3 | E82: 4 | F82: 5 | G82: 6 | H82: 7 | I82: 8 | J82: 9 | K82: 10 | L82: 11 | M82: 12 | N82: TOTAL
A83: TOTAL VARIABLES | B83: =SUM(B84:B86) -> 148070.18 | C83: =SUM(C84:C86) -> 148070.18 | D83: =SUM(D84:D86) -> 148070.18 | E83: =SUM(E84:E86) -> 148070.18 | F83: =SUM(F84:F86) -> 148070.18 | G83: =SUM(G84:G86) -> 148070.18 | H83: =SUM(H84:H86) -> 148070.18 | I83: =SUM(I84:I86) -> 148070.18 | ... N83: =SUM(N84:N86) -> 1776842.1
A84: Materia prima | B84: =$B$71*1.0075 -> 108428.96 | C84: =$B$71*1.0075 -> 108428.96 | D84: =$B$71*1.0075 -> 108428.96 | E84: =$B$71*1.0075 -> 108428.96 | F84: =$B$71*1.0075 -> 108428.96 | G84: =$B$71*1.0075 -> 108428.96 | H84: =$B$71*1.0075 -> 108428.96 | I84: =$B$71*1.0075 -> 108428.96 | ... M84: =$B$71*1.0075 -> 108428.96 | N84: =SUM(B84:M84) -> 1301147.5
A85: Mano de obra directa | B85: =$B$72*1.01 -> 17408.41 | C85: =$B$72*1.01 -> 17408.41 | D85: =$B$72*1.01 -> 17408.41 | E85: =$B$72*1.01 -> 17408.41 | F85: =$B$72*1.01 -> 17408.41 | G85: =$B$72*1.01 -> 17408.41 | H85: =$B$72*1.01 -> 17408.41 | I85: =$B$72*1.01 -> 17408.41 | ... M85: =$B$72*1.01 -> 17408.41 | N85: =SUM(B85:M85) -> 208900.92
A86: Costos Indirectos de Fabricación | B86: ='M. DE CALCULO DE COSTOS VARIABL'!$F$42 -> 22232.811 | C86: ='M. DE CALCULO DE COSTOS VARIABL'!$F$42 -> 22232.811 | D86: ='M. DE CALCULO DE COSTOS VARIABL'!$F$42 -> 22232.811 | E86: ='M. DE CALCULO DE COSTOS VARIABL'!$F$42 -> 22232.811 | F86: ='M. DE CALCULO DE COSTOS VARIABL'!$F$42 -> 22232.811 | G86: ='M. DE CALCULO DE COSTOS VARIABL'!$F$42 -> 22232.811 | H86: ='M. DE CALCULO DE COSTOS VARIABL'!$F$42 -> 22232.811 | I86: ='M. DE CALCULO DE COSTOS VARIABL'!$F$42 -> 22232.811 | ... M86: ='M. DE CALCULO DE COSTOS VARIABL'!$F$42 -> 22232.811 | N86: =SUM(B86:M86) -> 266793.73
A87: TOTAL FIJOS | B87: =B88+B89 -> 34358.994 | C87: =SUM(C88:C89) -> 34358.994 | D87: =SUM(D88:D89) -> 34358.994 | E87: =SUM(E88:E89) -> 34358.994 | F87: =SUM(F88:F89) -> 34358.994 | G87: =SUM(G88:G89) -> 34358.994 | H87: =SUM(H88:H89) -> 34358.994 | I87: =SUM(I88:I89) -> 34358.994 | J87: =SUM(J88:J89) -> 34358.994 | ... M87: =SUM(M88:M89) -> 34358.994 | N87: =SUM(B87:M87) -> 412307.93
A88: Gastos de administración | B88: =$B$75*1.01 -> 17742.371 | C88: =$B$75*1.01 -> 17742.371 | D88: =$B$75*1.01 -> 17742.371 | E88: =$B$75*1.01 -> 17742.371 | F88: =$B$75*1.01 -> 17742.371 | G88: =$B$75*1.01 -> 17742.371 | H88: =$B$75*1.01 -> 17742.371 | I88: =$B$75*1.01 -> 17742.371 | ... M88: =$B$75*1.01 -> 17742.371 | N88: =SUM(B88:M88) -> 212908.45
A89: Gastos de venta | B89: =$B$10 -> 16616.623 | C89: =$B$10 -> 16616.623 | D89: =$B$10 -> 16616.623 | E89: =$B$10 -> 16616.623 | F89: =$B$10 -> 16616.623 | G89: =$B$10 -> 16616.623 | H89: =$B$10 -> 16616.623 | I89: =$B$10 -> 16616.623 | ... M89: =$B$10 -> 16616.623 | N89: =SUM(B89:M89) -> 199399.48
A90: TOTAL COSTO OPERACIÓN | B90: =+B87+B83 -> 182429.17 | C90: =+C87+C83 -> 182429.17 | D90: =+D87+D83 -> 182429.17 | E90: =+E87+E83 -> 182429.17 | F90: =+F87+F83 -> 182429.17 | G90: =+G87+G83 -> 182429.17 | H90: =+H87+H83 -> 182429.17 | I90: =+I87+I83 -> 182429.17 | ... N90: =+N87+N83 -> 2189150
B95: COSTOS DE PRODUCCION AÑO 5
A96: VARIABLES | B96: 1 | C96: 2 | D96: 3 | E96: 4 | F96: 5 | G96: 6 | H96: 7 | I96: 8 | J96: 9 | K96: 10 | L96: 11 | M96: 12 | N96: TOTAL
A97: TOTAL VARIABLES | B97: =SUM(B98:B100) -> 149057.48 | C97: =SUM(C98:C100) -> 149057.48 | D97: =SUM(D98:D100) -> 149057.48 | E97: =SUM(E98:E100) -> 149057.48 | F97: =SUM(F98:F100) -> 149057.48 | G97: =SUM(G98:G100) -> 149057.48 | H97: =SUM(H98:H100) -> 149057.48 | I97: =SUM(I98:I100) -> 149057.48 | ... N97: =SUM(N98:N100) -> 1788689.7
A98: Materia prima | B98: =108428.955378082*1.0075 -> 109242.17 | C98: =108428.955378082*1.0075 -> 109242.17 | D98: =108428.955378082*1.0075 -> 109242.17 | E98: =108428.955378082*1.0075 -> 109242.17 | F98: =108428.955378082*1.0075 -> 109242.17 | G98: =108428.955378082*1.0075 -> 109242.17 | H98: =108428.955378082*1.0075 -> 109242.17 | I98: =108428.955378082*1.0075 -> 109242.17 | ... M98: =108428.955378082*1.0075 -> 109242.17 | N98: =SUM(B98:M98) -> 1310906.1
A99: Mano de obra directa | B99: =17408.4101678514*1.01 -> 17582.494 | C99: =17408.4101678514*1.01 -> 17582.494 | D99: =17408.4101678514*1.01 -> 17582.494 | E99: =17408.4101678514*1.01 -> 17582.494 | F99: =17408.4101678514*1.01 -> 17582.494 | G99: =17408.4101678514*1.01 -> 17582.494 | H99: =17408.4101678514*1.01 -> 17582.494 | I99: =17408.4101678514*1.01 -> 17582.494 | ... M99: =17408.4101678514*1.01 -> 17582.494 | N99: =SUM(B99:M99) -> 210989.93
A100: Costos Indirectos de Fabricación | B100: 22232.811 | C100: 22232.811 | D100: 22232.811 | E100: 22232.811 | F100: 22232.811 | G100: 22232.811 | H100: 22232.811 | I100: ='M. DE CALCULO DE COSTOS VARIABL'!$F$42 -> 22232.811 | J100: 22232.811 | K100: 22232.811 | L100: 22232.811 | M100: 22232.811 | N100: =SUM(B100:M100) -> 266793.73
A101: TOTAL FIJOS | B101: =B102+B103 -> 34536.418 | C101: =SUM(C102:C103) -> 34536.418 | D101: =SUM(D102:D103) -> 34536.418 | E101: =SUM(E102:E103) -> 34536.418 | F101: =SUM(F102:F103) -> 34536.418 | G101: =SUM(G102:G103) -> 34536.418 | H101: =SUM(H102:H103) -> 34536.418 | I101: =SUM(I102:I103) -> 34536.418 | J101: =SUM(J102:J103) -> 34536.418 | ... M101: =SUM(M102:M103) -> 34536.418 | N101: =SUM(B101:M101) -> 414437.02
A102: Gastos de administración | B102: =17742.3712127807*1.01 -> 17919.795 | C102: =17742.3712127807*1.01 -> 17919.795 | D102: =17742.3712127807*1.01 -> 17919.795 | E102: =17742.3712127807*1.01 -> 17919.795 | F102: =17742.3712127807*1.01 -> 17919.795 | G102: =17742.3712127807*1.01 -> 17919.795 | H102: =17742.3712127807*1.01 -> 17919.795 | I102: =17742.3712127807*1.01 -> 17919.795 | ... M102: =17742.3712127807*1.01 -> 17919.795 | N102: =SUM(B102:M102) -> 215037.54
A103: Gastos de venta | B103: 16616.623 | C103: 16616.623 | D103: 16616.623 | E103: 16616.623 | F103: 16616.623 | G103: 16616.623 | H103: 16616.623 | I103: 16616.623 | J103: 16616.623 | K103: 16616.623 | L103: 16616.623 | M103: 16616.623 | N103: =SUM(B103:M103) -> 199399.48
A104: TOTAL COSTO OPERACIÓN | B104: =+B101+B97 -> 183593.9 | C104: =+C101+C97 -> 183593.9 | D104: =+D101+D97 -> 183593.9 | E104: =+E101+E97 -> 183593.9 | F104: =+F101+F97 -> 183593.9 | G104: =+G101+G97 -> 183593.9 | H104: =+H101+H97 -> 183593.9 | I104: =+I101+I97 -> 183593.9 | ... N104: =+N101+N97 -> 2203126.7

Sheet M. DE CALCULO DE GASTOS FIJOS
A1: ESTRUCTURA DE INGRESOS Y EGERESOS
A3: MEMORIAS DE CALCULO GASTOS FIJOS
A5: PROYECTO: Las Amarguitas Fabrica de Cervezas y Destilados
A6: SOCIEDAD RESPONSABILIDAD LIMITADA
A7: BENEFICIARIOS: PABLO PUIG TRESS, HUGO PUIG TRESS.
A9: MEMORIA DE CALCULO GASTOS DE ADMINISTRACIÓN | F9: MESES
B10: MEDIDA | C10: CANT | D10: C.U. | E10: TOTAL | F10: 1 | G10: 2 | H10: 3 | I10: 4 | J10: 5 | K10: 6 | L10: 7 | M10: 8 | N10: 9 | O10: 10 | P10: 11 | Q10: 12
A11: Paquete de Internet y telefonía con ADM factura | B11: Servicio | C11: 12 | D11: 320.93 | E11: =D11*C11 -> 3851.16 | F11: =D11 -> 320.93 | G11: =D11 -> 320.93 | H11: =F11 -> 320.93 | I11: =G11 -> 320.93 | J11: =H11 -> 320.93 | K11: =I11 -> 320.93 | L11: =J11 -> 320.93 | M11: =K11 -> 320.93 | N11: =L11 -> 320.93 | O11: =M11 -> 320.93 | ... Q11: =O11 -> 320.93
A12: Gerente General | B12: Meses Trabajados | C12: 12 | D12: =8364.57*2 -> 16729.14 | E12: =D12*C12 -> 200749.68 | F12: =$D$32 -> 16729.14 | G12: =$D$32 -> 16729.14 | H12: =$D$32 -> 16729.14 | I12: =$D$32 -> 16729.14 | J12: =$D$32 -> 16729.14 | K12: =$D$32 -> 16729.14 | L12: =$D$32 -> 16729.14 | M12: =$D$32 -> 16729.14 | ... Q12: =$D$32 -> 16729.14
A13: Subtotal | E13: =SUM(E11:E12) -> 204600.84 | F13: =SUM(F11:F12) -> 17050.07 | G13: =SUM(G11:G12) -> 17050.07 | H13: =SUM(H11:H12) -> 17050.07 | I13: =SUM(I11:I12) -> 17050.07 | J13: =SUM(J11:J12) -> 17050.07 | K13: =SUM(K11:K12) -> 17050.07 | L13: =SUM(L11:L12) -> 17050.07 | ... Q13: =SUM(Q11:Q12) -> 17050.07
A16: MEMORIA DE CALCULO GASTOS DE VENTA | F16: MESES
F17: 1 | G17: 2 | H17: 3 | I17: 4 | J17: 5 | K17: 6 | L17: 7 | M17: 8 | N17: 9 | O17: 10 | P17: 11 | Q17: 12
A18: Gerencia de Ventas | B18: Meses Trabajados | C18: 12 | D18: =7908.32*2 -> 15816.64 | E18: =D18*C18 -> 189799.68 | F18: =D18 -> 15816.64 | G18: =D18 -> 15816.64 | H18: =F18 -> 15816.64 | I18: =G18 -> 15816.64 | J18: =H18 -> 15816.64 | K18: =I18 -> 15816.64 | L18: =J18 -> 15816.64 | M18: =K18 -> 15816.64 | N18: =L18 -> 15816.64 | O18: =M18 -> 15816.64 | ... Q18: =O18 -> 15816.64
A19: Publicidad | B19: tiempo (meses) | C19: 12 | D19: 249.98 | E19: =D19*C19 -> 2999.76 | F19: =$D$39 -> 249.98 | G19: =$D$39 -> 249.98 | H19: =$D$39 -> 249.98 | I19: =$D$39 -> 249.98 | J19: =$D$39 -> 249.98 | K19: =$D$39 -> 249.98 | L19: =$D$39 -> 249.98 | M19: =$D$39 -> 249.98 | ... Q19: =$D$39 -> 249.98
A20: Almacenamiento | B20: tiempo (meses) | C20: 12 | D20: =550.003 -> 550.003 | E20: =D20*C20 -> 6600.036 | F20: =D$40 -> 550.003 | G20: =E$40 -> 6600.036 | H20: =$F$40 -> 550.003 | I20: =$F$40 -> 550.003 | J20: =$F$40 -> 550.003 | K20: =$F$40 -> 550.003 | L20: =$F$40 -> 550.003 | M20: =$F$40 -> 550.003 | N20: =$F$40 -> 550.003 | O20: =$F$40 -> 550.003 | ... Q20: =$F$40 -> 550.003 | R20: =SUM(F41:Q41) -> 205449.51
A21: Subtotal | E21: =SUM(E18:E20) -> 199399.48 | F21: =SUM(F18:F20) -> 16616.623 | G21: =SUM(G18:G20) -> 22666.656 | H21: =SUM(H18:H20) -> 16616.623 | I21: =SUM(I18:I20) -> 16616.623 | J21: =SUM(J18:J20) -> 16616.623 | K21: =SUM(K18:K20) -> 16616.623 | L21: =SUM(L18:L20) -> 16616.623 | ... Q21: =SUM(Q18:Q20) -> 16616.623
A28: MEMORIA DE CALCULO GASTOS DE ADMINISTRACIÓN | F28: MESES
B29: MEDIDA | C29: CANT | D29: C.U. | E29: TOTAL | F29: 1 | G29: 2 | H29: 3 | I29: 4 | J29: 5 | K29: 6 | L29: 7 | M29: 8 | N29: 9 | O29: 10 | P29: 11 | Q29: 12
A30: Paquete de Internet y telefonía con ADM factura | B30: Servicio | C30: 12 | D30: 320.93 | E30: =D30*C30 -> 3851.16 | F30: =D30 -> 320.93 | G30: =D30 -> 320.93 | H30: =F30 -> 320.93 | I30: =G30 -> 320.93 | J30: =H30 -> 320.93 | K30: =I30 -> 320.93 | L30: =J30 -> 320.93 | M30: =K30 -> 320.93 | N30: =L30 -> 320.93 | O30: =M30 -> 320.93 | ... Q30: =O30 -> 320.93
A31: Gerente de Finanzas | B31: Meses Trabajados | C31: 12 | D31: =6083.32*2 -> 12166.64 | E31: =D31*C31 -> 145999.68 | F31: =$D$31 -> 12166.64 | G31: =$D$31 -> 12166.64 | H31: =$D$31 -> 12166.64 | I31: =$D$31 -> 12166.64 | J31: =$D$31 -> 12166.64 | K31: =$D$31 -> 12166.64 | L31: =$D$31 -> 12166.64 | M31: =$D$31 -> 12166.64 | ... Q31: =$D$31 -> 12166.64
A32: Gerente General | B32: Meses Trabajados | C32: 12 | D32: =8364.57*2 -> 16729.14 | E32: =D32*C32 -> 200749.68 | F32: =$D$32 -> 16729.14 | G32: =$D$32 -> 16729.14 | H32: =$D$32 -> 16729.14 | I32: =$D$32 -> 16729.14 | J32: =$D$32 -> 16729.14 | K32: =$D$32 -> 16729.14 | L32: =$D$32 -> 16729.14 | M32: =$D$32 -> 16729.14 | ... Q32: =$D$32 -> 16729.14
A33: Subtotal | E33: =SUM(E30:E32) -> 350600.52 | F33: =SUM(F30:F32) -> 29216.71 | G33: =SUM(G30:G32) -> 29216.71 | H33: =SUM(H30:H32) -> 29216.71 | I33: =SUM(I30:I32) -> 29216.71 | J33: =SUM(J30:J32) -> 29216.71 | K33: =SUM(K30:K32) -> 29216.71 | L33: =SUM(L30:L32) -> 29216.71 | ... Q33: =SUM(Q30:Q32) -> 29216.71
E34: =E32+E30 -> 204600.84
A36: MEMORIA DE CALCULO GASTOS DE VENTA | F36: MESES
F37: 1 | G37: 2 | H37: 3 | I37: 4 | J37: 5 | K37: 6 | L37: 7 | M37: 8 | N37: 9 | O37: 10 | P37: 11 | Q37: 12
A38: Gerencia de Ventas | B38: Meses Trabajados | C38: 12 | D38: =7908.32*2 -> 15816.64 | E38: =D38*C38 -> 189799.68 | F38: =D38 -> 15816.64 | G38: =D38 -> 15816.64 | H38: =F38 -> 15816.64 | I38: =G38 -> 15816.64 | J38: =H38 -> 15816.64 | K38: =I38 -> 15816.64 | L38: =J38 -> 15816.64 | M38: =K38 -> 15816.64 | N38: =L38 -> 15816.64 | O38: =M38 -> 15816.64 | ... Q38: =O38 -> 15816.64
A39: Publicidad | B39: tiempo (meses) | C39: 12 | D39: 249.98 | E39: =D39*C39 -> 2999.76 | F39: =$D$39 -> 249.98 | G39: =$D$39 -> 249.98 | H39: =$D$39 -> 249.98 | I39: =$D$39 -> 249.98 | J39: =$D$39 -> 249.98 | K39: =$D$39 -> 249.98 | L39: =$D$39 -> 249.98 | M39: =$D$39 -> 249.98 | ... Q39: =$D$39 -> 249.98
A40: Almacenamiento | B40: tiempo (meses) | C40: 12 | D40: =550.003 -> 550.003 | E40: =D40*C40 -> 6600.036 | F40: =D$40 -> 550.003 | G40: =E$40 -> 6600.036 | H40: =$F$40 -> 550.003 | I40: =$F$40 -> 550.003 | J40: =$F$40 -> 550.003 | K40: =$F$40 -> 550.003 | L40: =$F$40 -> 550.003 | M40: =$F$40 -> 550.003 | N40: =$F$40 -> 550.003 | O40: =$F$40 -> 550.003 | ... Q40: =$F$40 -> 550.003
A41: Subtotal | E41: =SUM(E38:E40) -> 199399.48 | F41: =SUM(F38:F40) -> 16616.623 | G41: =SUM(G38:G40) -> 22666.656 | H41: =SUM(H38:H40) -> 16616.623 | I41: =SUM(I38:I40) -> 16616.623 | J41: =SUM(J38:J40) -> 16616.623 | K41: =SUM(K38:K40) -> 16616.623 | L41: =SUM(L38:L40) -> 16616.623 | ... Q41: =SUM(Q38:Q40) -> 16616.623
E43: =E41+E33 -> 550000
A45: MEMORIA DE CALCULO GASTOS FIJOS PARA LA INVERSION FIJA | F45: MESES
A46: CONCEPTO | B46: MEDIDA | C46: CANT | D46: C.U. | E46: TOTAL | F46: 1 | G46: 2 | H46: 3 | I46: 4 | J46: 5 | K46: 6 | L46: 7 | M46: 8 | N46: 9 | O46: 10 | P46: 11 | Q46: 12
A47: Gastos de administración | B47: Meses Operados | C47: 12 | E47: =SUM(F47:Q47) -> 350600.52 | F47: =F33 -> 29216.71 | G47: =G33 -> 29216.71 | H47: =H33 -> 29216.71 | I47: =I33 -> 29216.71 | J47: =J33 -> 29216.71 | K47: =K33 -> 29216.71 | L47: =L33 -> 29216.71 | M47: =M33 -> 29216.71 | ... Q47: =Q33 -> 29216.71
A48: gastos de venta | B48: Meses Operados | C48: 12 | E48: =E41 -> 199399.48 | F48: =F41 -> 16616.623 | G48: =G41 -> 22666.656 | H48: =H41 -> 16616.623 | I48: =I41 -> 16616.623 | J48: =J41 -> 16616.623 | K48: =K41 -> 16616.623 | L48: =L41 -> 16616.623 | ... Q48: =Q41 -> 16616.623
A49: TOTAL GASTOS FIJOS | E49: =E47+E48 -> 550000 | F49: =SUM(F47:F48) -> 45833.333 | G49: =SUM(G47:G48) -> 51883.366 | H49: =SUM(H47:H48) -> 45833.333 | I49: =SUM(I47:I48) -> 45833.333 | J49: =SUM(J47:J48) -> 45833.333 | K49: =SUM(K47:K48) -> 45833.333 | L49: =SUM(L47:L48) -> 45833.333 | M49: =SUM(M47:M48) -> 45833.333 | ... Q49: =SUM(Q47:Q48) -> 45833.333

Sheet M. DE CALCULO DE COSTOS VARIABL
A1: ESTRUCTURA DE INGRESOS Y EGERESOS
A3: MEMORIAS DE CALCULO COSTOS VARIABLES
A5: PROYECTO: Las Amarguitas Fabrica de Cervezas y Destilados
A6: SOCIEDAD RESPONSABILIDAD LIMITADA
A7: BENEFICIARIOS: PABLO PUIG TRESS, HUGO PUIG TRESS.
A8: MEMORIA DE CALCULO MATERIA PRIMA E INSUMOS | F8: MEMORIA DE CALCULO MATERIA PRIMA E INSUMOS
A9: Lote 1 (Regia, Golden y Milf) | B9: MEDIDA | C9: CANT | D9: C.U. | E9: TOTAL | G9: MEDIDA | H9: CANT | I9: C.U. | J9: TOTAL
A10: Malta | B10: Kilos | C10: 300 | D10: 25 | E10: =C10*D10 -> 7500 | F10: Lote 2 (Dark, Ver-Got y Honey) | G10: Kilos | H10: 350 | I10: 32 | J10: =H10*I10 -> 11200
A11: Lupulo | B11: Onzas | C11: 200 | D11: 26 | E11: =C11*D11 -> 5200 | F11: Lupulo | G11: Onzas | H11: 250 | I11: 26 | J11: =H11*I11 -> 6500
A12: Levadura | B12: Gramos | C12: 1200 | D12: 4 | E12: =C12*D12 -> 4800 | F12: Levadura | G12: Gramos | H12: 1200 | I12: 4 | J12: =H12*I12 -> 4800
A13: Agua | B13: Litros | C13: 1350 | D13: 0.75 | E13: =C13*D13 -> 1012.5 | F13: Agua | G13: Litros | H13: 1400 | I13: 0.75 | J13: =H13*I13 -> 1050
A14: Cascara de naranja | B14: Kilos | C14: 1.5 | D14: 70 | E14: =C14*D14 -> 105 | F14: Caramelo | G14: Kilos | H14: 30 | I14: 40 | J14: =H14*I14 -> 1200
A15: Cascara de limón | B15: Kilos | C15: 2.25 | D15: 40 | E15: =C15*D15 -> 90 | F15: Durazno (congelado) | G15: Kilos | H15: 130 | I15: 35 | J15: =H15*I15 -> 4550
A16: Especias | B16: Kilos | C16: 5 | D16: 35 | E16: =C16*D16 -> 175 | F16: Pasas | G16: Kilos | H16: 15 | I16: 40 | J16: =H16*I16 -> 600
A17: Gallletas | B17: Kilos | C17: 15 | D17: 32 | E17: =C17*D17 -> 480 | F17: Miel | G17: Kilos | H17: 30 | I17: 50 | J17: =H17*I17 -> 1500
A18: Cafe Tostado | B18: Kilos | C18: 12 | D18: 70 | E18: =C18*D18 -> 840 | F18: Álmivar | G18: litros | H18: 20 | I18: 40 | J18: =I18*H18 -> 800
A19: Cacao Tostado | B19: Kilos | C19: 7.5 | D19: 60 | E19: =C19*D19 -> 450
A20: Almendra | B20: Litros | C20: 1 | D20: 30 | E20: =C20*D20 -> 30
A21: Subtotal | E21: =SUM(E10:E20) -> 20682.5 | F21: Subtotal | J21: =SUM(J10:J20) -> 32200
A24: MEMORIA DE CALCULO DE MOD
A25: Maestro cervecero | B25: Meses Trabajados | C25: 12 | D25: =4562.49*2 -> 9124.98 | E25: =C25*D25 -> 109499.76
A26: Auxiliar de producción | B26: Meses Trabajados | C26: 12 | D26: =3802.08*2 -> 7604.16 | E26: =D26*C26 -> 91249.92 | F26: Total de Materia Prima | G26: =J21+E21 -> 52882.5 | H26: 2 lotes en un mes
A27: Subtotal | D27: =D25+D26 -> 16729.14 | E27: =SUM(E25:E26) -> 200749.68
D29: =D25 -> 9124.98 | E29: =E25 -> 109499.76
A34: MEMORIA DE CALCULO PARA CIF
A35: Energía eléctrica (cálculo mensual de GDMTH) | B35: kWh | C35: 4070 | D35: Variable | E35: 20000 | F35: =E35*1.99 -> 39800
A36: Gas | B36: Litros | C36: 3000 | D36: 10.82 | E36: 23000 | F36: =E36 -> 23000
A37: Material de limpieza | B37: Varios | C37: Variable | D37: =E37 -> 3000 | E37: 3000 | F37: =E37 -> 3000
A38: Material de mantenimiento | B38: Varios | C38: Variable | D38: =E38 -> 6500 | E38: 6500 | F38: =E38 -> 6500
A39: Encargado de matenimiento | B39: Meses Trabajados | C39: 12 | D39: ='CONCENTRADO DE SUELDOS'!O9 -> 10286.211 | E39: =C39*D39 -> 123434.53
A40: Auxiliar de limpieza | B40: Meses Trabajados | C40: 12 | D40: =3785.8*2 -> 7571.6 | E40: =+C40*D40 -> 90859.2 | F40: =E40 -> 90859.2
A41: Subtotal | E41: =SUM(E35:E40) -> 266793.73 | F41: =E41 -> 266793.73
E42: =E41/12 -> 22232.811 | F42: =F41/12 -> 22232.811
A44: =A39 -> Encargado de matenimiento | B44: =B39 -> Meses Trabajados | C44: =C39 -> 12 | D44: ='CONCENTRADO DE SUELDOS'!O9 -> 10286.211 | E44: =C44*D44 -> 123434.53
E45: =E41+E44 -> 390228.25

Sheet DEPRECIACIONES
A1: CALCULO DE DEPRECIACIONES Y AMORTIZACIONES
A3: PROYECTO: Las Amarguitas Fabrica de Cervezas y Destilados
A4: SOCIEDAD RESPONSABILIDAD LIMITADA
A7: MUEBLES Y EQUIPO | B7: VALOR | C7: VIDA UTIL (AÑOS) | D7: TASA DE DEPREC. | E7: DEPRECIACION (ANUAL) | F7: DEPRECIACION (MENSUAL) | G7: DEPRC. ACUM | H7: REMANENTE
A8: Sillas para Escritorios | B8: 12000 | C8: 10 años | D8: 0.1 | E8: =B8*0.1 -> 1200 | F8: =E8/12 -> 100 | G8: =E8*3 -> 3600 | H8: =E8 -> 1200
A9: Escritorios | B9: 30000 | C9: 10 años | D9: 0.1 | E9: =B9*0.1 -> 3000 | F9: =E9/12 -> 250 | G9: =E9*3 -> 9000 | H9: =E9 -> 3000
A10: Computadoras | B10: 30000 | C10: 3-4 años | D10: 0.3 | E10: =B10*0.3 -> 9000 | F10: =E10/12 -> 750 | G10: =E10*3 -> 27000 | H10: =E10 -> 9000
A11: Estantes/Anaqueles | B11: 15000 | C11: 10 años | D11: 0.1 | E11: =B11*0.1 -> 1500 | F11: =E11/12 -> 125 | G11: =E11*3 -> 4500 | H11: =E11 -> 1500
A12: Sillas del restaurante | B12: 35000 | C12: 5 años | D12: 0.2 | E12: =B12*0.2 -> 7000 | F12: =E12/12 -> 583.33333 | G12: =E12*3 -> 21000 | H12: =E12 -> 7000
A13: Mesas del restaurante | B13: 60000 | C13: 5 años | D13: 0.2 | E13: =B13*0.2 -> 12000 | F13: =E13/12 -> 1000 | G13: =E13*3 -> 36000 | H13: =E13 -> 12000
A14: Utencilios de cocina | B14: 9000 | C14: 5 años | D14: 0.2 | E14: =B14*0.2 -> 1800 | F14: =E14/12 -> 150 | G14: =E14*3 -> 5400 | H14: =E14 -> 1800
A15: Vasos | B15: 3000 | C15: 2 años | D15: 0.2 | E15: =B15*0.2 -> 600 | F15: =E15/12 -> 50 | G15: =E15*2 -> 1200 | H15: =E15 -> 600
A16: Copas | B16: 3500 | C16: 2 años | D16: 0.2 | E16: =B16*0.2 -> 700 | F16: =E16/12 -> 58.333333 | G16: =E16*2 -> 1400 | H16: =E16 -> 700
A17: Platos | B17: 2500 | C17: 2 años | D17: 0.2 | E17: =B17*0.2 -> 500 | F17: =E17/12 -> 41.666667 | G17: =E17*2 -> 1000 | H17: =E17 -> 500
A18: Total | B18: =SUM(B8:B17) -> 200000 | E18: =SUM(E8:E17) -> 37300 | F18: =SUM(F8:F17) -> 3108.3333 | H18: =SUM(H8:H17) -> 37300
A21: MAQUINARIA | B21: VALOR | C21: VIDA UTIL (AÑOS) | D21: TASA DE DEPREC. | E21: DEPRECIACION (ANUAL) | F21: DEPRECIACION (MENSUAL) | G21: DEPRC. ACUM | H21: REMANENTE
A22: Plataforma y Escalera de Operación | B22: 50000 | C22: 10 | D22: 0.1 | E22: =B22*D22 -> 5000 | F22: =E22/12 -> 416.66667 | G22: =E22*9 -> 45000 | H22: =B22-G22 -> 5000
A23: Mash Tun / HLT (Tanque de Maceración y Agua Caliente) | B23: 169000 | C23: 10 | D23: 0.1 | E23: =B23*D23 -> 16900 | F23: =E23/12 -> 1408.3333 | G23: =E23*9 -> 152100 | H23: =B23-G23 -> 16900
A24: Lauter Tun (Tanque de Filtración) | B24: 220000 | C24: 10 | D24: 0.1 | E24: =B24*D24 -> 22000 | F24: =E24/12 -> 1833.3333 | G24: =E24*9 -> 198000 | H24: =B24-G24 -> 22000
A25: Kettle / Whirlpool (Tanque de Hervor y Separación) | B25: 50000 | C25: 10 | D25: 0.1 | E25: =B25*D25 -> 5000 | F25: =E25/12 -> 416.66667 | G25: =E25*9 -> 45000 | H25: =B25-G25 -> 5000
A26: Tanque con Agitador y Boquilla para Whirlpool | B26: 125000 | C26: 10 | D26: 0.1 | E26: =B26*D26 -> 12500 | F26: =E26/12 -> 1041.6667 | G26: =E26*9 -> 112500 | H26: =B26-G26 -> 12500
A27: Tanque de Agua Caliente o Fría (HLT/CLT) | B27: 95000 | C27: 10 | D27: 0.1 | E27: =B27*D27 -> 9500 | F27: =E27/12 -> 791.66667 | G27: =E27*9 -> 85500 | H27: =B27-G27 -> 9500
A28: Intercambiador de Calor | B28: 30000 | C28: 10 | D28: 0.1 | E28: =B28*D28 -> 3000 | F28: =E28/12 -> 250 | G28: =E28*9 -> 27000 | H28: =B28-G28 -> 3000
A29: Sistema de Tuberías y Bomba Sanitaria | B29: 20000 | C29: 10 | D29: 0.1 | E29: =B29*D29 -> 2000 | F29: =E29/12 -> 166.66667 | G29: =E29*9 -> 18000 | H29: =B29-G29 -> 2000
B30: =SUM(B22:B29) -> 759000 | H30: =SUM(H22:H29) -> 75900

Sheet AMORTIZACIONES (4 AÑOS)
A1: AMORTIZACIÓN DE LA DEUDA
A3: PROYECTO:
A4: SOCIEDAD
A5: BENEFICIARIOS:
A6: TABLA DE AMORTIZACION DE LA DEUDA
H7: 799000
A8: MESES | B8: TASA DE INTERES | C8: INTERES | D8: DEUDA ACUMULADA | E8: PAGO CAPITAL | F8: PAGO INTERES | G8: PAGO TOTAL | H8: SALDO | I8: FECHAS DE PAGO
A9: 1 | B9: 0.0189 | C9: =H7*B$9 -> 15101.1 | D9: =H7+C9 -> 814101.1 | E9: 16645.83 | F9: =C9 -> 15101.1 | G9: =E9+F9 -> 31746.93 | H9: =D9-G9 -> 782354.17 | I9: =DATE(2025,11,10) -> 45971
A10: 2 | B10: 0.0189 | C10: =H9*B$9 -> 14786.494 | D10: =H9+C10 -> 797140.66 | E10: =E$9 -> 16645.83 | F10: =C10 -> 14786.494 | G10: =E10+F10 -> 31432.324 | H10: =D10-G10 -> 765708.34 | I10: =EDATE(I9,1) -> 46001
A11: 3 | B11: 0.0189 | C11: =H10*B$9 -> 14471.888 | D11: =H10+C11 -> 780180.23 | E11: =E$9 -> 16645.83 | F11: =C11 -> 14471.888 | G11: =E11+F11 -> 31117.718 | H11: =D11-G11 -> 749062.51 | I11: =EDATE(I10,1) -> 46032
A12: 4 | B12: 0.0189 | C12: =H11*B$9 -> 14157.281 | D12: =H11+C12 -> 763219.79 | E12: =E$9 -> 16645.83 | F12: =C12 -> 14157.281 | G12: =E12+F12 -> 30803.111 | H12: =D12-G12 -> 732416.68 | I12: =EDATE(I11,1) -> 46063
A13: 5 | B13: 0.0189 | C13: =H12*B$9 -> 13842.675 | D13: =H12+C13 -> 746259.36 | E13: =E$9 -> 16645.83 | F13: =C13 -> 13842.675 | G13: =E13+F13 -> 30488.505 | H13: =D13-G13 -> 715770.85 | I13: =EDATE(I12,1) -> 46091
A14: 6 | B14: 0.0189 | C14: =H13*B$9 -> 13528.069 | D14: =H13+C14 -> 729298.92 | E14: =E$9 -> 16645.83 | F14: =C14 -> 13528.069 | G14: =E14+F14 -> 30173.899 | H14: =D14-G14 -> 699125.02 | I14: =EDATE(I13,1) -> 46122
A15: 7 | B15: 0.0189 | C15: =H14*B$9 -> 13213.463 | D15: =H14+C15 -> 712338.48 | E15: =E$9 -> 16645.83 | F15: =C15 -> 13213.463 | G15: =E15+F15 -> 29859.293 | H15: =D15-G15 -> 682479.19 | I15: =EDATE(I14,1) -> 46152
A16: 8 | B16: 0.0189 | C16: =H15*B$9 -> 12898.857 | D16: =H15+C16 -> 695378.05 | E16: =E$9 -> 16645.83 | F16: =C16 -> 12898.857 | G16: =E16+F16 -> 29544.687 | H16: =D16-G16 -> 665833.36 | I16: =EDATE(I15,1) -> 46183
A17: 9 | B17: 0.0189 | C17: =H16*B$9 -> 12584.251 | D17: =H16+C17 -> 678417.61 | E17: =E$9 -> 16645.83 | F17: =C17 -> 12584.251 | G17: =E17+F17 -> 29230.081 | H17: =D17-G17 -> 649187.53 | I17: =EDATE(I16,1) -> 46213
A18: 10 | B18: 0.0189 | C18: =H17*B$9 -> 12269.644 | D18: =H17+C18 -> 661457.17 | E18: =E$9 -> 16645.83 | F18: =C18 -> 12269.644 | G18: =E18+F18 -> 28915.474 | H18: =D18-G18 -> 632541.7 | I18: =EDATE(I17,1) -> 46244
A19: 11 | B19: 0.0189 | C19: =H18*B$9 -> 11955.038 | D19: =H18+C19 -> 644496.74 | E19: =E$9 -> 16645.83 | F19: =C19 -> 11955.038 | G19: =E19+F19 -> 28600.868 | H19: =D19-G19 -> 615895.87 | I19: =EDATE(I18,1) -> 46275
A20: 12 | B20: 0.0189 | C20: =H19*B$9 -> 11640.432 | D20: =H19+C20 -> 627536.3 | E20: =E$9 -> 16645.83 | F20: =C20 -> 11640.432 | G20: =E20+F20 -> 28286.262 | H20: =D20-G20 -> 599250.04 | I20: =EDATE(I19,1) -> 46305
A21: 13 | B21: 0.0189 | C21: =H20*B$9 -> 11325.826 | D21: =H20+C21 -> 610575.87 | E21: =E$9 -> 16645.83 | F21: =C21 -> 11325.826 | G21: =E21+F21 -> 27971.656 | H21: =D21-G21 -> 582604.21 | I21: =EDATE(I20,1) -> 46336
... A43: 35 | B43: 0.0189 | C43: =H42*B$9 -> 4404.4896 | D43: =H42+C43 -> 237446.27 | E43: =E$9 -> 16645.83 | F43: =C43 -> 4404.4896 | G43: =E43+F43 -> 21050.32 | H43: =D43-G43 -> 216395.95 | I43: =EDATE(I42,1) -> 47006
A44: 36 | B44: 0.0189 | C44: =H43*B$9 -> 4089.8835 | D44: =H43+C44 -> 220485.83 | E44: =E$9 -> 16645.83 | F44: =C44 -> 4089.8835 | G44: =E44+F44 -> 20735.713 | H44: =D44-G44 -> 199750.12
A45: 37 | B45: 0.0189 | C45: =H44*B$9 -> 3775.2773 | D45: =H44+C45 -> 203525.4 | E45: =E$9 -> 16645.83 | F45: =C45 -> 3775.2773 | G45: =E45+F45 -> 20421.107 | H45: =D45-G45 -> 183104.29
A46: 38 | B46: 0.0189 | C46: =H45*B$9 -> 3460.6711 | D46: =H45+C46 -> 186564.96 | E46: =E$9 -> 16645.83 | F46: =C46 -> 3460.6711 | G46: =E46+F46 -> 20106.501 | H46: =D46-G46 -> 166458.46
A47: 39 | B47: 0.0189 | C47: =H46*B$9 -> 3146.0649 | D47: =H46+C47 -> 169604.52 | E47: =E$9 -> 16645.83 | F47: =C47 -> 3146.0649 | G47: =E47+F47 -> 19791.895 | H47: =D47-G47 -> 149812.63
A48: 40 | B48: 0.0189 | C48: =H47*B$9 -> 2831.4587 | D48: =H47+C48 -> 152644.09 | E48: =E$9 -> 16645.83 | F48: =C48 -> 2831.4587 | G48: =E48+F48 -> 19477.289 | H48: =D48-G48 -> 133166.8 | K48: CALCULO POR MES
A49: 41 | B49: 0.0189 | C49: =H48*B$9 -> 2516.8525 | D49: =H48+C49 -> 135683.65 | E49: =E$9 -> 16645.83 | F49: =C49 -> 2516.8525 | G49: =E49+F49 -> 19162.683 | H49: =D49-G49 -> 116520.97
A50: 42 | B50: 0.0189 | C50: =H49*B$9 -> 2202.2463 | D50: =H49+C50 -> 118723.22 | E50: =E$9 -> 16645.83 | F50: =C50 -> 2202.2463 | G50: =E50+F50 -> 18848.076 | H50: =D50-G50 -> 99875.14
A51: 43 | B51: 0.0189 | C51: =H50*B$9 -> 1887.6401 | D51: =H50+C51 -> 101762.78 | E51: =E$9 -> 16645.83 | F51: =C51 -> 1887.6401 | G51: =E51+F51 -> 18533.47 | H51: =D51-G51 -> 83229.31
A52: 44 | B52: 0.0189 | C52: =H51*B$9 -> 1573.034 | D52: =H51+C52 -> 84802.344 | E52: =E$9 -> 16645.83 | F52: =C52 -> 1573.034 | G52: =E52+F52 -> 18218.864 | H52: =D52-G52 -> 66583.48
A53: 45 | B53: 0.0189 | C53: =H52*B$9 -> 1258.4278 | D53: =H52+C53 -> 67841.908 | E53: =E$9 -> 16645.83 | F53: =C53 -> 1258.4278 | G53: =E53+F53 -> 17904.258 | H53: =D53-G53 -> 49937.65
A54: 46 | B54: 0.0189 | C54: =H53*B$9 -> 943.82159 | D54: =H53+C54 -> 50881.472 | E54: =E$9 -> 16645.83 | F54: =C54 -> 943.82159 | G54: =E54+F54 -> 17589.652 | H54: =D54-G54 -> 33291.82
A55: 47 | B55: 0.0189 | C55: =H54*B$9 -> 629.2154 | D55: =H54+C55 -> 33921.035 | E55: =E$9 -> 16645.83 | F55: =C55 -> 629.2154 | G55: =E55+F55 -> 17275.045 | H55: =D55-G55 -> 16645.99
A56: 48 | B56: 0.0189 | C56: =H55*B$9 -> 314.60921 | D56: =H55+C56 -> 16960.599 | E56: =E$9 -> 16645.83 | F56: =C56 -> 314.60921 | G56: =E56+F56 -> 16960.439 | H56: =D56-G56 -> 0.16
A58: TOTAL
C59: =SUM(C9:C12) -> 58516.763 | D59: =D43 -> 237446.27 | E59: =SUM(E9:E43) -> 582604.05 | F59: =SUM(F9:F43) -> 341347.82 | G59: =SUM(E59:F59) -> 923951.87
A63: PRIMERA MINISTRACIÓN
A64: MONTO: | F64: SE
A65: FECHA: | F65: tiempo | G65: 4 | H65: =G65*12 -> 48
A66: SEGUNDA MINISTRACIÓN | F66: tasa anual | G66: 0.227 | H66: Frecuencia | I66: 48
A67: MONTO: | F67: amortizacion | G67: mensual | I67: =G66/I66 -> 0.0047291667
A68: FECHA: | B68: =+H12-B65 -> 732416.68 | F68: gracia | G68: 1 mes | I68: =-PMT(I67,H65,I69) -> 18645.714
I69: 799000
B74: TABLA DE AMORTIZACION DE LA DEUDA
J75: =H7 -> 799000
B76: MESES | C76: TASA DE INTERES | D76: INTERES | E76: DEUDA ACUMULADA | F76: PAGO CAPITAL | G76: PAGO INTERES | H76: PAGO TOTAL | I76: SALDO | J76: FECHAS DE PAGO
B77: 12 | C77: 0.227 | D77: =J75*C77 -> 181373 | E77: =J75+D77 -> 980373 | F77: =J75/4 -> 199750 | G77: =D77 -> 181373 | H77: =F77+G77 -> 381123 | I77: =E77-H77 -> 599250
B78: =12*2 -> 24 | C78: 0.227 | D78: =I77*C78 -> 136029.75 | E78: =I77+D78 -> 735279.75 | F78: =J75/4 -> 199750 | G78: =D78 -> 136029.75 | H78: =G78+F78 -> 335779.75 | I78: =E78-H78 -> 399500 | L78: CALCULO POR AÑO
B79: =12*3 -> 36 | C79: 0.227 | D79: =I78*C79 -> 90686.5 | E79: =I78+D79 -> 490186.5 | F79: =J75/4 -> 199750 | G79: =D79 -> 90686.5 | H79: =G79+F79 -> 290436.5 | I79: =E79-H79 -> 199750
B80: =12*4 -> 48 | C80: 0.227 | D80: =I79*C80 -> 45343.25 | E80: =I79+D80 -> 245093.25 | F80: =J75/4 -> 199750 | G80: =D80 -> 45343.25 | H80: =G80+F80 -> 245093.25 | I80: =E80-H80 -> 0
B81: TOTAL | D81: =SUM(D77:D80) -> 453432.5 | F81: 0 | G81: =SUM(G77:G80) -> 453432.5 | H81: 0

Sheet PROYECCIONES EGRESOS E INGRESOS
A4: 4.9 PUNTO DE EQUILIBRIO
A5: CONCEPTO | B5: AÑO 1 | C5: AÑO 2 | D5: AÑO 3 | E5: AÑO 4 | F5: AÑO 5 | S5: PRECIO UNITARIO | T5: 97.5
A6: INGRESOS | S6: COSTO VARIABLE UNITARIO | T6: =B10/(2990*12) -> 48.226798
A7: VENTAS | B7: ='CUADRO DE EGRESOS E INGRESOS'!O13 -> 3655699 | C7: =INGRESOS!N29 -> 4156302.4 | D7: =INGRESOS!N41 -> 4530369.6 | E7: =INGRESOS!N53 -> 4938102.9 | F7: =INGRESOS!N65 -> 5382532.2 | S7: COSTO FIJO TOTAL | T7: 669999.96 | U7: =T20*15% -> #REF!
A9: COSTOS DE OPERACION | S9: PUNTO DE EQUILIBRIO UNITARIO | T9: =T7/(T5-T6) -> 13597.654
A10: COSTOS VARIABLES | B10: =COSTOS!N29 -> 1730377.5 | C10: =COSTOS!N44 -> 1741856.3 | D10: =COSTOS!N57 -> 1753426.1 | E10: =COSTOS!N70 -> 1765087.8 | F10: =COSTOS!N83 -> 1776842.1 | S10: PUNTO DE EQUILIBRIO UNITARIO | T10: =T7/(1-(T6/T5)) -> 1325771.3
A11: COSTOS FIJOS | B11: =COSTOS!N33 -> 404000.32 | C11: =COSTOS!N48 -> 406046.32 | D11: =COSTOS!N61 -> 408112.79 | E11: =COSTOS!N74 -> 410199.93 | F11: =COSTOS!N87 -> 412307.93
A13: UTILIDAD DE OPERACIÓN | B13: =B7-B10-B11 -> 1521321.2 | C13: =C7-C10-C11 -> 2008399.8 | D13: =D7-D10-D11 -> 2368830.7 | E13: =E7-E10-E11 -> 2762815.2 | F13: =F7-F10-F11 -> 3193382.1
A14: IMPUESTOS | B14: ='CUADRO DE EGRESOS E INGRESOS'!Q17 -> 598528.49 | C14: ='CUADRO DE EGRESOS E INGRESOS'!Q31 -> 793359.94 | D14: ='CUADRO DE EGRESOS E INGRESOS'!Q44 -> 937532.29 | E14: ='CUADRO DE EGRESOS E INGRESOS'!Q55 -> 1095960.9 | F14: ='CUADRO DE EGRESOS E INGRESOS'!Q67 -> 1267352.9
A15: PAGO CAPITAL | B15: ='AMORTIZACIONES (4 AÑOS)'!E12*12 -> 199749.96 | C15: =SUM('AMORTIZACIONES (4 AÑOS)'!E21:E32) -> 199749.96 | D15: =SUM('AMORTIZACIONES (4 AÑOS)'!E33:E44) -> 199749.96 | E15: =SUM('AMORTIZACIONES (4 AÑOS)'!E45:E56) -> 199749.96 | F15: 0
A16: UTILIDAD NETA | B16: =B13-B14-B15 -> 723042.77 | C16: =C13-C14-C15 -> 1015289.9 | D16: =D13-D14-D15 -> 1231548.5 | E16: =E13-E14-E15 -> 1467104.3 | F16: =F13-F14-F15 -> 1926029.3
A17: PUNTO DE EQUILIBRIO
A18: como % de ventas
T19: =T20/T26 -> #REF!
S20: ventas | T20: =#REF! -> #REF! | U20: =#REF!*1.2 -> #REF! | V20: =#REF!*1.3 -> #REF! | W20: =T20/T5 -> #REF!
S21: costo variable | T21: =T19*T6 -> #REF! | U21: =COSTOS!N29*1.2 -> 2076453 | V21: =COSTOS!N29*1.3 -> 2249490.8 | W21: =T6*W20 -> #REF!
A22: UTILIDAD POR SOCIO | B22: =+B16/30 -> 24101.426 | C22: =+C16/30 -> 33842.998 | D22: =+D16/30 -> 41051.616 | E22: =+E16/30 -> 48903.476 | F22: =+F16/30 -> 64200.976 | S22: costos fijos | T22: =U7 -> #REF! | U22: =COSTOS!N33*1.2 -> 484800.38 | V22: =COSTOS!N33*1.3 -> 525200.41
W24: UNIDADES MONETARIAS
A25: GRÁFICA DEL PUNTO DE EQUILIBRIO | S25: COSTO FIJO | T25: ='M. DE CALCULO DE GASTOS FIJOS'!E43 -> 550000 | W25: PEu | X25: CF
S26: PRECIO DE VENTA - UNITARIO (Pvu) | T26: =T5 -> 97.5 | X26: 1- Cvu
S27: COSTO VARIAB. - UNIT (Cvu) | T27: =T6 -> 48.226798 | X27: PVU
S28: P.E UNIDADES MONT | T28: =$T$25/(1-$T$27/$T$26) -> 1088319.8
W30: UNIDADES PRODUCIDAS
S31: COSTO FIJO | T31: =T25 -> 550000
S32: PRECIO DE VENTA - UNITARIO (Pvu) | T32: =T26 -> 97.5
S33: COSTO VARIAB. - UNIT (Cvu) | T33: =T27 -> 48.226798
S34: P.E UNIDADES PROD | T34: =$T$31/($T$32-$T$33) -> 11162.254 | U34: 30000
S35: UTILIDAD | T35: =($T$32*U34)-($T$33*U34)-T31 -> 928196.07
T37: CANTIDAD | U37: VENTAS | V37: COSTOS TOTALES | W37: UTILIDADES
T38: =T39-4283 -> 6879.254 | U38: =$T$32*T38 -> 670727.26 | V38: =$T$31+$T$33*T38 -> 881764.39 | W38: =U38-V38 -> -211037.12
T39: =T34 -> 11162.254 | U39: =$T$32*T39 -> 1088319.8 | V39: =$T$31+$T$33*T39 -> 1088319.8 | W39: =U39-V39 -> 0
T40: =T39+4283 -> 15445.254 | U40: =$T$32*T40 -> 1505912.3 | V40: =$T$31+$T$33*T40 -> 1294875.1 | W40: =U40-V40 -> 211037.12
T41: =T40+4283 -> 19728.254 | U41: =$T$32*T41 -> 1923504.8 | V41: =$T$31+$T$33*T41 -> 1501430.5 | W41: =U41-V41 -> 422074.25
T42: =T41+4283 -> 24011.254 | U42: =$T$32*T42 -> 2341097.3 | V42: =$T$31+$T$33*T42 -> 1707985.9 | W42: =U42-V42 -> 633111.37
T43: =T42+4283 -> 28294.254 | U43: =$T$32*T43 -> 2758689.8 | V43: =$T$31+$T$33*T43 -> 1914541.3 | W43: =U43-V43 -> 844148.5
T44: =T43+4283 -> 32577.254 | U44: =$T$32*T44 -> 3176282.3 | V44: =$T$31+$T$33*T44 -> 2121096.6 | W44: =U44-V44 -> 1055185.6
T45: =T44+4283 -> 36860.254 | U45: =$T$32*T45 -> 3593874.8 | V45: =$T$31+$T$33*T45 -> 2327652 | W45: =U45-V45 -> 1266222.7

Sheet SENSIBILIDAD
A1: SENSIBILIZACION
A3: PROYECTO:
A4: SOCIEDAD
A5: BENEFICIARIOS:
A6: PARA EL PRIMER AÑO
C7: CAMBIO EN VENTAS | G7: CAMBIO EN COSTOS
A8: CONCEPTO | B8: TOTAL PROYECTO | C8: 0.05 | D8: 0.1 | E8: 0.15 | F8: 0.2 | G8: 0.05 | H8: 0.1 | I8: 0.15 | J8: 0.2
A9: VENTAS | B9: ='PROYECCIONES EGRESOS E INGRESOS'!$B$7 -> 3655699 | C9: ='PROYECCIONES EGRESOS E INGRESOS'!$B$7*1.05 -> 3838484 | D9: ='PROYECCIONES EGRESOS E INGRESOS'!$B$7*1.1 -> 4021269 | E9: ='PROYECCIONES EGRESOS E INGRESOS'!$B$7*1.15 -> 4204053.9 | F9: ='PROYECCIONES EGRESOS E INGRESOS'!$B$7*1.2 -> 4386838.9 | G9: ='PROYECCIONES EGRESOS E INGRESOS'!$B$7 -> 3655699 | H9: ='PROYECCIONES EGRESOS E INGRESOS'!$B$7 -> 3655699 | I9: ='PROYECCIONES EGRESOS E INGRESOS'!$B$7 -> 3655699 | J9: ='PROYECCIONES EGRESOS E INGRESOS'!$B$7 -> 3655699
A10: COSTOS TOTALES | B10: ='PROYECCIONES EGRESOS E INGRESOS'!$B$10+'PROYECCIONES EGRESOS E INGRESOS'!$B$11 -> 2134377.8 | C10: ='PROYECCIONES EGRESOS E INGRESOS'!$B$10+'PROYECCIONES EGRESOS E INGRESOS'!$B$11 -> 2134377.8 | D10: ='PROYECCIONES EGRESOS E INGRESOS'!$B$10+'PROYECCIONES EGRESOS E INGRESOS'!$B$11 -> 2134377.8 | E10: ='PROYECCIONES EGRESOS E INGRESOS'!$B$10+'PROYECCIONES EGRESOS E INGRESOS'!$B$11 -> 2134377.8 | F10: ='PROYECCIONES EGRESOS E INGRESOS'!$B$10+'PROYECCIONES EGRESOS E INGRESOS'!$B$11 -> 2134377.8 | G10: ='PROYECCIONES EGRESOS E INGRESOS'!$B$10+'PROYECCIONES EGRESOS E INGRESOS'!$B$11*1.05 -> 2154577.8 | H10: ='PROYECCIONES EGRESOS E INGRESOS'!$B$10+'PROYECCIONES EGRESOS E INGRESOS'!$B$11*1.1 -> 2174777.9 | I10: ='PROYECCIONES EGRESOS E INGRESOS'!$B$10+'PROYECCIONES EGRESOS E INGRESOS'!$B$11*1.15 -> 2194977.9 | J10: ='PROYECCIONES EGRESOS E INGRESOS'!$B$10+'PROYECCIONES EGRESOS E INGRESOS'!$B$11*1.2 -> 2215177.9
A11: TOTAL | B11: =SUM(B9-B10) -> 1521321.2 | C11: =C9-C10 -> 1704106.2 | D11: =D9-D10 -> 1886891.1 | E11: =E9-E10 -> 2069676.1 | F11: =F9-F10 -> 2252461 | G11: =G9-G10 -> 1501121.2 | H11: =H9-H10 -> 1480921.2 | I11: =I9-I10 -> 1460721.2 | J11: =J9-J10 -> 1440521.2
A13: RELACION B/C | B13: =+B9/B10 -> 1.7127703 | C13: =+C9/C10 -> 1.7984089 | D13: =+D9/D10 -> 1.8840474 | E13: =+E9/E10 -> 1.9696859 | F13: =+F9/F10 -> 2.0553244 | G13: =+G9/G10 -> 1.6967125 | H13: =+H9/H10 -> 1.6809529 | I13: =+I9/I10 -> 1.6654833 | J13: =+J9/J10 -> 1.6502959
A15: PARA EL SEGUNDO AÑO
C16: CAMBIO EN VENTAS | G16: CAMBIO EN COSTOS
A17: CONCEPTO | B17: TOTAL PROYECTO | C17: 0.05 | D17: 0.1 | E17: 0.15 | F17: 0.2 | G17: 0.05 | H17: 0.1 | I17: 0.15 | J17: 0.2
A18: VENTAS | B18: ='PROYECCIONES EGRESOS E INGRESOS'!$C$7 -> 4156302.4 | C18: ='PROYECCIONES EGRESOS E INGRESOS'!$C$7*1.05 -> 4364117.5 | D18: ='PROYECCIONES EGRESOS E INGRESOS'!$C$7*1.1 -> 4571932.7 | E18: ='PROYECCIONES EGRESOS E INGRESOS'!$C$7*1.15 -> 4779747.8 | F18: ='PROYECCIONES EGRESOS E INGRESOS'!$C$7*1.2 -> 4987562.9 | G18: ='PROYECCIONES EGRESOS E INGRESOS'!$C$7 -> 4156302.4 | H18: ='PROYECCIONES EGRESOS E INGRESOS'!$C$7 -> 4156302.4 | I18: ='PROYECCIONES EGRESOS E INGRESOS'!$C$7 -> 4156302.4 | J18: ='PROYECCIONES EGRESOS E INGRESOS'!$C$7 -> 4156302.4
A19: COSTOS TOTALES | B19: ='PROYECCIONES EGRESOS E INGRESOS'!C14+'PROYECCIONES EGRESOS E INGRESOS'!$C$15 -> 993109.9 | C19: =$B$19 -> 993109.9 | D19: =$B$19 -> 993109.9 | E19: =$B$19 -> 993109.9 | F19: =$B$19 -> 993109.9 | G19: =$B$19*1.05 -> 1042765.4 | H19: =$B$19*1.1 -> 1092420.9 | I19: =$B$19*1.15 -> 1142076.4 | J19: =$B$19*1.2 -> 1191731.9
A20: TOTAL | B20: =SUM(B18-B19) -> 3163192.5 | C20: =C18-C19 -> 3371007.7 | D20: =D18-D19 -> 3578822.8 | E20: =E18-E19 -> 3786637.9 | F20: =F18-F19 -> 3994453 | G20: =G18-G19 -> 3113537 | H20: =H18-H19 -> 3063881.5 | I20: =I18-I19 -> 3014226 | J20: =J18-J19 -> 2964570.6
A22: RELACION B/C | B22: =+B18/B19 -> 4.1851385 | C22: =+C18/C19 -> 4.3943954 | D22: =+D18/D19 -> 4.6036523 | E22: =+E18/E19 -> 4.8129092 | F22: =+F18/F19 -> 5.0221662 | G22: =+G18/G19 -> 3.9858462 | H22: =+H18/H19 -> 3.8046713 | I22: =+I18/I19 -> 3.6392508 | J22: =+J18/J19 -> 3.4876154
A25: PARA EL TERCER AÑO
C26: CAMBIO EN VENTAS | G26: CAMBIO EN COSTOS
A27: CONCEPTO | B27: TOTAL PROYECTO | C27: 0.05 | D27: 0.1 | E27: 0.15 | F27: 0.2 | G27: 0.05 | H27: 0.1 | I27: 0.15 | J27: 0.2
A28: VENTAS | B28: ='PROYECCIONES EGRESOS E INGRESOS'!$D$7 -> 4530369.6 | C28: ='PROYECCIONES EGRESOS E INGRESOS'!$D$7*1.05 -> 4756888.1 | D28: ='PROYECCIONES EGRESOS E INGRESOS'!$D$7*1.1 -> 4983406.6 | E28: ='PROYECCIONES EGRESOS E INGRESOS'!$D$7*1.15 -> 5209925.1 | F28: ='PROYECCIONES EGRESOS E INGRESOS'!$D$7*1.2 -> 5436443.6 | G28: ='PROYECCIONES EGRESOS E INGRESOS'!$D$7 -> 4530369.6 | H28: ='PROYECCIONES EGRESOS E INGRESOS'!$D$7 -> 4530369.6 | I28: ='PROYECCIONES EGRESOS E INGRESOS'!$D$7 -> 4530369.6 | J28: ='PROYECCIONES EGRESOS E INGRESOS'!$D$7 -> 4530369.6
A29: COSTOS TOTALES | B29: ='PROYECCIONES EGRESOS E INGRESOS'!$D$10+'PROYECCIONES EGRESOS E INGRESOS'!$D$11 -> 2161538.9 | C29: ='PROYECCIONES EGRESOS E INGRESOS'!$D$10+'PROYECCIONES EGRESOS E INGRESOS'!$D$11 -> 2161538.9 | D29: ='PROYECCIONES EGRESOS E INGRESOS'!$D$10+'PROYECCIONES EGRESOS E INGRESOS'!$D$11 -> 2161538.9 | E29: ='PROYECCIONES EGRESOS E INGRESOS'!$D$10+'PROYECCIONES EGRESOS E INGRESOS'!$D$11 -> 2161538.9 | F29: ='PROYECCIONES EGRESOS E INGRESOS'!$D$10+'PROYECCIONES EGRESOS E INGRESOS'!$D$11 -> 2161538.9 | G29: =('PROYECCIONES EGRESOS E INGRESOS'!$D$10+'PROYECCIONES EGRESOS E INGRESOS'!$D$11)*1.05 -> 2269615.9 | H29: =('PROYECCIONES EGRESOS E INGRESOS'!$D$10+'PROYECCIONES EGRESOS E INGRESOS'!$D$11)*1.1 -> 2377692.8 | I29: =('PROYECCIONES EGRESOS E INGRESOS'!$D$10+'PROYECCIONES EGRESOS E INGRESOS'!$D$11)*1.15 -> 2485769.8 | J29: =('PROYECCIONES EGRESOS E INGRESOS'!$D$10+'PROYECCIONES EGRESOS E INGRESOS'!$D$11)*1.2 -> 2593846.7
A30: TOTAL | B30: =SUM(B28-B29) -> 2368830.7 | C30: =C28-C29 -> 2595349.2 | D30: =D28-D29 -> 2821867.7 | E30: =E28-E29 -> 3048386.2 | F30: =F28-F29 -> 3274904.7 | G30: =G28-G29 -> 2260753.8 | H30: =H28-H29 -> 2152676.8 | I30: =I28-I29 -> 2044599.9 | J30: =J28-J29 -> 1936522.9
A32: RELACION B/C | B32: =+B28/B29 -> 2.0959001 | C32: =+C28/C29 -> 2.2006951 | D32: =+D28/D29 -> 2.3054901 | E32: =+E28/E29 -> 2.4102851 | F32: =+F28/F29 -> 2.5150801 | G32: =+G28/G29 -> 1.9960953 | H32: =+H28/H29 -> 1.9053637 | I32: =+I28/I29 -> 1.8225218 | J32: =+J28/J29 -> 1.7465834
A36: PARA EL CUARTO AÑO
C37: CAMBIO EN VENTAS | G37: CAMBIO EN COSTOS
A38: CONCEPTO | B38: TOTAL PROYECTO | C38: 0.05 | D38: 0.1 | E38: 0.15 | F38: 0.2 | G38: 0.05 | H38: 0.1 | I38: 0.15 | J38: 0.2
A39: VENTAS | B39: ='PROYECCIONES EGRESOS E INGRESOS'!$E$7 -> 4938102.9 | C39: ='PROYECCIONES EGRESOS E INGRESOS'!$E$7 -> 4938102.9 | D39: ='PROYECCIONES EGRESOS E INGRESOS'!$E$7 -> 4938102.9 | E39: ='PROYECCIONES EGRESOS E INGRESOS'!$E$7 -> 4938102.9 | F39: ='PROYECCIONES EGRESOS E INGRESOS'!$E$7 -> 4938102.9 | G39: ='PROYECCIONES EGRESOS E INGRESOS'!$E$7 -> 4938102.9 | H39: ='PROYECCIONES EGRESOS E INGRESOS'!$E$7 -> 4938102.9 | I39: ='PROYECCIONES EGRESOS E INGRESOS'!$E$7 -> 4938102.9 | J39: ='PROYECCIONES EGRESOS E INGRESOS'!$E$7 -> 4938102.9
A40: COSTOS TOTALES | B40: ='PROYECCIONES EGRESOS E INGRESOS'!$E$10+'PROYECCIONES EGRESOS E INGRESOS'!$E$11 -> 2175287.8 | C40: ='PROYECCIONES EGRESOS E INGRESOS'!$E$10+'PROYECCIONES EGRESOS E INGRESOS'!$E$11 -> 2175287.8 | D40: ='PROYECCIONES EGRESOS E INGRESOS'!$E$10+'PROYECCIONES EGRESOS E INGRESOS'!$E$11 -> 2175287.8 | E40: ='PROYECCIONES EGRESOS E INGRESOS'!$E$10+'PROYECCIONES EGRESOS E INGRESOS'!$E$11 -> 2175287.8 | F40: ='PROYECCIONES EGRESOS E INGRESOS'!$E$10+'PROYECCIONES EGRESOS E INGRESOS'!$E$11 -> 2175287.8 | G40: =('PROYECCIONES EGRESOS E INGRESOS'!$E$10+'PROYECCIONES EGRESOS E INGRESOS'!$E$11)*1.05 -> 2284052.1 | H40: =('PROYECCIONES EGRESOS E INGRESOS'!$E$10+'PROYECCIONES EGRESOS E INGRESOS'!$E$11)*1.1 -> 2392816.5 | I40: =('PROYECCIONES EGRESOS E INGRESOS'!$E$10+'PROYECCIONES EGRESOS E INGRESOS'!$E$11)*1.15 -> 2501580.9 | J40: =('PROYECCIONES EGRESOS E INGRESOS'!$E$10+'PROYECCIONES EGRESOS E INGRESOS'!$E$11)*1.2 -> 2610345.3
A41: TOTAL | B41: =B39-B40 -> 2762815.2 | C41: =C39-C40 -> 2762815.2 | D41: =D39-D40 -> 2762815.2 | E41: =E39-E40 -> 2762815.2 | F41: =F39-F40 -> 2762815.2 | G41: =G39-G40 -> 2654050.8 | H41: =H39-H40 -> 2545286.4 | I41: =I39-I40 -> 2436522 | J41: =J39-J40 -> 2327757.6
A43: RELACION B/C | B43: =+B39/B40 -> 2.2700918 | C43: =+C39/C40 -> 2.2700918 | D43: =+D39/D40 -> 2.2700918 | E43: =+E39/E40 -> 2.2700918 | F43: =+F39/F40 -> 2.2700918 | G43: =+G39/G40 -> 2.1619922 | H43: =+H39/H40 -> 2.0637198 | I43: =+I39/I40 -> 1.9739929 | J43: =+J39/J40 -> 1.8917432
A47: PARA EL QUINTO AÑO
C48: CAMBIO EN VENTAS | G48: CAMBIO EN COSTOS
A49: CONCEPTO | B49: TOTAL PROYECTO | C49: 0.05 | D49: 0.1 | E49: 0.15 | F49: 0.2 | G49: 0.05 | H49: 0.1 | I49: 0.15 | J49: 0.2
A50: VENTAS | B50: ='PROYECCIONES EGRESOS E INGRESOS'!$F$7 -> 5382532.2 | C50: ='PROYECCIONES EGRESOS E INGRESOS'!$F$7 -> 5382532.2 | D50: ='PROYECCIONES EGRESOS E INGRESOS'!$F$7 -> 5382532.2 | E50: ='PROYECCIONES EGRESOS E INGRESOS'!$F$7 -> 5382532.2 | F50: ='PROYECCIONES EGRESOS E INGRESOS'!$F$7 -> 5382532.2 | G50: ='PROYECCIONES EGRESOS E INGRESOS'!$F$7 -> 5382532.2 | H50: ='PROYECCIONES EGRESOS E INGRESOS'!$F$7 -> 5382532.2 | I50: ='PROYECCIONES EGRESOS E INGRESOS'!$F$7 -> 5382532.2 | J50: ='PROYECCIONES EGRESOS E INGRESOS'!$F$7 -> 5382532.2
A51: COSTOS TOTALES | B51: ='PROYECCIONES EGRESOS E INGRESOS'!$F$10+'PROYECCIONES EGRESOS E INGRESOS'!$F$11 -> 2189150 | C51: ='PROYECCIONES EGRESOS E INGRESOS'!$F$10+'PROYECCIONES EGRESOS E INGRESOS'!$F$11 -> 2189150 | D51: ='PROYECCIONES EGRESOS E INGRESOS'!$F$10+'PROYECCIONES EGRESOS E INGRESOS'!$F$11 -> 2189150 | E51: ='PROYECCIONES EGRESOS E INGRESOS'!$F$10+'PROYECCIONES EGRESOS E INGRESOS'!$F$11 -> 2189150 | F51: ='PROYECCIONES EGRESOS E INGRESOS'!$F$10+'PROYECCIONES EGRESOS E INGRESOS'!$F$11 -> 2189150 | G51: =('PROYECCIONES EGRESOS E INGRESOS'!$F$10+'PROYECCIONES EGRESOS E INGRESOS'!$F$11)*1.1 -> 2408065 | H51: =('PROYECCIONES EGRESOS E INGRESOS'!$F$10+'PROYECCIONES EGRESOS E INGRESOS'!$F$11)*1.1 -> 2408065 | I51: =('PROYECCIONES EGRESOS E INGRESOS'!$F$10+'PROYECCIONES EGRESOS E INGRESOS'!$F$11)*1.15 -> 2517522.6 | J51: =('PROYECCIONES EGRESOS E INGRESOS'!$F$10+'PROYECCIONES EGRESOS E INGRESOS'!$F$11)*1.2 -> 2626980.1
A52: TOTAL | B52: =B50-B51 -> 3193382.1 | C52: =C50-C51 -> 3193382.1 | D52: =D50-D51 -> 3193382.1 | E52: =E50-E51 -> 3193382.1 | F52: =F50-F51 -> 3193382.1 | G52: =G50-G51 -> 2974467.1 | H52: =H50-H51 -> 2974467.1 | I52: =I50-I51 -> 2865009.6 | J52: =J50-J51 -> 2755552.1
A54: RELACION B/C | B54: =+B50/B51 -> 2.4587315 | C54: =+C50/C51 -> 2.4587315 | D54: =+D50/D51 -> 2.4587315 | E54: =+E50/E51 -> 2.4587315 | F54: =+F50/F51 -> 2.4587315 | G54: =+G50/G51 -> 2.2352105 | H54: =+H50/H51 -> 2.2352105 | I54: =+I50/I51 -> 2.1380274 | J54: =+J50/J51 -> 2.0489429

Sheet INGRESOS
A2: MEMORIAS DE INGRESOS
A4: PROYECTO:
A5: SOCIEDAD
A6: BENEFICIARIOS:
A8: CONCEPTOS | B8: INGRESOS POR VENTA MENSUAL AÑO 1 | P8: Tabla de precios | R8: Primer semestre | S8: Segundo semestre | T8: Año 2 | U8: Año 3 | V8: Año 4 | W8: Año 5 | X8: Año 6
A9: MES | B9: 1 | C9: 2 | D9: 3 | E9: 4 | F9: 5 | G9: 6 | H9: 7 | I9: 8 | J9: 9 | K9: 10 | L9: 11 | M9: 12 | N9: TOTAL | P9: {=A11:A16} -> Cerveza Regia | R9: 97.5 | S9: =R9*1.09 -> 106.275 | T9: =S9*1.09 -> 115.83975 | U9: =T9*1.09 -> 126.26533 | V9: =U9*1.09 -> 137.62921 | W9: =V9*1.09 -> 150.01584 | X9: =W9*1.09 -> 163.51726
A10: VENTAS segun el producto | N10: ANUAL | P10: Cerveza Golden | R10: 97.5 | S10: =R10*1.09 -> 106.275 | T10: =S10*1.09 -> 115.83975 | U10: =T10*1.09 -> 126.26533 | V10: =U10*1.09 -> 137.62921 | W10: =V10*1.09 -> 150.01584 | X10: =W10*1.09 -> 163.51726
A11: Cerveza Regia | B11: =498.33*97.5 -> 48587.175 | C11: =498.33*97.5 -> 48587.175 | D11: =498.33*97.5 -> 48587.175 | E11: =498.33*97.5 -> 48587.175 | F11: =498.33*97.5 -> 48587.175 | G11: =498.33*97.5 -> 48587.175 | H11: =498.33*$S$9 -> 52960.021 | I11: =498.33*$S$9 -> 52960.021 | J11: =498.33*$S$9 -> 52960.021 | K11: =498.33*$S$9 -> 52960.021 | L11: =498.33*$S$9 -> 52960.021 | M11: =498.33*$S$9 -> 52960.021 | P11: Cerveza Honey | R11: 97.5 | S11: =R11*1.09 -> 106.275 | T11: =S11*1.09 -> 115.83975 | U11: =T11*1.09 -> 126.26533 | V11: =U11*1.09 -> 137.62921 | W11: =V11*1.09 -> 150.01584 | X11: =W11*1.09 -> 163.51726
A12: Cerveza Golden | B12: =498.33*97.5 -> 48587.175 | C12: =498.33*97.5 -> 48587.175 | D12: =498.33*97.5 -> 48587.175 | E12: =498.33*97.5 -> 48587.175 | F12: =498.33*97.5 -> 48587.175 | G12: =498.33*97.5 -> 48587.175 | H12: =498.33*$S$9 -> 52960.021 | I12: =498.33*$S$9 -> 52960.021 | J12: =498.33*$S$9 -> 52960.021 | K12: =498.33*$S$9 -> 52960.021 | L12: =498.33*$S$9 -> 52960.021 | M12: =498.33*$S$9 -> 52960.021 | P12: Cerveza Milf | R12: 97.5 | S12: =R12*1.09 -> 106.275 | T12: =S12*1.09 -> 115.83975 | U12: =T12*1.09 -> 126.26533 | V12: =U12*1.09 -> 137.62921 | W12: =V12*1.09 -> 150.01584 | X12: =W12*1.09 -> 163.51726
A13: Cerveza Honey | B13: =498.33*97.5 -> 48587.175 | C13: =498.33*97.5 -> 48587.175 | D13: =498.33*97.5 -> 48587.175 | E13: =498.33*97.5 -> 48587.175 | F13: =498.33*97.5 -> 48587.175 | G13: =498.33*97.5 -> 48587.175 | H13: =498.33*$S$9 -> 52960.021 | I13: =498.33*$S$9 -> 52960.021 | J13: =498.33*$S$9 -> 52960.021 | K13: =498.33*$S$9 -> 52960.021 | L13: =498.33*$S$9 -> 52960.021 | M13: =498.33*$S$9 -> 52960.021 | P13: Cerveza Dark | R13: 97.5 | S13: =R13*1.09 -> 106.275 | T13: =S13*1.09 -> 115.83975 | U13: =T13*1.09 -> 126.26533 | V13: =U13*1.09 -> 137.62921 | W13: =V13*1.09 -> 150.01584 | X13: =W13*1.09 -> 163.51726
A14: Cerveza Milf | B14: =498.33*97.5 -> 48587.175 | C14: =498.33*97.5 -> 48587.175 | D14: =498.33*97.5 -> 48587.175 | E14: =498.33*97.5 -> 48587.175 | F14: =498.33*97.5 -> 48587.175 | G14: =498.33*97.5 -> 48587.175 | H14: =498.33*$S$9 -> 52960.021 | I14: =498.33*$S$9 -> 52960.021 | J14: =498.33*$S$9 -> 52960.021 | K14: =498.33*$S$9 -> 52960.021 | L14: =498.33*$S$9 -> 52960.021 | M14: =498.33*$S$9 -> 52960.021 | P14: Cerveza Ver-got | R14: 97.5 | S14: =R14*1.09 -> 106.275 | T14: =S14*1.09 -> 115.83975 | U14: =T14*1.09 -> 126.26533 | V14: =U14*1.09 -> 137.62921 | W14: =V14*1.09 -> 150.01584 | X14: =W14*1.09 -> 163.51726
A15: Cerveza Dark | B15: =498.33*97.5 -> 48587.175 | C15: =498.33*97.5 -> 48587.175 | D15: =498.33*97.5 -> 48587.175 | E15: =498.33*97.5 -> 48587.175 | F15: =498.33*97.5 -> 48587.175 | G15: =498.33*97.5 -> 48587.175 | H15: =498.33*$S$9 -> 52960.021 | I15: =498.33*$S$9 -> 52960.021 | J15: =498.33*$S$9 -> 52960.021 | K15: =498.33*$S$9 -> 52960.021 | L15: =498.33*$S$9 -> 52960.021 | M15: =498.33*$S$9 -> 52960.021
A16: Cerveza Ver-got | B16: =498.33*97.5 -> 48587.175 | C16: =498.33*97.5 -> 48587.175 | D16: =498.33*97.5 -> 48587.175 | E16: =498.33*97.5 -> 48587.175 | F16: =498.33*97.5 -> 48587.175 | G16: =498.33*97.5 -> 48587.175 | H16: =498.33*$S$9 -> 52960.021 | I16: =498.33*$S$9 -> 52960.021 | J16: =498.33*$S$9 -> 52960.021 | K16: =498.33*$S$9 -> 52960.021 | L16: =498.33*$S$9 -> 52960.021 | M16: =498.33*$S$9 -> 52960.021
A17: TOTAL DE INGRESOS | B17: =SUM(B11:B16) -> 291523.05 | C17: =SUM(C11:C16) -> 291523.05 | D17: =SUM(D11:D16) -> 291523.05 | E17: =SUM(E11:E16) -> 291523.05 | F17: =SUM(F11:F16) -> 291523.05 | G17: =SUM(G11:G16) -> 291523.05 | H17: =SUM(H11:H16) -> 317760.12 | I17: =SUM(I11:I16) -> 317760.12 | ... M17: =SUM(M11:M16) -> 317760.12 | N17: =SUM(B17:M17) -> 3655699
A20: CONCEPTOS | B20: INGRESOS POR VENTA MENSUAL AÑO 2
A21: MES | B21: =B9 -> 1 | C21: =C9 -> 2 | D21: =D9 -> 3 | E21: =E9 -> 4 | F21: =F9 -> 5 | G21: =G9 -> 6 | H21: =H9 -> 7 | I21: =I9 -> 8 | ... M21: =M9 -> 12
A22: VENTAS segun el producto
A23: Cerveza Regia | B23: =498.33*$T$9 -> 57726.423 | C23: =498.33*$T$9 -> 57726.423 | D23: =498.33*$T$9 -> 57726.423 | E23: =498.33*$T$9 -> 57726.423 | F23: =498.33*$T$9 -> 57726.423 | G23: =498.33*$T$9 -> 57726.423 | H23: =498.33*$T$9 -> 57726.423 | I23: =498.33*$T$9 -> 57726.423 | ... M23: =498.33*$T$9 -> 57726.423 | N23: =SUM(B23:M23) -> 692717.07
A24: Cerveza Golden | B24: =498.33*$T$9 -> 57726.423 | C24: =498.33*$T$9 -> 57726.423 | D24: =498.33*$T$9 -> 57726.423 | E24: =498.33*$T$9 -> 57726.423 | F24: =498.33*$T$9 -> 57726.423 | G24: =498.33*$T$9 -> 57726.423 | H24: =498.33*$T$9 -> 57726.423 | I24: =498.33*$T$9 -> 57726.423 | ... M24: =498.33*$T$9 -> 57726.423 | N24: =SUM(B24:M24) -> 692717.07
A25: Cerveza Honey | B25: =498.33*$T$9 -> 57726.423 | C25: =498.33*$T$9 -> 57726.423 | D25: =498.33*$T$9 -> 57726.423 | E25: =498.33*$T$9 -> 57726.423 | F25: =498.33*$T$9 -> 57726.423 | G25: =498.33*$T$9 -> 57726.423 | H25: =498.33*$T$9 -> 57726.423 | I25: =498.33*$T$9 -> 57726.423 | ... M25: =498.33*$T$9 -> 57726.423 | N25: =SUM(B25:M25) -> 692717.07
A26: Cerveza Milf | B26: =498.33*$T$9 -> 57726.423 | C26: =498.33*$T$9 -> 57726.423 | D26: =498.33*$T$9 -> 57726.423 | E26: =498.33*$T$9 -> 57726.423 | F26: =498.33*$T$9 -> 57726.423 | G26: =498.33*$T$9 -> 57726.423 | H26: =498.33*$T$9 -> 57726.423 | I26: =498.33*$T$9 -> 57726.423 | ... M26: =498.33*$T$9 -> 57726.423 | N26: =SUM(B26:M26) -> 692717.07
A27: Cerveza Dark | B27: =498.33*$T$9 -> 57726.423 | C27: =498.33*$T$9 -> 57726.423 | D27: =498.33*$T$9 -> 57726.423 | E27: =498.33*$T$9 -> 57726.423 | F27: =498.33*$T$9 -> 57726.423 | G27: =498.33*$T$9 -> 57726.423 | H27: =498.33*$T$9 -> 57726.423 | I27: =498.33*$T$9 -> 57726.423 | ... M27: =498.33*$T$9 -> 57726.423 | N27: =SUM(B27:M27) -> 692717.07
A28: Cerveza Ver-got | B28: =498.33*$T$9 -> 57726.423 | C28: =498.33*$T$9 -> 57726.423 | D28: =498.33*$T$9 -> 57726.423 | E28: =498.33*$T$9 -> 57726.423 | F28: =498.33*$T$9 -> 57726.423 | G28: =498.33*$T$9 -> 57726.423 | H28: =498.33*$T$9 -> 57726.423 | I28: =498.33*$T$9 -> 57726.423 | ... M28: =498.33*$T$9 -> 57726.423 | N28: =SUM(B28:M28) -> 692717.07
A29: TOTAL DE INGRESOS | B29: =SUM(B23:B28) -> 346358.54 | C29: =SUM(C23:C28) -> 346358.54 | D29: =SUM(D23:D28) -> 346358.54 | E29: =SUM(E23:E28) -> 346358.54 | F29: =SUM(F23:F28) -> 346358.54 | G29: =SUM(G23:G28) -> 346358.54 | H29: =SUM(H23:H28) -> 346358.54 | I29: =SUM(I23:I28) -> 346358.54 | ... N29: =SUM(N23:N28) -> 4156302.4
A32: CONCEPTOS | B32: INGRESOS POR VENTA MENSUAL AÑO 3
A33: MES
A34: VENTAS segun el producto
A35: Cerveza Regia | B35: =498.33*$U$9 -> 62921.801 | C35: =498.33*$U$9 -> 62921.801 | D35: =498.33*$U$9 -> 62921.801 | E35: =498.33*$U$9 -> 62921.801 | F35: =498.33*$U$9 -> 62921.801 | G35: =498.33*$U$9 -> 62921.801 | H35: =498.33*$U$9 -> 62921.801 | I35: =498.33*$U$9 -> 62921.801 | ... M35: =498.33*$U$9 -> 62921.801 | N35: =SUM(B35:M35) -> 755061.61
A36: Cerveza Golden | B36: =498.33*$U$9 -> 62921.801 | C36: =498.33*$U$9 -> 62921.801 | D36: =498.33*$U$9 -> 62921.801 | E36: =498.33*$U$9 -> 62921.801 | F36: =498.33*$U$9 -> 62921.801 | G36: =498.33*$U$9 -> 62921.801 | H36: =498.33*$U$9 -> 62921.801 | I36: =498.33*$U$9 -> 62921.801 | ... M36: =498.33*$U$9 -> 62921.801 | N36: =SUM(B36:M36) -> 755061.61
A37: Cerveza Honey | B37: =498.33*$U$9 -> 62921.801 | C37: =498.33*$U$9 -> 62921.801 | D37: =498.33*$U$9 -> 62921.801 | E37: =498.33*$U$9 -> 62921.801 | F37: =498.33*$U$9 -> 62921.801 | G37: =498.33*$U$9 -> 62921.801 | H37: =498.33*$U$9 -> 62921.801 | I37: =498.33*$U$9 -> 62921.801 | ... M37: =498.33*$U$9 -> 62921.801 | N37: =SUM(B37:M37) -> 755061.61
A38: Cerveza Milf | B38: =498.33*$U$9 -> 62921.801 | C38: =498.33*$U$9 -> 62921.801 | D38: =498.33*$U$9 -> 62921.801 | E38: =498.33*$U$9 -> 62921.801 | F38: =498.33*$U$9 -> 62921.801 | G38: =498.33*$U$9 -> 62921.801 | H38: =498.33*$U$9 -> 62921.801 | I38: =498.33*$U$9 -> 62921.801 | ... M38: =498.33*$U$9 -> 62921.801 | N38: =SUM(B38:M38) -> 755061.61
A39: Cerveza Dark | B39: =498.33*$U$9 -> 62921.801 | C39: =498.33*$U$9 -> 62921.801 | D39: =498.33*$U$9 -> 62921.801 | E39: =498.33*$U$9 -> 62921.801 | F39: =498.33*$U$9 -> 62921.801 | G39: =498.33*$U$9 -> 62921.801 | H39: =498.33*$U$9 -> 62921.801 | I39: =498.33*$U$9 -> 62921.801 | ... M39: =498.33*$U$9 -> 62921.801 | N39: =SUM(B39:M39) -> 755061.61
A40: Cerveza Ver-got | B40: =498.33*$U$9 -> 62921.801 | C40: =498.33*$U$9 -> 62921.801 | D40: =498.33*$U$9 -> 62921.801 | E40: =498.33*$U$9 -> 62921.801 | F40: =498.33*$U$9 -> 62921.801 | G40: =498.33*$U$9 -> 62921.801 | H40: =498.33*$U$9 -> 62921.801 | I40: =498.33*$U$9 -> 62921.801 | ... M40: =498.33*$U$9 -> 62921.801 | N40: =SUM(B40:M40) -> 755061.61
A41: TOTAL DE INGRESOS | B41: =SUM(B35:B40) -> 377530.8 | C41: =SUM(C35:C40) -> 377530.8 | D41: =SUM(D35:D40) -> 377530.8 | E41: =SUM(E35:E40) -> 377530.8 | F41: =SUM(F35:F40) -> 377530.8 | G41: =SUM(G35:G40) -> 377530.8 | H41: =SUM(H35:H40) -> 377530.8 | I41: =SUM(I35:I40) -> 377530.8 | ... N41: =SUM(N35:N40) -> 4530369.6
A44: CONCEPTOS | B44: INGRESOS POR VENTA MENSUAL AÑO 4
A45: MES
A46: VENTAS segun el producto
A47: Cerveza Regia | B47: =498.33*$V$9 -> 68584.763 | C47: =498.33*$V$9 -> 68584.763 | D47: =498.33*$V$9 -> 68584.763 | E47: =498.33*$V$9 -> 68584.763 | F47: =498.33*$V$9 -> 68584.763 | G47: =498.33*$V$9 -> 68584.763 | H47: =498.33*$V$9 -> 68584.763 | I47: =498.33*$V$9 -> 68584.763 | ... M47: =498.33*$V$9 -> 68584.763 | N47: =SUM(B47:M47) -> 823017.15
A48: Cerveza Golden | B48: =498.33*$V$9 -> 68584.763 | C48: =498.33*$V$9 -> 68584.763 | D48: =498.33*$V$9 -> 68584.763 | E48: =498.33*$V$9 -> 68584.763 | F48: =498.33*$V$9 -> 68584.763 | G48: =498.33*$V$9 -> 68584.763 | H48: =498.33*$V$9 -> 68584.763 | I48: =498.33*$V$9 -> 68584.763 | ... M48: =498.33*$V$9 -> 68584.763 | N48: =SUM(B48:M48) -> 823017.15
A49: Cerveza Honey | B49: =498.33*$V$9 -> 68584.763 | C49: =498.33*$V$9 -> 68584.763 | D49: =498.33*$V$9 -> 68584.763 | E49: =498.33*$V$9 -> 68584.763 | F49: =498.33*$V$9 -> 68584.763 | G49: =498.33*$V$9 -> 68584.763 | H49: =498.33*$V$9 -> 68584.763 | I49: =498.33*$V$9 -> 68584.763 | ... M49: =498.33*$V$9 -> 68584.763 | N49: =SUM(B49:M49) -> 823017.15
A50: Cerveza Milf | B50: =498.33*$V$9 -> 68584.763 | C50: =498.33*$V$9 -> 68584.763 | D50: =498.33*$V$9 -> 68584.763 | E50: =498.33*$V$9 -> 68584.763 | F50: =498.33*$V$9 -> 68584.763 | G50: =498.33*$V$9 -> 68584.763 | H50: =498.33*$V$9 -> 68584.763 | I50: =498.33*$V$9 -> 68584.763 | ... M50: =498.33*$V$9 -> 68584.763 | N50: =SUM(B50:M50) -> 823017.15
A51: Cerveza Dark | B51: =498.33*$V$9 -> 68584.763 | C51: =498.33*$V$9 -> 68584.763 | D51: =498.33*$V$9 -> 68584.763 | E51: =498.33*$V$9 -> 68584.763 | F51: =498.33*$V$9 -> 68584.763 | G51: =498.33*$V$9 -> 68584.763 | H51: =498.33*$V$9 -> 68584.763 | I51: =498.33*$V$9 -> 68584.763 | ... M51: =498.33*$V$9 -> 68584.763 | N51: =SUM(B51:M51) -> 823017.15
A52: Cerveza Ver-got | B52: =498.33*$V$9 -> 68584.763 | C52: =498.33*$V$9 -> 68584.763 | D52: =498.33*$V$9 -> 68584.763 | E52: =498.33*$V$9 -> 68584.763 | F52: =498.33*$V$9 -> 68584.763 | G52: =498.33*$V$9 -> 68584.763 | H52: =498.33*$V$9 -> 68584.763 | I52: =498.33*$V$9 -> 68584.763 | ... M52: =498.33*$V$9 -> 68584.763 | N52: =SUM(B52:M52) -> 823017.15
A53: TOTAL DE INGRESOS | B53: =SUM(B47:B52) -> 411508.58 | C53: =SUM(C47:C52) -> 411508.58 | D53: =SUM(D47:D52) -> 411508.58 | E53: =SUM(E47:E52) -> 411508.58 | F53: =SUM(F47:F52) -> 411508.58 | G53: =SUM(G47:G52) -> 411508.58 | H53: =SUM(H47:H52) -> 411508.58 | I53: =SUM(I47:I52) -> 411508.58 | ... N53: =SUM(N47:N52) -> 4938102.9
A56: CONCEPTOS | B56: INGRESOS POR VENTA MENSUAL AÑO 5
A57: MES
A58: VENTAS segun el producto
A59: Cerveza Regia | B59: =498.33*$W$9 -> 74757.391 | C59: =498.33*$W$9 -> 74757.391 | D59: =498.33*$W$9 -> 74757.391 | E59: =498.33*$W$9 -> 74757.391 | F59: =498.33*$W$9 -> 74757.391 | G59: =498.33*$W$9 -> 74757.391 | H59: =498.33*$W$9 -> 74757.391 | I59: =498.33*$W$9 -> 74757.391 | ... M59: =498.33*$W$9 -> 74757.391 | N59: =SUM(B59:M59) -> 897088.7
A60: Cerveza Golden | B60: =498.33*$W$9 -> 74757.391 | C60: =498.33*$W$9 -> 74757.391 | D60: =498.33*$W$9 -> 74757.391 | E60: =498.33*$W$9 -> 74757.391 | F60: =498.33*$W$9 -> 74757.391 | G60: =498.33*$W$9 -> 74757.391 | H60: =498.33*$W$9 -> 74757.391 | I60: =498.33*$W$9 -> 74757.391 | ... M60: =498.33*$W$9 -> 74757.391 | N60: =SUM(B60:M60) -> 897088.7
A61: Cerveza Honey | B61: =498.33*$W$9 -> 74757.391 | C61: =498.33*$W$9 -> 74757.391 | D61: =498.33*$W$9 -> 74757.391 | E61: =498.33*$W$9 -> 74757.391 | F61: =498.33*$W$9 -> 74757.391 | G61: =498.33*$W$9 -> 74757.391 | H61: =498.33*$W$9 -> 74757.391 | I61: =498.33*$W$9 -> 74757.391 | ... M61: =498.33*$W$9 -> 74757.391 | N61: =SUM(B61:M61) -> 897088.7
A62: Cerveza Milf | B62: =498.33*$W$9 -> 74757.391 | C62: =498.33*$W$9 -> 74757.391 | D62: =498.33*$W$9 -> 74757.391 | E62: =498.33*$W$9 -> 74757.391 | F62: =498.33*$W$9 -> 74757.391 | G62: =498.33*$W$9 -> 74757.391 | H62: =498.33*$W$9 -> 74757.391 | I62: =498.33*$W$9 -> 74757.391 | ... M62: =498.33*$W$9 -> 74757.391 | N62: =SUM(B62:M62) -> 897088.7
A63: Cerveza Dark | B63: =498.33*$W$9 -> 74757.391 | C63: =498.33*$W$9 -> 74757.391 | D63: =498.33*$W$9 -> 74757.391 | E63: =498.33*$W$9 -> 74757.391 | F63: =498.33*$W$9 -> 74757.391 | G63: =498.33*$W$9 -> 74757.391 | H63: =498.33*$W$9 -> 74757.391 | I63: =498.33*$W$9 -> 74757.391 | ... M63: =498.33*$W$9 -> 74757.391 | N63: =SUM(B63:M63) -> 897088.7
A64: Cerveza Ver-got | B64: =498.33*$W$9 -> 74757.391 | C64: =498.33*$W$9 -> 74757.391 | D64: =498.33*$W$9 -> 74757.391 | E64: =498.33*$W$9 -> 74757.391 | F64: =498.33*$W$9 -> 74757.391 | G64: =498.33*$W$9 -> 74757.391 | H64: =498.33*$W$9 -> 74757.391 | I64: =498.33*$W$9 -> 74757.391 | ... M64: =498.33*$W$9 -> 74757.391 | N64: =SUM(B64:M64) -> 897088.7
A65: TOTAL DE INGRESOS | B65: =SUM(B59:B64) -> 448544.35 | C65: =SUM(C59:C64) -> 448544.35 | D65: =SUM(D59:D64) -> 448544.35 | E65: =SUM(E59:E64) -> 448544.35 | F65: =SUM(F59:F64) -> 448544.35 | G65: =SUM(G59:G64) -> 448544.35 | H65: =SUM(H59:H64) -> 448544.35 | I65: =SUM(I59:I64) -> 448544.35 | ... N65: =SUM(N59:N64) -> 5382532.2
A68: CONCEPTOS | B68: INGRESOS POR VENTA MENSUAL AÑO 5
A69: MES
A70: VENTAS segun el producto
A71: Cerveza Regia | B71: =498.33*$X$9 -> 81485.557 | C71: =498.33*$X$9 -> 81485.557 | D71: =498.33*$X$9 -> 81485.557 | E71: =498.33*$X$9 -> 81485.557 | F71: =498.33*$X$9 -> 81485.557 | G71: =498.33*$X$9 -> 81485.557 | H71: =498.33*$X$9 -> 81485.557 | I71: =498.33*$X$9 -> 81485.557 | ... M71: =498.33*$X$9 -> 81485.557 | N71: =SUM(B71:M71) -> 977826.68
A72: Cerveza Golden | B72: =498.33*$X$9 -> 81485.557 | C72: =498.33*$X$9 -> 81485.557 | D72: =498.33*$X$9 -> 81485.557 | E72: =498.33*$X$9 -> 81485.557 | F72: =498.33*$X$9 -> 81485.557 | G72: =498.33*$X$9 -> 81485.557 | H72: =498.33*$X$9 -> 81485.557 | I72: =498.33*$X$9 -> 81485.557 | ... M72: =498.33*$X$9 -> 81485.557 | N72: =SUM(B72:M72) -> 977826.68
A73: Cerveza Honey | B73: =498.33*$X$9 -> 81485.557 | C73: =498.33*$X$9 -> 81485.557 | D73: =498.33*$X$9 -> 81485.557 | E73: =498.33*$X$9 -> 81485.557 | F73: =498.33*$X$9 -> 81485.557 | G73: =498.33*$X$9 -> 81485.557 | H73: =498.33*$X$9 -> 81485.557 | I73: =498.33*$X$9 -> 81485.557 | ... M73: =498.33*$X$9 -> 81485.557 | N73: =SUM(B73:M73) -> 977826.68
A74: Cerveza Milf | B74: =498.33*$X$9 -> 81485.557 | C74: =498.33*$X$9 -> 81485.557 | D74: =498.33*$X$9 -> 81485.557 | E74: =498.33*$X$9 -> 81485.557 | F74: =498.33*$X$9 -> 81485.557 | G74: =498.33*$X$9 -> 81485.557 | H74: =498.33*$X$9 -> 81485.557 | I74: =498.33*$X$9 -> 81485.557 | ... M74: =498.33*$X$9 -> 81485.557 | N74: =SUM(B74:M74) -> 977826.68
A75: Cerveza Dark | B75: =498.33*$X$9 -> 81485.557 | C75: =498.33*$X$9 -> 81485.557 | D75: =498.33*$X$9 -> 81485.557 | E75: =498.33*$X$9 -> 81485.557 | F75: =498.33*$X$9 -> 81485.557 | G75: =498.33*$X$9 -> 81485.557 | H75: =498.33*$X$9 -> 81485.557 | I75: =498.33*$X$9 -> 81485.557 | ... M75: =498.33*$X$9 -> 81485.557 | N75: =SUM(B75:M75) -> 977826.68
A76: Cerveza Ver-got | B76: =498.33*$X$9 -> 81485.557 | C76: =498.33*$X$9 -> 81485.557 | D76: =498.33*$X$9 -> 81485.557 | E76: =498.33*$X$9 -> 81485.557 | F76: =498.33*$X$9 -> 81485.557 | G76: =498.33*$X$9 -> 81485.557 | H76: =498.33*$X$9 -> 81485.557 | I76: =498.33*$X$9 -> 81485.557 | ... M76: =498.33*$X$9 -> 81485.557 | N76: =SUM(B76:M76) -> 977826.68
A77: TOTAL DE INGRESOS | B77: =SUM(B71:B76) -> 488913.34 | C77: =SUM(C71:C76) -> 488913.34 | D77: =SUM(D71:D76) -> 488913.34 | E77: =SUM(E71:E76) -> 488913.34 | F77: =SUM(F71:F76) -> 488913.34 | G77: =SUM(G71:G76) -> 488913.34 | H77: =SUM(H71:H76) -> 488913.34 | I77: =SUM(I71:I76) -> 488913.34 | ... N77: =SUM(N71:N76) -> 5866960.1

Sheet TIR - VAN
B2: VAN, TIR Y B/C
C4: TASA DE ACTUALIZACIÓN | F4: 0.15
C6: AÑO | D6: INGRESOS | E6: Remanente | F6: COSTOS | G6: FLUJO DE EFECTIVO | H6: TASA | I6: INGRESOS | J6: EGRESOS
H7: (1+t)-n | I7: ACTUALIZADOS | J7: ACTUALIZADOS
C8: 0 | D8: ='PROYECCIONES EGRESOS E INGRESOS'!B7 -> 3655699 | F8: =COSTOS!N29 -> 1730377.5 | G8: =D8-F8 -> 1925321.5 | H8: =1/(1+$F$4)^C8 -> 1 | I8: =H8*D8 -> 3655699 | J8: =H8*F8 -> 1730377.5
C9: 1 | D9: =INGRESOS!N29 -> 4156302.4 | F9: =COSTOS!N44 -> 1741856.3 | G9: =D9-F9 -> 2414446.2 | H9: =1/(1+$F$4)^C9 -> 0.86956522 | I9: =H9*D9 -> 3614176 | J9: =H9*F9 -> 1514657.6 | K9: =I9/J9 -> 2.386134
C10: 2 | D10: =INGRESOS!N41 -> 4530369.6 | F10: =COSTOS!N57 -> 1753426.1 | G10: =D10-F10 -> 2776943.5 | H10: =1/(1+$F$4)^C10 -> 0.75614367 | I10: =H10*D10 -> 3425610.3 | J10: =H10*F10 -> 1325842.1 | K10: =I10/J10 -> 2.5837243
C11: 3 | D11: =INGRESOS!N53 -> 4938102.9 | F11: =COSTOS!N70 -> 1765087.8 | G11: =D11-F11 -> 3173015.1 | H11: =1/(1+$F$4)^C11 -> 0.65751623 | I11: =H11*D11 -> 3246882.8 | J11: =H11*F11 -> 1160573.9 | K11: =I11/J11 -> 2.7976528
C12: 4 | D12: =INGRESOS!N65 -> 5382532.2 | F12: =COSTOS!N83 -> 1776842.1 | G12: =D12-F12 -> 3605690.1 | H12: =1/(1+$F$4)^C12 -> 0.57175325 | I12: =H12*D12 -> 3077480.2 | J12: =H12*F12 -> 1015915.2 | K12: =I12/J12 -> 3.0292687
C13: 5 | D13: =INGRESOS!N77 -> 5866960.1 | E13: =DEPRECIACIONES!H30+DEPRECIACIONES!H18 -> 113200 | F13: =COSTOS!N97 -> 1788689.7 | G13: =D13+E13-F13 -> 4191470.3 | H13: =1/(1+$F$4)^C13 -> 0.49717674 | I13: =H13*D13+E13 -> 3030116.1 | J13: =H13*F13 -> 889294.92 | K13: =I13/J13 -> 3.4073241
C14: TOTAL | D14: =SUM(D8:D13) -> 28529966 | F14: =SUM(F8:F13) -> 10556280 | G14: =SUM(G8:G13) -> 18086887 | I14: =SUM(I8:I13)+DEPRECIACIONES!H30+DEPRECIACIONES!H18 -> 20163165 | J14: =SUM(J8:J13) -> 7636661.2 | K14: =SUM(K9:K13) -> 14.204104
G17: VAN | H17: =I14-J14 -> 12526503
G18: TIR | H18: 0.15
G19: B/C | H19: =I14/J14 -> 2.6403115

Sheet Balanza Proforma
A2: +
A3: BALANCE GENERAL PROFORMA | C3: SALDO ANTIGUO | F3: AJUSTES | I3: SALDO NUEVO | L3: ASIENTOS
A4: CONCEPTO FIJO | B4: AÑO 1 | C4: D | D4: H | F4: D | G4: H | L4: CONCEPTO | M4: D | N4: H | P4: ventas | Q4: =N13 -> 3655699
A5: ACTIVO CIRCULANTE | L5: 1 | P5: cv | Q5: =M21 -> 1730377.5
A6: Caja | C6: ='Estados Financieros '!C34 -> 13500 | L6: BANCOS | M6: ='ESTRUCTURA FINANCIERA'!F30 -> 759000 | P6: ub | Q6: =Q4-Q5 -> 1925321.5
A7: ='Estados Financieros '!B35 -> Bancos | C7: ='Estados Financieros '!C35 -> 894300.06 | I7: =C7+F8+F10-G9-G11-G12-G13-G14-G15+C6 -> 1922922.5 | L7: DOCUMENTOS POR PAGAR L.P. | N7: =M6 -> 759000 | P7: ga | Q7: =M15 -> 350600.52
E8: 1) | F8: =M6 -> 759000 | L8: 2 | P8: gv | Q8: ='M. DE CALCULO DE GASTOS FIJOS'!E41+M30 -> 275299.48
G9: =N10 -> 759000 | H9: 2) | L9: MAQUINARIA Y EQUIPO | M9: =M6 -> 759000 | P9: u de op | Q9: =Q6-Q7-Q8 -> 1299421.5
E10: 3) | F10: =M12 -> 3655699 | L10: BANCOS | N10: =M6 -> 759000
G11: =N16 -> 350600.52 | H11: 4) | L11: 3 | P11: gf | Q11: =M27 -> 160449.19
G12: =N25 -> 199749.96 | H12: 5) | L12: BANCOS | M12: ='PROYECCIONES EGRESOS E INGRESOS'!B7 -> 3655699 | Q12: =Q9-Q11 -> 1138972.4
G13: =N22 -> 1730377.5 | H13: 6) | L13: VENTAS | N13: =M12 -> 3655699 | P13: impuestos
G14: =N19 -> 199399.48 | H14: 7) | L14: 4 | P14: ptu | Q14: =Q12*0.1 -> 113897.24
G15: =N28 -> 160449.19 | H15: 8) | L15: GASTOS DE ADMINISTRACIÓN | M15: ='M. DE CALCULO DE GASTOS FIJOS'!E33 -> 350600.52 | P15: isr | Q15: =Q12*0.3 -> 341691.71
A16: ='Estados Financieros '!B36 -> Clientes | C16: ='Estados Financieros '!C36 -> 315000 | I16: =C16 -> 315000 | L16: BANCOS | N16: =M15 -> 350600.52 | P16: UTIL NETA | Q16: =Q12-Q14-Q15 -> 683383.41
A17: ='Estados Financieros '!B37 -> Deudores diversos | C17: ='Estados Financieros '!C37 -> 85000 | I17: =C17 -> 85000 | L17: 5
A18: ='Estados Financieros '!B38 -> Inventarios PT | C18: ='Estados Financieros '!C38 -> 150000 | I18: =C18 -> 150000 | L18: GASTOS DE VENTAS | M18: ='M. DE CALCULO DE GASTOS FIJOS'!E41 -> 199399.48
A19: ='Estados Financieros '!B39 -> Inventarios MP | C19: ='Estados Financieros '!C39 -> 140000 | I19: =C19 -> 140000 | L19: BANCOS | N19: =M18 -> 199399.48 | Q19: P y G
A20: ='Estados Financieros '!B40 -> Inventarios PP | C20: ='Estados Financieros '!C40 -> 50000 | I20: =C20 -> 50000 | L20: 6 | P20: 12) | Q20: =M39 -> 350600.52 | R20: =N37 -> 1925321.5 | S20: (11
A21: Total activo circulante | B21: =SUM(C6:C20) -> 1647800.1 | L21: COSTOS DE VENTAS | M21: ='PROYECCIONES EGRESOS E INGRESOS'!B10 -> 1730377.5 | P21: 13) | Q21: =M42 -> 275299.48
A22: ACTIVO FIJO | L22: BANCOS | N22: =M21 -> 1730377.5 | P22: 14) | Q22: =M45 -> 160449.19
A23: Terrreno | C23: ='Estados Financieros '!C43 -> 1450000 | I23: =C23 -> 1450000 | L23: 7 | P23: 15) | Q23: =M48 -> 455588.94
A24: ='Estados Financieros '!B44 -> Edificio | C24: ='Estados Financieros '!C44 -> 1050000 | I24: =C24 -> 1050000 | L24: DOCUMENTOS POR PAGAR L.P. | M24: ='PROYECCIONES EGRESOS E INGRESOS'!B15 -> 199749.96 | Q24: =SUM(Q20:Q23) -> 1241938.1
A25: Maquinaria y equipo | C25: ='Estados Financieros '!C45 -> 1000000 | E25: 2) | F25: =M9 -> 759000 | I25: =C25+F25 -> 1759000 | L25: BANCOS | N25: =M24 -> 199749.96 | P25: 16) | Q25: =R20-Q24 -> 683383.41
L26: 8
A27: ='Estados Financieros '!B46 -> Mobiliario y equipo de oficina | C27: ='Estados Financieros '!C46 -> 200000 | I27: =C27 -> 200000 | L27: GASTOS FINANCIEROS (intereses) | M27: =SUM('AMORTIZACIONES (4 AÑOS)'!F9:F20) -> 160449.19
A28: ='Estados Financieros '!B47 -> Depreciación Acum. | D28: ='Estados Financieros '!C47 -> 1552500 | G28: =N31 -> 75900 | H28: 9) | J28: =D28+G28 -> 1628400 | L28: BANCOS | N28: =M27 -> 160449.19
L29: 9 | Q29: RES DEL EJERC
A30: TOTAL DE ACTIVO FIJO | B30: =SUM(C23:C28) -> 3700000 | L30: GASTOS DE VENTA | M30: =SUM(DEPRECIACIONES!E22:E29) -> 75900 | R30: =Q25 -> 683383.41 | S30: (16
A31: ACTIVO DIFERIDO | L31: DEP. ACUM. DE MAQUINARIA | N31: =M30 -> 75900
A32: ='Estados Financieros '!B50 -> Patentes | C32: ='Estados Financieros '!C50 -> 90000 | I32: =C32 -> 90000 | L32: 10
A33: ='Estados Financieros '!B51 -> Amortización acum. | D33: ='Estados Financieros '!C51 -> 81000 | J33: =D33 -> 81000 | L33: VENTAS | M33: ='TIR - VAN'!F8 -> 1730377.5
L34: CV | N34: ='TIR - VAN'!F8 -> 1730377.5
A35: TOTAL ACTIVO DIFERIDO | B35: =C32+D33 -> 171000 | L35: 11
A36: TOTAL ACTIVO | B36: =B21+C23+C25+C24+C27-D28+C32-D33 -> 3804300.1 | L36: VENTAS | M36: =Q6 -> 1925321.5
A37: PASIVO CIRCULANTE | L37: PERDIDAS Y GANANCIAS | N37: =M36 -> 1925321.5
A38: ='Estados Financieros '!D34 -> Documentos por pagar C.P | D38: ='Estados Financieros '!E34 -> 57000 | J38: =D38+G38-F38-C38 -> 57000 | L38: 12
A39: Intereses por pagar | L39: PERDIDAS Y GANANCIAS | M39: =Q7 -> 350600.52
A40: ='Estados Financieros '!D35 -> Proveedores | D40: ='Estados Financieros '!E35 -> 110800 | J40: =D40 -> 110800 | L40: GASTOS DE ADMINISTRACIÓN | N40: =M39 -> 350600.52
A41: ='Estados Financieros '!D36 -> Acreedores | D41: ='Estados Financieros '!E36 -> 109200 | J41: =D41 -> 109200 | L41: 13
A42: ='Estados Financieros '!D37 -> Impuestos por pagar | D42: ='Estados Financieros '!E37 -> 198319.88 | J42: =D42 -> 198319.88 | L42: PERDIDAS Y GANANCIAS | M42: =Q8 -> 275299.48
A43: ='Estados Financieros '!D38 -> Creaditos Bancarios | D43: ='Estados Financieros '!E38 -> 85500 | J43: =D43 -> 85500 | L43: GASTOS DE VENTA | N43: =M42 -> 275299.48
A44: ='Estados Financieros '!D39 -> Servicios por pagar | D44: ='Estados Financieros '!E39 -> 100000 | J44: =D44 -> 100000 | L44: 14
A45: TOTAL DE PASIVO CIRCULANTE | B45: =SUM(D38:D44) -> 660819.88 | L45: PERDIDAS Y GANANCIAS | M45: =Q11 -> 160449.19
A46: PASIVO A LARGO PLAZO | L46: GASTOS FINANCIEROS | N46: =M45 -> 160449.19
A47: ='Estados Financieros '!D42 -> Documentos por pagar L.P | D47: ='Estados Financieros '!E42 -> 423000 | E47: 7) | F47: =M24 -> 199749.96 | G47: =N10 -> 759000 | H47: 1) | J47: =D47+G47-F47 -> 982250.04 | L47: 15
L48: PERDIDAS Y GANANCIAS | M48: =Q14+Q15 -> 455588.94
A49: TOTAL PASIVO A LARGO PLAZO | B49: =D47 -> 423000 | L49: IMPUESTOS | N49: =M48 -> 455588.94
A50: TOTAL PASIVO | B50: =SUM(B45,B49) -> 1083819.9 | L50: 16
A51: CAPITAL CONTABLE | L51: PERDIDAS Y GANANCIAS | M51: =Q25 -> 683383.41
A52: ='Estados Financieros '!D45 -> Capital social | D52: ='Estados Financieros '!E45 -> 1567333.7 | J52: =D52 -> 1567333.7 | L52: RESULTADO DEL EJERC | N52: =Q25 -> 683383.41
A53: ='Estados Financieros '!D46 -> Reserva Legal | D53: ='Estados Financieros '!E46 -> 313466.73 | J53: =D53 -> 313466.73 | L53: 17
A54: ='Estados Financieros '!D47 -> Resultado de Ejercicios A. | D54: ='Estados Financieros '!E47 -> 252000 | G54: =N55 -> 337679.8 | H54: (17 | J54: =D54+G54 -> 589679.8 | L54: RES DEL EJERCICIO | M54: 337679.8
A55: ='Estados Financieros '!D48 -> Utilidades Retenidas | D55: ='Estados Financieros '!E48 -> 250000 | J55: =D55 -> 250000 | L55: RES DE EJERC ANTER | N55: =M54 -> 337679.8
A56: ='Estados Financieros '!D49 -> Utilidades del ejercicio | D56: ='Estados Financieros '!H49 -> 337679.8 | E56: 17) | F56: 337679.8 | G56: =N52 -> 683383.41 | H56: (16 | J56: =D56+G56-F56 -> 683383.41
A58: TOTAL CAPITAL CONTABLE | B58: =SUM(D52:D56) -> 2720480.2
A59: PASIVO + CAPITAL | B59: =B50+B58 -> 3804300.1
A60: Estado de resultados
A61: ='Estados Financieros '!G32 -> Ventas | G61: =N13 -> 3655699 | H61: 3) | J61: =G61-F62-F63 -> 0
E62: 10) | F62: =M33 -> 1730377.5
E63: 11) | F63: =M36 -> 1925321.5
A64: ='Estados Financieros '!G33 -> (-) Inventario Inicial
A65: ='Estados Financieros '!G34 -> (+)Compras
A66: ='Estados Financieros '!G35 -> (-)Inventario final
A67: ='Estados Financieros '!G36 -> (=)Costo de ventas | E67: 6) | F67: =M21 -> 1730377.5 | I67: =F67-G68 -> 0
G68: =N34 -> 1730377.5 | H68: 10)
A69: ='Estados Financieros '!G37 -> (=)Utilidad Bruta
A71: ='Estados Financieros '!G39 -> (-) Gastos de administración | E71: 4) | F71: =M15 -> 350600.52 | G71: =N40 -> 350600.52 | H71: 12) | I71: =F71-G71 -> 0
A73: ='Estados Financieros '!G40 -> (-) Gastos de venta | E73: 5) | F73: =M18 -> 199399.48 | G73: =Q8 -> 275299.48 | H73: (13 | I73: =F73+F74-G73 -> 0
E74: 9) | F74: =M30 -> 75900
A76: ='Estados Financieros '!G42 -> Utilidad de operación
A77: ='Estados Financieros '!G43 -> Gastos financieros | E77: 8) | F77: =M27 -> 160449.19 | G77: =N46 -> 160449.19 | H77: (14 | I77: =F77-G77 -> 0
A79: ='Estados Financieros '!G44 -> Utilidad antes de ISR y PTU
A80: IMPUESTOS | G80: =N49 -> 455588.94 | H80: (15 | J80: =G80 -> 455588.94
A81: ='Estados Financieros '!G46 -> (-)PTU (10%)
A82: ='Estados Financieros '!G47 -> (-) ISR (30%)
A84: PERDIDAS Y GANANCIAS | E84: 12) | F84: =M39 -> 350600.52 | G84: =N37 -> 1925321.5 | H84: (11 | I84: =F84+F85+F86+F87+F88-G84 -> 0.004
E85: 14) | F85: =M45 -> 160449.19
E86: 15) | F86: =M48 -> 455588.94
E87: 16) | F87: =M51 -> 683383.41
E88: 13) | F88: =275299.48 -> 275299.48
J89: =G89 -> 0
C90: =SUM(C5:C89) -> 5437800.1 | D90: =SUM(D5:D89) -> 5437800.1 | F90: =SUM(F5:F89) -> 13808876 | G90: =SUM(G5:G89) -> 13808876 | I90: =SUM(I5:I89) -> 7211922.5 | J90: =SUM(J5:J89) -> 7211922.5
D91: =C90-D90 -> -0.0040000007 | G91: =F90-G90 -> 0.0040000007 | J91: =I90-J90 -> 0
G92: =G91/2 -> 0.0020000003

Sheet Estados Financieros proyectados
B7: Estado de Situación Financiera de "Las Amarguitas S. de R.L." | I7: Estado de resultados de "Las Amarguitas S.de R.L."
B8: Al 31 de diciembre de 2025 | I8: Del 1 de Enero al 31 de Diciembre de 2025
B9: Activos | D9: Pasivo
B10: Circulantes | D10: Circulante | I10: Ventas | J10: ='Balanza Proforma'!G61 -> 3655699
B11: Caja | C11: ='Balanza Proforma'!C6 -> 13500 | D11: Documentos por pagar C.P | E11: ='Balanza Proforma'!J38 -> 57000 | I11: (+) Inventario Inicial | J11: 64,000,32
B12: Bancos | C12: ='Balanza Proforma'!I7 -> 1922922.5 | D12: Proveedores | E12: ='Balanza Proforma'!J40 -> 110800 | I12: (+)Compras | J12: =COSTOS!N36 -> 2134377.8
B13: Clientes | C13: ='Balanza Proforma'!I16 -> 315000 | D13: Acreedores | E13: ='Balanza Proforma'!J41 -> 109200 | I13: (-)Inventario final | J13: =C15+C16+C17 -> 340000 | L13: =J12-J13 -> 1794377.8
B14: Deudores diversos | C14: ='Balanza Proforma'!I17 -> 85000 | D14: Impuestos por pagar | E14: ='Balanza Proforma'!J80+'Balanza Proforma'!J42 -> 653908.82 | I14: (=)Costo de ventas | J14: ='Balanza Proforma'!F67 -> 1730377.5 | L14: =L13-J14 -> 64000.316
B15: Inventarios PT | C15: ='Balanza Proforma'!I18 -> 150000 | D15: Creaditos Bancarios | E15: ='Balanza Proforma'!J43 -> 85500 | I15: (=)Utilidad Bruta | J15: =J10-J14 -> 1925321.5
B16: Inventarios MP | C16: ='Balanza Proforma'!I19 -> 140000 | D16: Servicios por pagar | E16: ='Balanza Proforma'!J44 -> 100000
B17: Inventarios PP | C17: ='Balanza Proforma'!I20 -> 50000 | I17: (-) Gastos de administración | J17: ='Balanza Proforma'!F71 -> 350600.52
B18: Total de Activo Circulante | C18: =SUM(C11:C17) -> 2676422.5 | D18: Total de Pasivo C.P. | E18: =SUM(E11:E16) -> 1116408.8 | I18: (-) Gastos de venta | J18: ='Balanza Proforma'!F73+'Balanza Proforma'!F74 -> 275299.48
I19: Utilidad de operación | J19: =J15-J17-J18 -> 1299421.5
B20: Activo Fijo | D20: Pasivo No Circulante
B21: Terreno | C21: ='Balanza Proforma'!C23 -> 1450000 | D21: Documentos por pagar L.P | E21: ='Balanza Proforma'!J47 -> 982250.04 | I21: Gastos financieros | J21: ='Balanza Proforma'!F77 -> 160449.19
B22: Edificio | C22: ='Balanza Proforma'!C24 -> 1050000 | I22: Utilidad antes de ISR y PTU | J22: =J19-J21 -> 1138972.4
B23: Maquinaria y equipo | C23: ='Balanza Proforma'!I25 -> 1759000 | D23: Total de Pasivo C.L. | E23: =E21 -> 982250.04
B24: Mobiliario y equipo de oficina | C24: ='Balanza Proforma'!I27 -> 200000 | I24: (-)PTU (10%) | J24: ='Balanza Proforma'!Q14 -> 113897.24
B25: Depreciación Acum. | C25: ='Balanza Proforma'!J28 -> 1628400 | D25: Capital Contable | I25: (-) ISR (30%) | J25: ='Balanza Proforma'!Q15 -> 341691.71
B26: Total de Activo Fijo | C26: =SUM(C21:C24)-C25 -> 2830600 | D26: Capital social | E26: ='Balanza Proforma'!J52+'Balanza Proforma'!C6 -> 1580833.7
D27: Reserva Legal | E27: ='Balanza Proforma'!J53 -> 313466.73 | I27: Utilidad neta | J27: =J22-J24-J25 -> 683383.41
B28: Activo Diferido | D28: Resultado de Ejercicios A. | E28: ='Balanza Proforma'!J54 -> 589679.8
B29: Patentes | C29: ='Balanza Proforma'!I32 -> 90000 | D29: Utilidades Retenidas | E29: ='Balanza Proforma'!J55 -> 250000
B30: Amortización acum. | C30: ='Balanza Proforma'!J33 -> 81000 | D30: Utilidades del ejercicio | E30: ='Balanza Proforma'!J56 -> 683383.41
B31: Total de Activo Diferido | C31: =C29-C30 -> 9000 | D31: Total de Capital | E31: =SUM(E26:E30) -> 3417363.6
B33: Total de Activo | C33: =C18+C26+C31 -> 5516022.5 | D33: Total de Pasivo + Capital | E33: =E18+E23+E31 -> 5516022.5
E34: =E33-C33 -> 0.0040000007

Sheet Estados Financieros 
B4: Estado de situación financiera 2023 | G4: Estado de resultados | I4: Procentajes Integrales | K4: Depreciación y amortización
B5: Activos | D5: Pasivo | G5: Ventas | H5: 2100000 | K5: Concepto | L5: Inversión inicial | M5: Tasa de depreciación anual % | N5: Depreacición y amortización anual
B6: Circulantes | D6: Circulante | G6: (-) Inventario Inicial | H6: 400000 | K6: Depreciación
B7: Caja | C7: 2500 | D7: Documentos por pagar C.P | E7: 54500 | G7: (+)Compras | H7: 750000 | K7: Activos tangibles | N7: 2015 | O7: 2016 | P7: 2017 | Q7: 2018 | R7: 2019 | S7: 2020 | T7: 2022 | U7: 2023 | V7: 2024
B8: Bancos | C8: 515000 | D8: Proveedores | E8: 140000 | G8: (-)Inventario final | H8: =C11+C12+C13 -> 275000
B9: Clientes | C9: 25000 | D9: Acreedores | E9: 81000 | G9: (=)Costo de ventas | H9: =H6+H7-H8 -> 875000 | I9: =H9/H5 -> 0.41666667 | K9: =B17 -> Maquinaria y equipo | L9: 1000000 | M9: 0.1 | N9: =L9*M9 -> 100000 | O9: 100000 | P9: 100000 | Q9: 100000 | R9: 100000 | S9: 100000 | T9: 100000 | U9: 100000 | V9: 100000 | W9: =SUM(N9:V9) -> 900000 | X9: =SUM(N9:U9) -> 800000
B10: Deudores diversos | C10: 16000 | D10: Impuestos por pagar | E10: =H18+H19 -> 148000 | G10: (=)Utilidad Bruta | H10: =H5-H9 -> 1225000 | K10: =B18 -> Mobiliario y equipo de oficina | L10: 200000 | M10: 0.1 | N10: =L10*M10 -> 20000 | O10: 20000 | P10: 20000 | Q10: 20000 | R10: 20000 | S10: 20000 | T10: 20000 | U10: 20000 | V10: 20000 | W10: =SUM(N10:V10) -> 180000 | X10: =SUM(N10:U10) -> 160000
B11: Inventarios PT | C11: 140000 | D11: Creaditos Bancarios | E11: 75000 | K11: Edificio | L11: =C16 -> 1050000 | M11: 0.05 | N11: =L11*M11 -> 52500 | O11: 52500 | P11: 52500 | Q11: 52500 | R11: 52500 | S11: 52500 | T11: 52500 | U11: 52500 | V11: 52500 | W11: =SUM(N11:V11) -> 472500 | X11: =SUM(N11:U11) -> 420000
B12: Inventarios MP | C12: 115000 | D12: Servicios por pagar | E12: =C17*5% -> 50000 | G12: (-) Gastos de administración | H12: 390000 | K12: Amortización
B13: Inventarios PP | C13: 20000 | D13: Pasivo a Largo Plazo | G13: (-) Gastos de venta | H13: 400000 | K13: Patentes | L13: 90000 | M13: 0.1 | N13: =L13*M13 -> 9000 | O13: 9000 | P13: 9000 | Q13: 9000 | R13: 9000 | S13: 9000 | T13: 9000 | U13: 9000 | V13: 9000 | W13: =SUM(N13:V13) -> 81000 | X13: =SUM(N13:U13) -> 72000
B14: Fijo | D14: Documentos por pagar L.P | E14: 275000 | G14: Utilidad de operación | H14: =H10-(H13+H12) -> 435000 | I14: =H14/H5 -> 0.20714286
B15: Terreno | C15: 1450000 | G15: Gastos financieros | H15: 35000
B16: Edificio | C16: 1050000 | D16: Capital | G16: Utilidad antes de ISR y PTU | H16: =H14-H15 -> 400000 | I16: =H16/H5 -> 0.19047619
B17: Maquinaria y equipo | C17: 1000000 | D17: Capital social | E17: 1330000
B18: Mobiliario y equipo de oficina | C18: 200000 | D18: Reserva Legal | E18: =E17*20% -> 266000 | G18: (-)PTU (10%) | H18: =H16*10% -> 40000
B19: Depreación Acum. | C19: =X9+X10+X11 -> 1380000 | D19: Resultado de Ejercicios A. | E19: 350000 | G19: (-) ISR (30%) | H19: =(H16-H18)*30% -> 108000
D20: Utilidades Retenidas | E20: 150000
B21: Diferidos | D21: Utilidades del Ejercicio | E21: =H21 -> 252000 | G21: Utilidad neta | H21: =H16-(H18+H19) -> 252000 | I21: =H21/H5 -> 0.12 | K21: Interpretación: El Estado de Resultados de Amarguitas S.de RL. de 2023, muestra un volumen de ventas de $2,100, 000, del cual el porcentaje de costo de ventas corresponde al 41.67%, es decir, representa lo que cuesta realizar la producción de cerveza. Mientras que, la utilidad de operación corresponde al 20.71%, porcentaje que representa todos los gastos administrativos y ventas. Finalmente la Rentabilidad corresponde al 12%, es decir por cada $1 qué vende, Amarguitas obtiene ¢12.
B22: Patentes | C22: =L13 -> 90000
B23: Amortización acum. | C23: =X13 -> 72000
C26: =SUM(C7:C18)+C22-C23-C19 -> 3171500 | D26: Total | E26: =SUM(E5:E25) -> 3171500
B27: Total de Activos
E28: =C26-E26 -> 0 | H28: =H36+H35 -> 1525000
B31: Estado de situación financiera 2024 | G31: Estado de resultados | I31: Porcentaje Integrales
B32: Activos | D32: Pasivo | G32: Ventas | H32: =2150000 -> 2150000
B33: Circulantes | D33: Circulante | G33: (-) Inventario Inicial | H33: =C11+C12+C13 -> 275000
B34: Caja | C34: =3500+5000+5000 -> 13500 | D34: Documentos por pagar C.P | E34: 57000 | G34: (+)Compras | H34: 1250000
B35: Bancos | C35: =843500+15000+35800.06 -> 894300.06 | D35: Proveedores | E35: 110800 | G35: (-)Inventario final | H35: =C38+C39+C40 -> 340000
B36: Clientes | C36: =65000+250000 -> 315000 | D36: Acreedores | E36: =89200+20000 -> 109200 | G36: (=)Costo de ventas | H36: =(H33+H34)-H35 -> 1185000 | I36: =H36/H32 -> 0.55116279
B37: Deudores diversos | C37: =35000+50000 -> 85000 | D37: Impuestos por pagar | E37: =H46+H47 -> 198319.88 | G37: (=)Utilidad Bruta | H37: =H32-H36 -> 965000 | K37: Interpretación: El Estado de Resultados de Amarguitas S.de RL. de 2024, muestra un volumen de ventas de $2,250,000, del cual el porcentaje de costo de ventas corresponde al 41.11%, es decir, representa lo que cuesta realizar la producción de cerveza. Mientras que, la utilidad de operación corresponde al 21.11%, porcentaje que representa todos los gastos administrativos y ventas. Finalmente la Rentabilidad corresponde al 12%, es decir por cada $1 qué vende, Amarguitas obtiene ¢12
B38: Inventarios PT | C38: =150000 -> 150000 | D38: Creaditos Bancarios | E38: 85500
B39: Inventarios MP | C39: =140000 -> 140000 | D39: Servicios por pagar | E39: =C45*10% -> 100000 | G39: (-) Gastos de administración | H39: ='M. DE CALCULO DE GASTOS FIJOS'!E13 -> 204600.84
B40: Inventarios PP | C40: =50000 -> 50000 | G40: (-) Gastos de venta | H40: ='M. DE CALCULO DE GASTOS FIJOS'!E21 -> 199399.48
B42: Fijo | D42: Documentos por pagar L.P | E42: 423000 | G42: Utilidad de operación | H42: =H37-(H40+H39) -> 560999.68 | I42: =H42/H32 -> 0.26093009
B43: Terreno | C43: 1450000 | G43: Gastos financieros | H43: 25000
B44: Edificio | C44: 1050000 | D44: Capital | G44: Utilidad antes de ISR y PTU | H44: =H42-H43 -> 535999.68 | I44: =H44/H32 -> 0.24930218
B45: Maquinaria y equipo | C45: 1000000 | D45: Capital social | E45: =1363333.33+204000.32 -> 1567333.7
B46: Mobiliario y equipo de oficina | C46: 200000 | D46: Reserva Legal | E46: =E45*20% -> 313466.73 | G46: (-)PTU (10%) | H46: =H44*10% -> 53599.968
B47: Depreciación Acum. | C47: =W9+W10+W11 -> 1552500 | D47: Resultado de Ejercicios A. | E47: =H21 -> 252000 | G47: (-) ISR (30%) | H47: =(H44-H46)*30% -> 144719.91
D48: Utilidades Retenidas | E48: 250000
B49: Diferidos | D49: Utilidades del ejercicio | E49: =H49 -> 337679.8 | G49: Utilidad neta | H49: =H44-H46-H47 -> 337679.8 | I49: =H49/H32 -> 0.15706037
B50: Patentes | C50: =L13 -> 90000
B51: Amortización acum. | C51: =W13 -> 81000 | K51: Capital de Trabajo | L51: =SUM(C34:C40)-SUM(E34:E39) -> 986980.18
K52: Razón de Capital de Trabajo (solvencia) | L52: =SUM(C34:C40)/SUM(E34:E39) -> 2.4935691 | N52: RECT | O52: 2 a 1 | P52: =L52-2 -> 0.49356913 | Q52: Superavit
K53: Prueba Acida (liquidez) | L53: =(E62-E61)/E63 -> 1.9790568 | N53: REPA | O53: 1.5 a 1 | P53: =L53-1.5 -> 0.47905676 | Q53: Superavit
B54: Total | C54: =SUM(C34:C46)+C50-C47-C51 -> 3804300.1 | D54: Total | E54: =SUM(E32:E53) -> 3804300.1 | K54: Rentabilidad | L54: =H49/H32 -> 0.15706037
E55: =E54-C54 -> 0.0039999997
H56: =H36+H39+H40+H35 -> 1929000.3
E57: =C54-E54 -> -0.0039999997
D61: Total de Inventarios | E61: =C38+C39+C40 -> 340000
D62: Total de Activo C. | E62: =SUM(C34:C40) -> 1647800.1
D63: Total de Pasivo C. | E63: =SUM(E33:E39) -> 660819.88

Sheet CONCENTRADO DE SUELDOS
A2: Concentrado de nómina | G2: Prestaciones | L2: Deducciones
A3: =A27 -> Puesto | B3: =B27 -> Nivel | C3: =C27 -> Fecha de ingreso | D3: =D27 -> Antigüedad | E3: =E27 -> Salario Base | F3: =F27 -> Salario Quincenal | G3: =G27 -> Aguinaldo | H3: =H27 -> Vacaciones | ... K3: =K27 -> SBC | L3: ISR | M3: IMSS | N3: Salario neto quincenal | O3: Salario neto mensual | P3: Salario neto anual
A4: =A28 -> Gerente general | B4: =B28 -> 1 | C4: =C28 -> 43160 | D4: =D28 -> 6 | E4: =E28 -> 550 | F4: =F28 -> 8364.565 | G4: =G28 -> 15 | H4: =H28 -> 20 | ... K4: =K28 -> 580.13699 | L4: =M87 -> 963.60911 | M4: =L68 -> 225.02142 | N4: =F4-L4-M4 -> 7175.9345 | O4: =N4*2 -> 14351.869 | P4: =O4*12 -> 172222.43
A5: =A29 -> Gerente de restaurante | B5: =B29 -> 2 | C5: =C29 -> 44274 | D5: =D29 -> 3 | E5: =E29 -> 500 | F5: =F29 -> 7604.15 | G5: =G29 -> 15 | H5: =H29 -> 16 | ... K5: =K29 -> 526.0274 | L5: =M88 -> 801.18446 | M5: =L69 -> 202.18553 | N5: =F5-L5-M5 -> 6600.78 | O5: =N5*2 -> 13201.56 | P5: =O5*12 -> 158418.72
A6: =A30 -> Gerente de producción | B6: =B30 -> 2 | C6: =C30 -> 44862 | D6: =D30 -> 2 | E6: =E30 -> 520 | F6: =F30 -> 7908.316 | G6: =G30 -> 15 | H6: =H30 -> 14 | ... K6: =K30 -> 546.35616 | L6: =M89 -> 866.15432 | M6: =L70 -> 210.76489 | N6: =F6-L6-M6 -> 6831.3968 | O6: =N6*2 -> 13662.794 | P6: =O6*12 -> 163953.52
A7: =A31 -> Gerente de ventas | B7: =B31 -> 2 | C7: =C31 -> 45260 | D7: =D31 -> 1 | E7: =E31 -> 520 | F7: =F31 -> 7908.316 | G7: =G31 -> 15 | H7: =H31 -> 12 | ... K7: =K31 -> 545.64384 | L7: =M90 -> 866.15432 | M7: =L71 -> 210.46426 | N7: =F7-L7-M7 -> 6831.6974 | O7: =N7*2 -> 13663.395 | P7: =O7*12 -> 163960.74
A8: =A32 -> Gerente de finanzas | B8: =B32 -> 2 | C8: =C32 -> 45061 | D8: =D32 -> 1 | E8: =E32 -> 400 | F8: =F32 -> 6083.32 | G8: =G32 -> 15 | H8: =H32 -> 12 | ... K8: =K32 -> 419.72603 | L8: =M91 -> 535.8096 | M8: =L72 -> 157.32313 | N8: =F8-L8-M8 -> 5390.1873 | O8: =N8*2 -> 10780.375 | P8: =O8*12 -> 129364.49
A9: =A33 -> Encargado de mantenimiento | B9: =B33 -> 3 | C9: =C33 -> 44315 | D9: =D33 -> 3 | E9: =E33 -> 380 | F9: =F33 -> 5779.154 | G9: =G33 -> 15 | H9: =H33 -> 16 | ... K9: =K33 -> 399.78082 | L9: =M92 -> 487.14304 | M9: =L73 -> 148.90565 | N9: =F9-L9-M9 -> 5143.1053 | O9: =N9*2 -> 10286.211 | P9: =O9*12 -> 123434.53
A10: =A34 -> Encargado de almacen | B10: =B34 -> 3 | C10: =C34 -> 44239 | D10: =D34 -> 3 | E10: =E34 -> 380 | F10: =F34 -> 5779.154 | G10: =G34 -> 15 | H10: =H34 -> 16 | ... K10: =K34 -> 399.78082 | L10: =M93 -> 487.14304 | M10: =L74 -> 148.90565 | N10: =F10-L10-M10 -> 5143.1053 | O10: =N10*2 -> 10286.211 | P10: =O10*12 -> 123434.53
A11: =A35 -> Jefe de cocina | B11: =B35 -> 3 | C11: =C35 -> 44247 | D11: =D35 -> 3 | E11: =E35 -> 380 | F11: =F35 -> 5779.154 | G11: =G35 -> 15 | H11: =H35 -> 16 | ... K11: =K35 -> 399.78082 | L11: =M94 -> 487.14304 | M11: =L75 -> 148.90565 | N11: =F11-L11-M11 -> 5143.1053 | O11: =N11*2 -> 10286.211 | P11: =O11*12 -> 123434.53
A12: =A36 -> Relaciones públicas | B12: =B36 -> 3 | C12: =C36 -> 43855 | D12: =D36 -> 4 | E12: =E36 -> 376.66667 | F12: =F36 -> 5728.4597 | G12: =G36 -> 15 | H12: =H36 -> 18 | ... K12: =K36 -> 396.78995 | L12: =M95 -> 479.03195 | M12: =L76 -> 147.64341 | N12: =F12-L12-M12 -> 5101.7843 | O12: =N12*2 -> 10203.569 | P12: =O12*12 -> 122442.82
A13: =A37 -> Maestro cervecero | B13: =B37 -> 3 | C13: =C37 -> 45029 | D13: =D37 -> 1 | E13: =E37 -> 300 | F13: =F37 -> 4562.49 | G13: =G37 -> 15 | H13: =H37 -> 12 | ... K13: =K37 -> 314.79452 | L13: =M96 -> 147.42393 | M13: =L77 -> 113.70288 | N13: =F13-L13-M13 -> 4301.3632 | O13: =N13*2 -> 8602.7264 | P13: =O13*12 -> 103232.72
A14: =A38 -> Auxiliar Contador | B14: =B38 -> 3 | C14: =C38 -> 44226 | D14: =D38 -> 3 | E14: =E38 -> 300 | F14: =F38 -> 4562.49 | G14: =G38 -> 15 | H14: =H38 -> 16 | ... K14: =K38 -> 315.61644 | L14: =M97 -> 147.42393 | M14: =L78 -> 113.99975 | N14: =F14-L14-M14 -> 4301.0663 | O14: =N14*2 -> 8602.1326 | P14: =O14*12 -> 103225.59
A15: =A39 -> Auxiliar de produccion | B15: =B39 -> 4 | C15: =C39 -> 45158 | D15: =D39 -> 1 | E15: =E39 -> 250 | F15: =F39 -> 3802.075 | G15: =G39 -> 15 | H15: =H39 -> 12 | ... K15: =K39 -> 262.32877 | L15: =M98 -> 64.690782 | M15: =L79 -> 94.752396 | N15: =F15-L15-M15 -> 3642.6318 | O15: =N15*2 -> 7285.2636 | P15: =O15*12 -> 87423.164
... A18: =A42 -> Auxiliar de limpieza | B18: =B42 -> 5 | C18: =C42 -> 45158 | D18: =D42 -> 1 | E18: =E42 -> 248.93 | F18: =F42 -> 3785.8021 | G18: =G42 -> 15 | H18: =H42 -> 12 | ... K18: =K42 -> 261.206 | L18: =M101 -> 62.920293 | M18: =L82 -> 94.346856 | N18: =F18-L18-M18 -> 3628.535 | O18: =N18*2 -> 7257.0699 | P18: =O18*12 -> 87084.839
N19: =SUM(N4:N18) -> 76519.832 | O19: =N19*2 -> 153039.66 | P19: =O19*12 -> 1836476
A24: Cálculo del Salario Base de Cotización | K24: 3 | L24: =E28 -> 550 | M24: ISN | N24: NOMINAL
K25: 5 | L25: =K28 -> 580.13699 | M25: INFONAVIT | N25: SBC IMSS | T25: UMA 2024 | U25: 108.57
G26: Prestaciones | T26: 3 Veces UMA | U26: 325.71
A27: Puesto | B27: Nivel | C27: Fecha de ingreso | D27: Antigüedad | E27: Salario Base | F27: Salario Quincenal | G27: Aguinaldo | H27: Vacaciones | I27: Prima vacacional | J27: Factor de integración | K27: SBC | L27: SBC*15
A28: Gerente general | B28: 1 | C28: 43160 | D28: =DATEDIF(C28,A$44,"y") -> 6 | E28: 550 | F28: =E28*15.2083 -> 8364.565 | G28: 15 | H28: 20 | I28: 0.25 | J28: =((H28*I28)+G28+365)/365 -> 1.0547945 | K28: =E28*J28 -> 580.13699 | L28: =K28*15.2083 -> 8822.8973 | T28: Cuotas patronales
A29: Gerente de restaurante | B29: 2 | C29: 44274 | D29: =DATEDIF(C29,A$44,"y") -> 3 | E29: 500 | F29: =E29*15.2083 -> 7604.15 | G29: 15 | H29: 16 | I29: 0.25 | J29: =((H29*I29)+G29+365)/365 -> 1.0520548 | K29: =E29*J29 -> 526.0274 | L29: =K29*15.2083 -> 7999.9825 | T29: Cuota fija | U29: 0.204
A30: Gerente de producción | B30: 2 | C30: 44862 | D30: =DATEDIF(C30,A$44,"y") -> 2 | E30: 520 | F30: =E30*15.2083 -> 7908.316 | G30: 15 | H30: 14 | I30: 0.25 | J30: =((H30*I30)+G30+365)/365 -> 1.0506849 | K30: =E30*J30 -> 546.35616 | L30: =K30*15.2083 -> 8309.1485 | T30: Cuota adicional sobre el UMA | U30: 0.011
A31: Gerente de ventas | B31: 2 | C31: 45260 | D31: =DATEDIF(C31,A$44,"y") -> 1 | E31: 520 | F31: =E31*15.2083 -> 7908.316 | G31: 15 | H31: 12 | I31: 0.25 | J31: =((H31*I31)+G31+365)/365 -> 1.0493151 | K31: =E31*J31 -> 545.64384 | L31: =K31*15.2083 -> 8298.3151 | T31: Prestaciones en dinero | U31: 0.007
A32: Gerente de finanzas | B32: 2 | C32: 45061 | D32: =DATEDIF(C32,A$44,"y") -> 1 | E32: 400 | F32: =E32*15.2083 -> 6083.32 | G32: 15 | H32: 12 | I32: 0.25 | J32: =((H32*I32)+G32+365)/365 -> 1.0493151 | K32: =E32*J32 -> 419.72603 | L32: =K32*15.2083 -> 6383.3193 | T32: Gtos. Med. | U32: 0.0105
A33: Encargado de mantenimiento | B33: 3 | C33: 44315 | D33: =DATEDIF(C33,A$44,"y") -> 3 | E33: 380 | F33: =E33*15.2083 -> 5779.154 | G33: 15 | H33: 16 | I33: 0.25 | J33: =((H33*I33)+G33+365)/365 -> 1.0520548 | K33: =E33*J33 -> 399.78082 | L33: =K33*15.2083 -> 6079.9867 | T33: Invalidez y vida | U33: 0.0175
A34: Encargado de almacen | B34: 3 | C34: 44239 | D34: =DATEDIF(C34,A$44,"y") -> 3 | E34: 380 | F34: =E34*15.2083 -> 5779.154 | G34: 15 | H34: 16 | I34: 0.25 | J34: =((H34*I34)+G34+365)/365 -> 1.0520548 | K34: =E34*J34 -> 399.78082 | L34: =K34*15.2083 -> 6079.9867 | T34: Guarderías y prestaciones | U34: 0.01
A35: Jefe de cocina | B35: 3 | C35: 44247 | D35: =DATEDIF(C35,A$44,"y") -> 3 | E35: 380 | F35: =E35*15.2083 -> 5779.154 | G35: 15 | H35: 16 | I35: 0.25 | J35: =((H35*I35)+G35+365)/365 -> 1.0520548 | K35: =E35*J35 -> 399.78082 | L35: =K35*15.2083 -> 6079.9867 | T35: Retiro | U35: 0.02
A36: Relaciones públicas | B36: 3 | C36: 43855 | D36: =DATEDIF(C36,A$44,"y") -> 4 | E36: 376.66667 | F36: =E36*15.2083 -> 5728.4597 | G36: 15 | H36: 18 | I36: 0.25 | J36: =((H36*I36)+G36+365)/365 -> 1.0534247 | K36: =E36*J36 -> 396.78995 | L36: =K36*15.2083 -> 6034.5007 | T36: Cesantía y vejez | U36: 0.0315
A37: Maestro cervecero | B37: 3 | C37: 45029 | D37: =DATEDIF(C37,A$44,"y") -> 1 | E37: 300 | F37: =E37*15.2083 -> 4562.49 | G37: 15 | H37: 12 | I37: 0.25 | J37: =((H37*I37)+G37+365)/365 -> 1.0493151 | K37: =E37*J37 -> 314.79452 | L37: =K37*15.2083 -> 4787.4895 | T37: F. vivienda | U37: 0.05
A38: Auxiliar Contador | B38: 3 | C38: 44226 | D38: =DATEDIF(C38,A$44,"y") -> 3 | E38: 300 | F38: =E38*15.2083 -> 4562.49 | G38: 15 | H38: 16 | I38: 0.25 | J38: =((H38*I38)+G38+365)/365 -> 1.0520548 | K38: =E38*J38 -> 315.61644 | L38: =K38*15.2083 -> 4799.9895
A39: Auxiliar de produccion | B39: 4 | C39: 45158 | D39: =DATEDIF(C39,A$44,"y") -> 1 | E39: 250 | F39: =E39*15.2083 -> 3802.075 | G39: 15 | H39: 12 | I39: 0.25 | J39: =((H39*I39)+G39+365)/365 -> 1.0493151 | K39: =E39*J39 -> 262.32877 | L39: =K39*15.2083 -> 3989.5746 | T39: Riesgo de trabajo
A40: Meseros | B40: 4 | C40: 45260 | D40: =DATEDIF(C40,A$44,"y") -> 1 | E40: 250 | F40: =E40*15.2083 -> 3802.075 | G40: 15 | H40: 12 | I40: 0.25 | J40: =((H40*I40)+G40+365)/365 -> 1.0493151 | K40: =E40*J40 -> 262.32877 | L40: =K40*15.2083 -> 3989.5746 | T40: Clase IV | U40: 0.0465325
A41: Cocineros | B41: 4 | C41: 44862 | D41: =DATEDIF(C41,A$44,"y") -> 2 | E41: 250 | F41: =E41*15.2083 -> 3802.075 | G41: 15 | H41: 14 | I41: 0.25 | J41: =((H41*I41)+G41+365)/365 -> 1.0506849 | K41: =E41*J41 -> 262.67123 | L41: =K41*15.2083 -> 3994.7829
A42: Auxiliar de limpieza | B42: 5 | C42: 45158 | D42: =DATEDIF(C42,A$44,"y") -> 1 | E42: 248.93 | F42: =E42*15.2083 -> 3785.8021 | G42: 15 | H42: 12 | I42: 0.25 | J42: =((H42*I42)+G42+365)/365 -> 1.0493151 | K42: =E42*J42 -> 261.206 | L42: =K42*15.2083 -> 3972.4992 | T42: Cuotras obrero
T43: Prestaciones en dinero | U43: 0.0025
A44: 45657 | T44: Gastos medicos pensionados | U44: 0.00375
T45: Cuota adicional por la diferencia del SBC y de tres veces la UMA | U45: 0.004
A46: Deducción de Cuotas patronales por trabajador | T46: Invalidez y vida | U46: 0.00625
T47: Cesantia y vejez | U47: 0.01125
A48: =A27 -> Puesto | B48: =B27 -> Nivel | C48: =C27 -> Fecha de ingreso | D48: =E27 -> Salario Base | E48: =F27 -> Salario Quincenal | F48: =K27 -> SBC | G48: Cuota Fija | H48: Cuota Adicional sobre el UMA | I48: Prestaciones en dinero | J48: Gastos Medicos | K48: Invalidez y vida | L48: Guarderías y prestaciones | M48: Retiro | N48: Cesantía y vejez | O48: Fondo para la vivienda | P48: Prima de Riesgo de trabajo | Q48: Total
A49: =A28 -> Gerente general | B49: =B28 -> 1 | C49: 43160 | D49: =E28 -> 550 | E49: =F28 -> 8364.565 | F49: =K28 -> 580.13699 | G49: =(U$25*15.2083)*U$29 -> 336.83769 | H49: =((F49-U$26)*U$30)*15.2083 -> 42.563421 | I49: =(F49*15.2083)*U$31 -> 61.760281 | J49: =(F49*15.2083)*U$32 -> 92.640422 | K49: =(F49*15.2083)*U$33 -> 154.4007 | L49: =(F49*15.2083)*U$34 -> 88.228973 | M49: =(F49*15.2083)*U$35 -> 176.45795 | N49: =(F49*15.2083)*U$36 -> 277.92127 | O49: =(F49*15.2083)*U$37 -> 441.14487 | P49: =(F49*15.2083)*U$40 -> 410.55147 | Q49: =SUM(G49:P49) -> 2082.507
A50: =A29 -> Gerente de restaurante | B50: =B29 -> 2 | C50: 44274 | D50: =E29 -> 500 | E50: =F29 -> 7604.15 | F50: =K29 -> 526.0274 | G50: =(U$25*15.2083)*U$29 -> 336.83769 | H50: =((F50-U$26)*U$30)*15.2083 -> 33.511358 | I50: =(F50*15.2083)*U$31 -> 55.999877 | J50: =(F50*15.2083)*U$32 -> 83.999816 | K50: =(F50*15.2083)*U$33 -> 139.99969 | L50: =(F50*15.2083)*U$34 -> 79.999825 | M50: =(F50*15.2083)*U$35 -> 159.99965 | N50: =(F50*15.2083)*U$36 -> 251.99945 | O50: =(F50*15.2083)*U$37 -> 399.99912 | P50: =(F50*15.2083)*U$40 -> 372.25918 | Q50: =SUM(G50:P50) -> 1914.6057
A51: =A30 -> Gerente de producción | B51: =B30 -> 2 | C51: 44862 | D51: =E30 -> 520 | E51: =F30 -> 7908.316 | F51: =K30 -> 546.35616 | G51: =(U$25*15.2083)*U$29 -> 336.83769 | H51: =((F51-U$26)*U$30)*15.2083 -> 36.912184 | I51: =(F51*15.2083)*U$31 -> 58.164039 | J51: =(F51*15.2083)*U$32 -> 87.246059 | K51: =(F51*15.2083)*U$33 -> 145.4101 | L51: =(F51*15.2083)*U$34 -> 83.091485 | M51: =(F51*15.2083)*U$35 -> 166.18297 | N51: =(F51*15.2083)*U$36 -> 261.73818 | O51: =(F51*15.2083)*U$37 -> 415.45742 | P51: =(F51*15.2083)*U$40 -> 386.64545 | Q51: =SUM(G51:P51) -> 1977.6856
A52: =A31 -> Gerente de ventas | B52: =B31 -> 2 | C52: 45260 | D52: =E31 -> 520 | E52: =F31 -> 7908.316 | F52: =K31 -> 545.64384 | G52: =(U$25*15.2083)*U$29 -> 336.83769 | H52: =((F52-U$26)*U$30)*15.2083 -> 36.793017 | I52: =(F52*15.2083)*U$31 -> 58.088206 | J52: =(F52*15.2083)*U$32 -> 87.132309 | K52: =(F52*15.2083)*U$33 -> 145.22052 | L52: =(F52*15.2083)*U$34 -> 82.983151 | M52: =(F52*15.2083)*U$35 -> 165.9663 | N52: =(F52*15.2083)*U$36 -> 261.39693 | O52: =(F52*15.2083)*U$37 -> 414.91576 | P52: =(F52*15.2083)*U$40 -> 386.14135 | Q52: =SUM(G52:P52) -> 1975.4752
A53: =A32 -> Gerente de finanzas | B53: =B32 -> 2 | C53: 45061 | D53: =E32 -> 400 | E53: =F32 -> 6083.32 | F53: =K32 -> 419.72603 | G53: =(U$25*15.2083)*U$29 -> 336.83769 | H53: =((F53-U$26)*U$30)*15.2083 -> 15.728063 | I53: =(F53*15.2083)*U$31 -> 44.683235 | J53: =(F53*15.2083)*U$32 -> 67.024853 | K53: =(F53*15.2083)*U$33 -> 111.70809 | L53: =(F53*15.2083)*U$34 -> 63.833193 | M53: =(F53*15.2083)*U$35 -> 127.66639 | N53: =(F53*15.2083)*U$36 -> 201.07456 | O53: =(F53*15.2083)*U$37 -> 319.16597 | P53: =(F53*15.2083)*U$40 -> 297.03181 | Q53: =SUM(G53:P53) -> 1584.7538
A54: =A33 -> Encargado de mantenimiento | B54: =B33 -> 3 | C54: 44315 | D54: =E33 -> 380 | E54: =F33 -> 5779.154 | F54: =K33 -> 399.78082 | G54: =(U$25*15.2083)*U$29 -> 336.83769 | H54: =((F54-U$26)*U$30)*15.2083 -> 12.391404 | I54: =(F54*15.2083)*U$31 -> 42.559907 | J54: =(F54*15.2083)*U$32 -> 63.83986 | K54: =(F54*15.2083)*U$33 -> 106.39977 | L54: =(F54*15.2083)*U$34 -> 60.799867 | M54: =(F54*15.2083)*U$35 -> 121.59973 | N54: =(F54*15.2083)*U$36 -> 191.51958 | O54: =(F54*15.2083)*U$37 -> 303.99933 | P54: =(F54*15.2083)*U$40 -> 282.91698 | Q54: =SUM(G54:P54) -> 1522.8641
A55: =A34 -> Encargado de almacen | B55: =B34 -> 3 | C55: 44239 | D55: =E34 -> 380 | E55: =F34 -> 5779.154 | F55: =K34 -> 399.78082 | G55: =(U$25*15.2083)*U$29 -> 336.83769 | H55: =((F55-U$26)*U$30)*15.2083 -> 12.391404 | I55: =(F55*15.2083)*U$31 -> 42.559907 | J55: =(F55*15.2083)*U$32 -> 63.83986 | K55: =(F55*15.2083)*U$33 -> 106.39977 | L55: =(F55*15.2083)*U$34 -> 60.799867 | M55: =(F55*15.2083)*U$35 -> 121.59973 | N55: =(F55*15.2083)*U$36 -> 191.51958 | O55: =(F55*15.2083)*U$37 -> 303.99933 | P55: =(F55*15.2083)*U$40 -> 282.91698 | Q55: =SUM(G55:P55) -> 1522.8641
A56: =A35 -> Jefe de cocina | B56: =B35 -> 3 | C56: 44247 | D56: =E35 -> 380 | E56: =F35 -> 5779.154 | F56: =K35 -> 399.78082 | G56: =(U$25*15.2083)*U$29 -> 336.83769 | H56: =((F56-U$26)*U$30)*15.2083 -> 12.391404 | I56: =(F56*15.2083)*U$31 -> 42.559907 | J56: =(F56*15.2083)*U$32 -> 63.83986 | K56: =(F56*15.2083)*U$33 -> 106.39977 | L56: =(F56*15.2083)*U$34 -> 60.799867 | M56: =(F56*15.2083)*U$35 -> 121.59973 | N56: =(F56*15.2083)*U$36 -> 191.51958 | O56: =(F56*15.2083)*U$37 -> 303.99933 | P56: =(F56*15.2083)*U$40 -> 282.91698 | Q56: =SUM(G56:P56) -> 1522.8641
A57: =A36 -> Relaciones públicas | B57: =B36 -> 3 | C57: 43855 | D57: =E36 -> 376.66667 | E57: =F36 -> 5728.4597 | F57: =K36 -> 396.78995 | G57: =(U$25*15.2083)*U$29 -> 336.83769 | H57: =((F57-U$26)*U$30)*15.2083 -> 11.891058 | I57: =(F57*15.2083)*U$31 -> 42.241505 | J57: =(F57*15.2083)*U$32 -> 63.362257 | K57: =(F57*15.2083)*U$33 -> 105.60376 | L57: =(F57*15.2083)*U$34 -> 60.345007 | M57: =(F57*15.2083)*U$35 -> 120.69001 | N57: =(F57*15.2083)*U$36 -> 190.08677 | O57: =(F57*15.2083)*U$37 -> 301.72503 | P57: =(F57*15.2083)*U$40 -> 280.8004 | Q57: =SUM(G57:P57) -> 1513.5835
A58: =A37 -> Maestro cervecero | B58: =B37 -> 3 | C58: 45029 | D58: =E37 -> 300 | E58: =F37 -> 4562.49 | F58: =K37 -> 314.79452 | G58: =(U$25*15.2083)*U$29 -> 336.83769 | H58: 0 | I58: =(F58*15.2083)*U$31 -> 33.512427 | J58: =(F58*15.2083)*U$32 -> 50.26864 | K58: =(F58*15.2083)*U$33 -> 83.781066 | L58: =(F58*15.2083)*U$34 -> 47.874895 | M58: =(F58*15.2083)*U$35 -> 95.74979 | N58: =(F58*15.2083)*U$36 -> 150.80592 | O58: =(F58*15.2083)*U$37 -> 239.37448 | P58: =(F58*15.2083)*U$40 -> 222.77386 | Q58: =SUM(G58:P58) -> 1260.9788
A59: =A38 -> Auxiliar Contador | B59: =B38 -> 3 | C59: 44226 | D59: =E38 -> 300 | E59: =F38 -> 4562.49 | F59: =K38 -> 315.61644 | G59: =(U$25*15.2083)*U$29 -> 336.83769 | H59: 0 | I59: =(F59*15.2083)*U$31 -> 33.599926 | J59: =(F59*15.2083)*U$32 -> 50.39989 | K59: =(F59*15.2083)*U$33 -> 83.999816 | L59: =(F59*15.2083)*U$34 -> 47.999895 | M59: =(F59*15.2083)*U$35 -> 95.99979 | N59: =(F59*15.2083)*U$36 -> 151.19967 | O59: =(F59*15.2083)*U$37 -> 239.99947 | P59: =(F59*15.2083)*U$40 -> 223.35551 | Q59: =SUM(G59:P59) -> 1263.3917
A60: =A39 -> Auxiliar de produccion | B60: =B39 -> 4 | C60: 45158 | D60: =E39 -> 250 | E60: =F39 -> 3802.075 | F60: =K39 -> 262.32877 | G60: =(U$25*15.2083)*U$29 -> 336.83769 | H60: 0 | I60: =(F60*15.2083)*U$31 -> 27.927022 | J60: =(F60*15.2083)*U$32 -> 41.890533 | K60: =(F60*15.2083)*U$33 -> 69.817555 | L60: =(F60*15.2083)*U$34 -> 39.895746 | M60: =(F60*15.2083)*U$35 -> 79.791492 | N60: =(F60*15.2083)*U$36 -> 125.6716 | O60: =(F60*15.2083)*U$37 -> 199.47873 | P60: =(F60*15.2083)*U$40 -> 185.64488 | Q60: =SUM(G60:P60) -> 1106.9552
A61: =A40 -> Meseros | B61: =B40 -> 4 | C61: 45260 | D61: =E40 -> 250 | E61: =F40 -> 3802.075 | F61: =K40 -> 262.32877 | G61: =(U$25*15.2083)*U$29 -> 336.83769 | H61: 0 | I61: =(F61*15.2083)*U$31 -> 27.927022 | J61: =(F61*15.2083)*U$32 -> 41.890533 | K61: =(F61*15.2083)*U$33 -> 69.817555 | L61: =(F61*15.2083)*U$34 -> 39.895746 | M61: =(F61*15.2083)*U$35 -> 79.791492 | N61: =(F61*15.2083)*U$36 -> 125.6716 | O61: =(F61*15.2083)*U$37 -> 199.47873 | P61: =(F61*15.2083)*U$40 -> 185.64488 | Q61: =SUM(G61:P61) -> 1106.9552
A62: =A41 -> Cocineros | B62: =B41 -> 4 | C62: 44862 | D62: =E41 -> 250 | E62: =F41 -> 3802.075 | F62: =K41 -> 262.67123 | G62: =(U$25*15.2083)*U$29 -> 336.83769 | H62: 0 | I62: =(F62*15.2083)*U$31 -> 27.96348 | J62: =(F62*15.2083)*U$32 -> 41.945221 | K62: =(F62*15.2083)*U$33 -> 69.908701 | L62: =(F62*15.2083)*U$34 -> 39.947829 | M62: =(F62*15.2083)*U$35 -> 79.895658 | N62: =(F62*15.2083)*U$36 -> 125.83566 | O62: =(F62*15.2083)*U$37 -> 199.73915 | P62: =(F62*15.2083)*U$40 -> 185.88724 | Q62: =SUM(G62:P62) -> 1107.9606
A63: =A42 -> Auxiliar de limpieza | B63: =B42 -> 5 | C63: 45158 | D63: =E42 -> 248.93 | E63: =F42 -> 3785.8021 | F63: =K42 -> 261.206 | G63: =(U$25*15.2083)*U$29 -> 336.83769 | H63: 0 | I63: =(F63*15.2083)*U$31 -> 27.807494 | J63: =(F63*15.2083)*U$32 -> 41.711242 | K63: =(F63*15.2083)*U$33 -> 69.518736 | L63: =(F63*15.2083)*U$34 -> 39.724992 | M63: =(F63*15.2083)*U$35 -> 79.449984 | N63: =(F63*15.2083)*U$36 -> 125.13373 | O63: =(F63*15.2083)*U$37 -> 198.62496 | P63: =(F63*15.2083)*U$40 -> 184.85032 | Q63: =SUM(G63:P63) -> 1103.6591
G64: =SUM(G49:G63) -> 5052.5653 | H64: =SUM(H49:H63) -> 214.57331 | I64: =SUM(I49:I63) -> 627.35424 | J64: =SUM(J49:J63) -> 941.03135 | K64: =SUM(K49:K63) -> 1568.3856 | L64: =SUM(L49:L63) -> 896.22034 | M64: =SUM(M49:M63) -> 1792.4407 | N64: =SUM(N49:N63) -> 2823.0941 | ... Q64: =SUM(Q49:Q63) -> 22567.104
A65: Deducción de Cuotas Obrero por trabajador
A67: =A27 -> Puesto | B67: =B27 -> Nivel | C67: =C27 -> Fecha de ingreso | D67: =E27 -> Salario Base | E67: =K27 -> SBC | F67: =L27 -> SBC*15 | G67: Prestaciones en dinero | H67: Gastos medicos pensionados | I67: Cuota adicional por la diferencia del SBC y de tres veces la UMA | J67: Invalidez y vida | K67: Cesantia y vejez | L67: Total | N67: Salario Nominal | O67: Porcentaje de ISN | P67: ISN a Pagar | S67: SBC | T67: Porcentaje de INFONAVIT | U67: INFONAVIT a Pagar
A68: =A28 -> Gerente general | B68: =B28 -> 1 | C68: 43160 | D68: =E28 -> 550 | E68: =K28 -> 580.13699 | F68: =L28 -> 8822.8973 | G68: =F68*U$43 -> 22.057243 | H68: =F68*U$44 -> 33.085865 | I68: =((E68-U$26)*15.2083)*U$45 -> 15.477608 | J68: =F68*U$46 -> 55.143108 | K68: =F68*U$47 -> 99.257595 | L68: =SUM(G68:K68) -> 225.02142 | N68: =E4 -> 550 | O68: 0.03 | P68: =N68*O68 -> 16.5 | S68: =F49 -> 580.13699 | T68: 0.05 | U68: =S68*T68 -> 29.006849
A69: =A29 -> Gerente de restaurante | B69: =B29 -> 2 | C69: 44274 | D69: =E29 -> 500 | E69: =K29 -> 526.0274 | F69: =L29 -> 7999.9825 | G69: =F69*U$43 -> 19.999956 | H69: =F69*U$44 -> 29.999934 | I69: =((E69-U$26)*15.2083)*U$45 -> 12.185948 | J69: =F69*U$46 -> 49.99989 | K69: =F69*U$47 -> 89.999803 | L69: =SUM(G69:K69) -> 202.18553 | N69: =E5 -> 500 | O69: 0.03 | P69: =N69*O69 -> 15 | S69: =F50 -> 526.0274 | T69: 0.05 | U69: =S69*T69 -> 26.30137
A70: =A30 -> Gerente de producción | B70: =B30 -> 2 | C70: 44862 | D70: =E30 -> 520 | E70: =K30 -> 546.35616 | F70: =L30 -> 8309.1485 | G70: =F70*U$43 -> 20.772871 | H70: =F70*U$44 -> 31.159307 | I70: =((E70-U$26)*15.2083)*U$45 -> 13.422612 | J70: =F70*U$46 -> 51.932178 | K70: =F70*U$47 -> 93.47792 | L70: =SUM(G70:K70) -> 210.76489 | N70: =E6 -> 520 | O70: 0.03 | P70: =N70*O70 -> 15.6 | S70: =F51 -> 546.35616 | T70: 0.05 | U70: =S70*T70 -> 27.317808
A71: =A31 -> Gerente de ventas | B71: =B31 -> 2 | C71: 45260 | D71: =E31 -> 520 | E71: =K31 -> 545.64384 | F71: =L31 -> 8298.3151 | G71: =F71*U$43 -> 20.745788 | H71: =F71*U$44 -> 31.118682 | I71: =((E71-U$26)*15.2083)*U$45 -> 13.379279 | J71: =F71*U$46 -> 51.86447 | K71: =F71*U$47 -> 93.356045 | L71: =SUM(G71:K71) -> 210.46426 | N71: =E7 -> 520 | O71: 0.03 | P71: =N71*O71 -> 15.6 | S71: =F52 -> 545.64384 | T71: 0.05 | U71: =S71*T71 -> 27.282192
A72: =A32 -> Gerente de finanzas | B72: =B32 -> 2 | C72: 45061 | D72: =E32 -> 400 | E72: =K32 -> 419.72603 | F72: =L32 -> 6383.3193 | G72: =F72*U$43 -> 15.958298 | H72: =F72*U$44 -> 23.937448 | I72: =((E72-U$26)*15.2083)*U$45 -> 5.7192958 | J72: =F72*U$46 -> 39.895746 | K72: =F72*U$47 -> 71.812343 | L72: =SUM(G72:K72) -> 157.32313 | N72: =E8 -> 400 | O72: 0.03 | P72: =N72*O72 -> 12 | S72: =F53 -> 419.72603 | T72: 0.05 | U72: =S72*T72 -> 20.986301
A73: =A33 -> Encargado de mantenimiento | B73: =B33 -> 3 | C73: 44315 | D73: =E33 -> 380 | E73: =K33 -> 399.78082 | F73: =L33 -> 6079.9867 | G73: =F73*U$43 -> 15.199967 | H73: =F73*U$44 -> 22.79995 | I73: =((E73-U$26)*15.2083)*U$45 -> 4.5059651 | J73: =F73*U$46 -> 37.999917 | K73: =F73*U$47 -> 68.39985 | L73: =SUM(G73:K73) -> 148.90565 | N73: =E9 -> 380 | O73: 0.03 | P73: =N73*O73 -> 11.4 | S73: =F54 -> 399.78082 | T73: 0.05 | U73: =S73*T73 -> 19.989041
A74: =A34 -> Encargado de almacen | B74: =B34 -> 3 | C74: 44239 | D74: =E34 -> 380 | E74: =K34 -> 399.78082 | F74: =L34 -> 6079.9867 | G74: =F74*U$43 -> 15.199967 | H74: =F74*U$44 -> 22.79995 | I74: =((E74-U$26)*15.2083)*U$45 -> 4.5059651 | J74: =F74*U$46 -> 37.999917 | K74: =F74*U$47 -> 68.39985 | L74: =SUM(G74:K74) -> 148.90565 | N74: =E10 -> 380 | O74: 0.03 | P74: =N74*O74 -> 11.4 | S74: =F55 -> 399.78082 | T74: 0.05 | U74: =S74*T74 -> 19.989041
A75: =A35 -> Jefe de cocina | B75: =B35 -> 3 | C75: 44247 | D75: =E35 -> 380 | E75: =K35 -> 399.78082 | F75: =L35 -> 6079.9867 | G75: =F75*U$43 -> 15.199967 | H75: =F75*U$44 -> 22.79995 | I75: =((E75-U$26)*15.2083)*U$45 -> 4.5059651 | J75: =F75*U$46 -> 37.999917 | K75: =F75*U$47 -> 68.39985 | L75: =SUM(G75:K75) -> 148.90565 | N75: =E11 -> 380 | O75: 0.03 | P75: =N75*O75 -> 11.4 | S75: =F56 -> 399.78082 | T75: 0.05 | U75: =S75*T75 -> 19.989041
A76: =A36 -> Relaciones públicas | B76: =B36 -> 3 | C76: 43855 | D76: =E36 -> 376.66667 | E76: =K36 -> 396.78995 | F76: =L36 -> 6034.5007 | G76: =F76*U$43 -> 15.086252 | H76: =F76*U$44 -> 22.629377 | I76: =((E76-U$26)*15.2083)*U$45 -> 4.3240211 | J76: =F76*U$46 -> 37.715629 | K76: =F76*U$47 -> 67.888132 | L76: =SUM(G76:K76) -> 147.64341 | N76: =E12 -> 376.66667 | O76: 0.03 | P76: =N76*O76 -> 11.3 | S76: =F57 -> 396.78995 | T76: 0.05 | U76: =S76*T76 -> 19.839498
A77: =A37 -> Maestro cervecero | B77: =B37 -> 3 | C77: 45029 | D77: =E37 -> 300 | E77: =K37 -> 314.79452 | F77: =L37 -> 4787.4895 | G77: =F77*U$43 -> 11.968724 | H77: =F77*U$44 -> 17.953086 | I77: 0 | J77: =F77*U$46 -> 29.921809 | K77: =F77*U$47 -> 53.859257 | L77: =SUM(G77:K77) -> 113.70288 | N77: =E13 -> 300 | O77: 0.03 | P77: =N77*O77 -> 9 | S77: =F58 -> 314.79452 | T77: 0.05 | U77: =S77*T77 -> 15.739726
A78: =A38 -> Auxiliar Contador | B78: =B38 -> 3 | C78: 44226 | D78: =E38 -> 300 | E78: =K38 -> 315.61644 | F78: =L38 -> 4799.9895 | G78: =F78*U$43 -> 11.999974 | H78: =F78*U$44 -> 17.999961 | I78: 0 | J78: =F78*U$46 -> 29.999934 | K78: =F78*U$47 -> 53.999882 | L78: =SUM(G78:K78) -> 113.99975 | N78: =E14 -> 300 | O78: 0.03 | P78: =N78*O78 -> 9 | S78: =F59 -> 315.61644 | T78: 0.05 | U78: =S78*T78 -> 15.780822
A79: =A39 -> Auxiliar de produccion | B79: =B39 -> 4 | C79: 45158 | D79: =E39 -> 250 | E79: =K39 -> 262.32877 | F79: =L39 -> 3989.5746 | G79: =F79*U$43 -> 9.9739365 | H79: =F79*U$44 -> 14.960905 | I79: 0 | J79: =F79*U$46 -> 24.934841 | K79: =F79*U$47 -> 44.882714 | L79: =SUM(G79:K79) -> 94.752396 | N79: =E15 -> 250 | O79: 0.03 | P79: =N79*O79 -> 7.5 | S79: =F60 -> 262.32877 | T79: 0.05 | U79: =S79*T79 -> 13.116438
A80: =A40 -> Meseros | B80: =B40 -> 4 | C80: 45260 | D80: =E40 -> 250 | E80: =K40 -> 262.32877 | F80: =L40 -> 3989.5746 | G80: =F80*U$43 -> 9.9739365 | H80: =F80*U$44 -> 14.960905 | I80: 0 | J80: =F80*U$46 -> 24.934841 | K80: =F80*U$47 -> 44.882714 | L80: =SUM(G80:K80) -> 94.752396 | N80: =E16 -> 250 | O80: 0.03 | P80: =N80*O80 -> 7.5 | S80: =F61 -> 262.32877 | T80: 0.05 | U80: =S80*T80 -> 13.116438
A81: =A41 -> Cocineros | B81: =B41 -> 4 | C81: 44862 | D81: =E41 -> 250 | E81: =K41 -> 262.67123 | F81: =L41 -> 3994.7829 | G81: =F81*U$43 -> 9.9869573 | H81: =F81*U$44 -> 14.980436 | I81: 0 | J81: =F81*U$46 -> 24.967393 | K81: =F81*U$47 -> 44.941308 | L81: =SUM(G81:K81) -> 94.876094 | N81: =E17 -> 250 | O81: 0.03 | P81: =N81*O81 -> 7.5 | S81: =F62 -> 262.67123 | T81: 0.05 | U81: =S81*T81 -> 13.133562
A82: =A42 -> Auxiliar de limpieza | B82: =B42 -> 5 | C82: 45158 | D82: =E42 -> 248.93 | E82: =K42 -> 261.206 | F82: =L42 -> 3972.4992 | G82: =F82*U$43 -> 9.931248 | H82: =F82*U$44 -> 14.896872 | I82: 0 | J82: =F82*U$46 -> 24.82812 | K82: =F82*U$47 -> 44.690616 | L82: =SUM(G82:K82) -> 94.346856 | N82: =E18 -> 248.93 | O82: 0.03 | P82: =N82*O82 -> 7.4679 | S82: =F63 -> 261.206 | T82: 0.05 | U82: =S82*T82 -> 13.0603
G83: =SUM(G68:G82) -> 224.05508 | H83: =SUM(H68:H82) -> 336.08263 | I83: =SUM(I68:I82) -> 78.02666 | J83: =SUM(J68:J82) -> 560.13771 | K83: =SUM(K68:K82) -> 1008.2479 | L83: =SUM(L68:L82) -> 2206.55
A84: Deducción de ISR por trabajador
O85: Tárifas ISR 2024
A86: =A27 -> Puesto | B86: =B27 -> Nivel | C86: =C27 -> Fecha de ingreso | D86: =E27 -> Salario Base | E86: =F27 -> Salario Quincenal | F86: Límite inferior | G86: Excedente de % | H86: Tasa de ISR | I86: ISR excedente | J86: Cuota fija | K86: ISR determinado | L86: Subsidio al empleo | M86: ISR a retener | O86: Límite inferior | P86: Límite superior | Q86: Cuota Fija | R86: % sobre el excedente del límite inferior
A87: =A28 -> Gerente general | B87: =B28 -> 1 | C87: 43160 | D87: =E28 -> 550 | E87: =F28 -> 8364.565 | F87: =O92 -> 7641.91 | G87: =E87-F87 -> 722.655 | H87: =R92 -> 0.2136 | I87: =G87*H87 -> 154.35911 | J87: =Q92 -> 809.25 | K87: =I87+J87 -> 963.60911 | L87: 0 | M87: =K87-L87 -> 963.60911 | O87: 0.01 | P87: 368.1 | Q87: 0 | R87: 0.0192
A88: =A29 -> Gerente de restaurante | B88: =B29 -> 2 | C88: 44274 | D88: =E29 -> 500 | E88: =F29 -> 7604.15 | F88: =O92 -> 7641.91 | G88: =E88-F88 -> -37.76 | H88: =R92 -> 0.2136 | I88: =G88*H88 -> -8.065536 | J88: =Q92 -> 809.25 | K88: =I88+J88 -> 801.18446 | L88: 0 | M88: =K88-L88 -> 801.18446 | O88: 368.11 | P88: 3124.35 | Q88: 7.05 | R88: 0.064
A89: =A30 -> Gerente de producción | B89: =B30 -> 2 | C89: 44862 | D89: =E30 -> 520 | E89: =F30 -> 7908.316 | F89: =O92 -> 7641.91 | G89: =E89-F89 -> 266.406 | H89: =R92 -> 0.2136 | I89: =G89*H89 -> 56.904322 | J89: =Q92 -> 809.25 | K89: =I89+J89 -> 866.15432 | L89: 0 | M89: =K89-L89 -> 866.15432 | O89: 3124.36 | P89: 5490.75 | Q89: 183.45 | R89: 0.1088
A90: =A31 -> Gerente de ventas | B90: =B31 -> 2 | C90: 45260 | D90: =E31 -> 520 | E90: =F31 -> 7908.316 | F90: =O92 -> 7641.91 | G90: =E90-F90 -> 266.406 | H90: =R92 -> 0.2136 | I90: =G90*H90 -> 56.904322 | J90: =Q92 -> 809.25 | K90: =I90+J90 -> 866.15432 | L90: 0 | M90: =K90-L90 -> 866.15432 | O90: 5490.76 | P90: 6382.8 | Q90: 441 | R90: 0.16
A91: =A32 -> Gerente de finanzas | B91: =B32 -> 2 | C91: 45061 | D91: =E32 -> 400 | E91: =F32 -> 6083.32 | F91: =O90 -> 5490.76 | G91: =E91-F91 -> 592.56 | H91: =R90 -> 0.16 | I91: =G91*H91 -> 94.8096 | J91: =Q90 -> 441 | K91: =I91+J91 -> 535.8096 | L91: 0 | M91: =K91-L91 -> 535.8096 | O91: 6382.81 | P91: 7641.9 | Q91: 583.65 | R91: 0.1792
A92: =A33 -> Encargado de mantenimiento | B92: =B33 -> 3 | C92: 44315 | D92: =E33 -> 380 | E92: =F33 -> 5779.154 | F92: =O90 -> 5490.76 | G92: =E92-F92 -> 288.394 | H92: =R90 -> 0.16 | I92: =G92*H92 -> 46.14304 | J92: =Q90 -> 441 | K92: =I92+J92 -> 487.14304 | L92: 0 | M92: =K92-L92 -> 487.14304 | O92: 7641.91 | P92: 15412.8 | Q92: 809.25 | R92: 0.2136
A93: =A34 -> Encargado de almacen | B93: =B34 -> 3 | C93: 44239 | D93: =E34 -> 380 | E93: =F34 -> 5779.154 | F93: =O90 -> 5490.76 | G93: =E93-F93 -> 288.394 | H93: =R90 -> 0.16 | I93: =G93*H93 -> 46.14304 | J93: =Q90 -> 441 | K93: =I93+J93 -> 487.14304 | L93: 0 | M93: =K93-L93 -> 487.14304
A94: =A35 -> Jefe de cocina | B94: =B35 -> 3 | C94: 44247 | D94: =E35 -> 380 | E94: =F35 -> 5779.154 | F94: =O90 -> 5490.76 | G94: =E94-F94 -> 288.394 | H94: =R90 -> 0.16 | I94: =G94*H94 -> 46.14304 | J94: =Q90 -> 441 | K94: =I94+J94 -> 487.14304 | L94: 0 | M94: =K94-L94 -> 487.14304 | O94: Subsidio para el empleo
A95: =A36 -> Relaciones públicas | B95: =B36 -> 3 | C95: 43855 | D95: =E36 -> 376.66667 | E95: =F36 -> 5728.4597 | F95: =O90 -> 5490.76 | G95: =E95-F95 -> 237.69967 | H95: =R90 -> 0.16 | I95: =G95*H95 -> 38.031947 | J95: =Q90 -> 441 | K95: =I95+J95 -> 479.03195 | L95: 0 | M95: =K95-L95 -> 479.03195 | O95: UMA 2024 | P95: 108.57
A96: =A37 -> Maestro cervecero | B96: =B37 -> 3 | C96: 45029 | D96: =E37 -> 300 | E96: =F37 -> 4562.49 | F96: =O89 -> 3124.36 | G96: =E96-F96 -> 1438.13 | H96: =R89 -> 0.1088 | I96: =G96*H96 -> 156.46854 | J96: =Q89 -> 183.45 | K96: =I96+J96 -> 339.91854 | L96: =P$97*15 -> 192.49461 | M96: =K96-L96 -> 147.42393 | O96: %Del decreto | P96: 0.1182
A97: =A38 -> Auxiliar Contador | B97: =B38 -> 3 | C97: 44226 | D97: =E38 -> 300 | E97: =F38 -> 4562.49 | F97: =O89 -> 3124.36 | G97: =E97-F97 -> 1438.13 | H97: =R89 -> 0.1088 | I97: =G97*H97 -> 156.46854 | J97: =Q89 -> 183.45 | K97: =I97+J97 -> 339.91854 | L97: =P$97*15 -> 192.49461 | M97: =K97-L97 -> 147.42393 | O97: Subsidio diario | P97: 12.832974
A98: =A39 -> Auxiliar de produccion | B98: =B39 -> 4 | C98: 45158 | D98: =E39 -> 250 | E98: =F39 -> 3802.075 | F98: =O89 -> 3124.36 | G98: =E98-F98 -> 677.715 | H98: =R89 -> 0.1088 | I98: =G98*H98 -> 73.735392 | J98: =Q89 -> 183.45 | K98: =I98+J98 -> 257.18539 | L98: =P$97*15 -> 192.49461 | M98: =K98-L98 -> 64.690782 | O98: Subisidio MENSUAL | P98: 390.12241
A99: =A40 -> Meseros | B99: =B40 -> 4 | C99: 45260 | D99: =E40 -> 250 | E99: =F40 -> 3802.075 | F99: =O89 -> 3124.36 | G99: =E99-F99 -> 677.715 | H99: =R89 -> 0.1088 | I99: =G99*H99 -> 73.735392 | J99: =Q89 -> 183.45 | K99: =I99+J99 -> 257.18539 | L99: =P$97*15 -> 192.49461 | M99: =K99-L99 -> 64.690782
A100: =A41 -> Cocineros | B100: =B41 -> 4 | C100: 44862 | D100: =E41 -> 250 | E100: =F41 -> 3802.075 | F100: =O89 -> 3124.36 | G100: =E100-F100 -> 677.715 | H100: =R89 -> 0.1088 | I100: =G100*H100 -> 73.735392 | J100: =Q89 -> 183.45 | K100: =I100+J100 -> 257.18539 | L100: =P$97*15 -> 192.49461 | M100: =K100-L100 -> 64.690782
A101: =A42 -> Auxiliar de limpieza | B101: =B42 -> 5 | C101: 45158 | D101: =E42 -> 248.93 | E101: =F42 -> 3785.8021 | F101: =O89 -> 3124.36 | G101: =E101-F101 -> 661.44212 | H101: =R89 -> 0.1088 | I101: =G101*H101 -> 71.964903 | J101: =Q89 -> 183.45 | K101: =I101+J101 -> 255.4149 | L101: =P$97*15 -> 192.49461 | M101: =K101-L101 -> 62.920293
